Workbook
Name _INFOSYS: #REF!
Name _INFOSYSLTS: #REF!
Name Accrued_Liab_Pct: [2]Assumptions!$C$75
Name Bad_Debt_Pct: [2]Assumptions!$C$80
Name Benefits_Pct: [2]Assumptions!$C$55
Name Buyback: [2]Assumptions!$C$103
Name CASE: [1]LBO!$E$7
Name CIRC: [1]LBO!$E$6
Name Commit_Fee_Rate: [2]Assumptions!$C$89
Name Deferred_Rev_Pct: [2]Assumptions!$C$79
Name DIO: [2]Assumptions!$C$73
Name Dividend_Payout: [2]Assumptions!$C$99
Name DPO: [2]Assumptions!$C$74
Name DSCR_Floor: [2]Assumptions!$C$91
Name DSO: [2]Assumptions!$C$72
Name Employer_Tax_Pct: [2]Assumptions!$C$54
Name GA_FTE_Base: [2]Assumptions!$C$50
Name GA_FTE_Growth: [2]Assumptions!$C$52
Name GA_NonHead: [2]Assumptions!$C$53
Name GA_Salary: [2]Assumptions!$C$51
Name Growth_CapEx_Pct: [2]Assumptions!$F$67
Name Inflation: [2]Assumptions!$C$41
Name Insurance_Amount: [2]Assumptions!$C$60
Name Insurance_Esc: [2]Assumptions!$C$61
Name Int_Cov_Floor: [2]Assumptions!$C$93
Name Int_Income_Rate: [2]Assumptions!$C$94
Name IQ_CH: 110000
Name IQ_CQ: 5000
Name IQ_CY: 10000
Name IQ_DAILY: 500000
Name IQ_FH: 100000
Name IQ_FQ: 500
Name IQ_FY: 1000
Name IQ_LTM: 2000
Name IQ_MONTH: 15000
Name IQ_NTM: 6000
Name IQ_WEEK: 50000
Name IQ_YTD: 3000
Name Leverage_Ceil: [2]Assumptions!$C$92
Name Maint_CapEx_Pct: [2]Assumptions!$F$66
Name Min_Cash: [2]Assumptions!$C$90
Name Mktg_Pct: [2]Assumptions!$F$57
Name Model_Start_Year: [2]Assumptions!$C$10
Name New_Asset_Life: [2]Assumptions!$C$69
Name New_Debt_Draw: [2]Assumptions!$C$86
Name New_Issuance: [2]Assumptions!$C$102
Name NOL_Opening: [2]Assumptions!$C$98
Name Open_Acc_Depr: [2]Assumptions!$C$113
Name Open_Accrued: [2]Assumptions!$C$115
Name Open_AP: [2]Assumptions!$C$114
Name Open_AR: [2]Assumptions!$C$108
Name Open_Cash: [2]Assumptions!$C$107
Name Open_Deferred_Rev: [2]Assumptions!$C$116
Name Open_Inventory: [2]Assumptions!$C$109
Name Open_Other_CA: [2]Assumptions!$C$111
Name Open_Other_CL: [2]Assumptions!$C$117
Name Open_PPE_Gross: [2]Assumptions!$C$112
Name Open_Prepaid: [2]Assumptions!$C$110
Name Open_Ret_Earnings: [2]Assumptions!$C$123
Name Open_Share_Capital: [2]Assumptions!$C$119

Sheet Dashboard
B2: Dashboard
B3: Headline operating, profitability and cash outputs at a glance | D3: (Values in Crores)
B5: Key Performance Indicators
B6: Revenue | D6: Gross Profit | F6: EBITDA | H6: Net Income | J6: Revenue CAGR
B7: =' Forecasted FS>'!N9 -> 256609.29 | D7: =' Forecasted FS>'!N15 -> 68844.286 | F7: =' Forecasted FS>'!N21 -> 58578.857 | H7: =' Forecasted FS>'!N36 -> 35165.429 | J7: =' Forecasted FS>'!N10 -> 0.062184507
B9: Final year | D9: Final year | F9: Final year | H9: Final year | J9: Yr1-final
B10: Gross Margin | D10: EBITDA Margin | F10: Net Margin | H10: Cash from Ops | J10: Net Δ Cash
B11: =' Forecasted FS>'!N16 -> 0.26828447 | D11: =' Forecasted FS>'!N22 -> 0.22828035 | F11: =' Forecasted FS>'!N37 -> 0.1370388 | H11: =' Forecasted FS>'!N82 -> 49564.091 | J11: =' Forecasted FS>'!N103 -> 5090.482
B13: Final year | D13: Final year | F13: Final year | H13: Final year | J13: Final year
B15: Operating & Cash Flow Summary
B16: Metric | C16: =[2]Income_Statement!C6 -> 2026 | D16: =[2]Income_Statement!D6 -> 2027 | E16: =[2]Income_Statement!E6 -> 2028 | F16: =[2]Income_Statement!F6 -> 2029 | G16: =[2]Income_Statement!G6 -> 2030
B17: Total Revenue | C17: =' Forecasted FS>'!I9 -> 178650 | D17: =' Forecasted FS>'!J9 -> 196517.57 | E17: =' Forecasted FS>'!K9 -> 211540.5 | F17: =' Forecasted FS>'!L9 -> 226563.43 | G17: =' Forecasted FS>'!M9 -> 241586.36
B18: Gross Profit | C18: =' Forecasted FS>'!I15 -> 50393 | D18: =' Forecasted FS>'!J15 -> 54401.429 | E18: =' Forecasted FS>'!K15 -> 58012.143 | F18: =' Forecasted FS>'!L15 -> 61622.857 | G18: =' Forecasted FS>'!M15 -> 65233.571
B19: EBITDA | C19: =' Forecasted FS>'!I21 -> 42280 | D19: =' Forecasted FS>'!J21 -> 46055 | E19: =' Forecasted FS>'!K21 -> 49185.964 | F19: =' Forecasted FS>'!L21 -> 52316.929 | G19: =' Forecasted FS>'!M21 -> 55447.893
B20: Net Income | C20: =' Forecasted FS>'!I36 -> 26441 | D20: =' Forecasted FS>'!J36 -> 27828.714 | E20: =' Forecasted FS>'!K36 -> 29662.893 | F20: =' Forecasted FS>'!L36 -> 31497.071 | G20: =' Forecasted FS>'!M36 -> 33331.25
B21: Net Margin % | C21: =' Forecasted FS>'!I37 -> 0.14800448 | D21: =' Forecasted FS>'!J37 -> 0.14160929 | E21: =' Forecasted FS>'!K37 -> 0.14022323 | F21: =' Forecasted FS>'!L37 -> 0.13902099 | G21: =' Forecasted FS>'!M37 -> 0.13796826
B22: Cash from Operations | C22: =' Forecasted FS>'!I82 -> 33986 | D22: =' Forecasted FS>'!J82 -> 36954.714 | E22: =' Forecasted FS>'!K82 -> 39434.551 | F22: =' Forecasted FS>'!L82 -> 43147.335 | G22: =' Forecasted FS>'!M82 -> 46949.203
B23: Capital Expenditure | C23: =' Forecasted FS>'!I85 -> -2727 | D23: =' Forecasted FS>'!J85 -> -2268.4286 | E23: =' Forecasted FS>'!K85 -> -2507.8163 | F23: =' Forecasted FS>'!L85 -> -2518.0787 | G23: =' Forecasted FS>'!M85 -> -2500.0887
B25: Trend Charts
B39: Revenue Mix (helper
B40: Segment 1 | C40: =[2]Income_Statement!C9 -> 56000000 | D40: =[2]Income_Statement!D9 -> 61600000
B80: Revenue -> Net Income Bridge (final year
B98: Waterfall Chart Data (helper)
B100: Revenue | C100: =0 -> 0 | D100: =' Forecasted FS>'!N9 -> 256609.29
B101: Less: COGS | C101: =D102 -> 68844.286 | D101: =' Forecasted FS>'!N12 -> 187765
B102: Gross Profit | C102: =0 -> 0 | D102: =D100-D101 -> 68844.286
B103: Less: OpEx | C103: =D104 -> 58578.857 | D103: =' Forecasted FS>'!N15-' Forecasted FS>'!N21 -> 10265.429
B104: EBITDA | C104: =0 -> 0 | D104: =D102-D103 -> 58578.857
B105: Less: D&A/Int/Tax | C105: =D106 -> 35165.429 | D105: =' Forecasted FS>'!N21-' Forecasted FS>'!N36 -> 23413.429
B106: Net Income | C106: =0 -> 0 | D106: =D104-D105 -> 35165.429

Sheet  Forecasted FS>
B2: In Crores(Cr.)
B4: ="Historical Financial Statements - "& 'Raw Data Sheet'!B1 -> Historical Financial Statements - INFOSYS LTD
B5: Years | C5: ='Raw Data Sheet'!E16 -> 43921 | D5: =C5+365 -> 44286 | E5: =D5+365 -> 44651 | F5: =E5+365 -> 45016 | G5: =F5+365 -> 45381 | H5: =G5+365 -> 45746 | I5: =H5+365 -> 46111 | J5: =I5+365 -> 46476 | K5: =J5+365 -> 46841 | ... N5: =M5+365 -> 47936
B6: Year Weights | C6: 1 | D6: 2 | E6: 3 | F6: 4 | G6: 5 | H6: 6 | I6: 7 | J6: 8 | K6: 9 | L6: 10 | M6: 11 | N6: 12
A8: # | B8: Income Statement
B9: Sales | C9: =IFERROR('Raw Data Sheet'!E17,0) -> 90791 | D9: =IFERROR('Raw Data Sheet'!F17,0) -> 100472 | E9: =IFERROR('Raw Data Sheet'!G17,0) -> 121641 | F9: =IFERROR('Raw Data Sheet'!H17,0) -> 146767 | G9: =IFERROR('Raw Data Sheet'!I17,0) -> 153670 | H9: =IFERROR('Raw Data Sheet'!J17,0) -> 162990 | I9: =IFERROR('Raw Data Sheet'!K17,0) -> 178650 | J9: =FORECAST(J6,$C$9:$I$9,$C$6:$I$6) -> 196517.57 | K9: =FORECAST(K6,$C$9:$I$9,$C$6:$I$6) -> 211540.5 | L9: =FORECAST(L6,$C$9:$I$9,$C$6:$I$6) -> 226563.43 | M9: =FORECAST(M6,$C$9:$I$9,$C$6:$I$6) -> 241586.36 | N9: =FORECAST(N6,$C$9:$I$9,$C$6:$I$6) -> 256609.29
B10: Sales Growth | C10: - | D10: =D9/C9-1 -> 0.10662951 | E10: =E9/D9-1 -> 0.21069552 | F10: =F9/E9-1 -> 0.20655864 | G10: =G9/F9-1 -> 0.047033734 | H10: =H9/G9-1 -> 0.060649444 | I10: =I9/H9-1 -> 0.096079514 | J10: =J9/I9-1 -> 0.10001439 | K10: =K9/J9-1 -> 0.076445727 | ... N10: =N9/M9-1 -> 0.062184507
B12: COGS | C12: =IFERROR(SUM('Raw Data Sheet'!E20:E22)-1*'Raw Data Sheet'!E19,0) -> 62210 | D12: =IFERROR(SUM('Raw Data Sheet'!F20:F22)-1*'Raw Data Sheet'!F19,0) -> 68490 | E12: =IFERROR(SUM('Raw Data Sheet'!G20:G22)-1*'Raw Data Sheet'!G19,0) -> 84819 | F12: =IFERROR(SUM('Raw Data Sheet'!H20:H22)-1*'Raw Data Sheet'!H19,0) -> 104880 | G12: =IFERROR(SUM('Raw Data Sheet'!I20:I22)-1*'Raw Data Sheet'!I19,0) -> 110030 | H12: =IFERROR(SUM('Raw Data Sheet'!J20:J22)-1*'Raw Data Sheet'!J19,0) -> 116585 | I12: =IFERROR(SUM('Raw Data Sheet'!K20:K22)-1*'Raw Data Sheet'!K19,0) -> 128257 | J12: =FORECAST(J6,$C$12:$I$12,$C$6:$I$6) -> 142116.14 | K12: =FORECAST(K6,$C$12:$I$12,$C$6:$I$6) -> 153528.36 | L12: =FORECAST(L6,$C$12:$I$12,$C$6:$I$6) -> 164940.57 | M12: =FORECAST(M6,$C$12:$I$12,$C$6:$I$6) -> 176352.79 | N12: =FORECAST(N6,$C$12:$I$12,$C$6:$I$6) -> 187765
B13: COGS % of sales | C13: =C12/C9 -> 0.68520007 | D13: =D12/D9 -> 0.68168246 | E13: =E12/E9 -> 0.69728957 | F13: =F12/F9 -> 0.71460206 | G13: =G12/G9 -> 0.71601484 | H13: =H12/H9 -> 0.71528928 | I13: =I12/I9 -> 0.71792331 | J13: =J12/J9 -> 0.7231727 | ... N13: =N12/N9 -> 0.73171553
B15: Gross Profit | C15: =C9-C12 -> 28581 | D15: =D9-D12 -> 31982 | E15: =E9-E12 -> 36822 | F15: =F9-F12 -> 41887 | G15: =G9-G12 -> 43640 | H15: =H9-H12 -> 46405 | I15: =I9-I12 -> 50393 | J15: =J9-J12 -> 54401.429 | ... N15: =N9-N12 -> 68844.286
B16: GP % of sales | C16: =C15/C9 -> 0.31479993 | D16: =D15/D9 -> 0.31831754 | E16: =E15/E9 -> 0.30271043 | F16: =F15/F9 -> 0.28539794 | G16: =G15/G9 -> 0.28398516 | H16: =H15/H9 -> 0.28471072 | I16: =I15/I9 -> 0.28207669 | J16: =J15/J9 -> 0.2768273 | ... N16: =N15/N9 -> 0.26828447
B18: Selling & General Expenses | C18: =IFERROR(SUM('Raw Data Sheet'!E23:E24),0) -> 6314 | D18: =IFERROR(SUM('Raw Data Sheet'!F23:F24),0) -> 4093 | E18: =IFERROR(SUM('Raw Data Sheet'!G23:G24),0) -> 5331 | F18: =IFERROR(SUM('Raw Data Sheet'!H23:H24),0) -> 6757 | G18: =IFERROR(SUM('Raw Data Sheet'!I23:I24),0) -> 7215 | H18: =IFERROR(SUM('Raw Data Sheet'!J23:J24),0) -> 7169 | I18: =IFERROR(SUM('Raw Data Sheet'!K23:K24),0) -> 8113 | J18: =FORECAST(J6,$C$18:$I$18,$C$6:$I$6) -> 8346.4286 | K18: =FORECAST(K6,$C$18:$I$18,$C$6:$I$6) -> 8826.1786 | L18: =FORECAST(L6,$C$18:$I$18,$C$6:$I$6) -> 9305.9286 | M18: =FORECAST(M6,$C$18:$I$18,$C$6:$I$6) -> 9785.6786 | N18: =FORECAST(N6,$C$18:$I$18,$C$6:$I$6) -> 10265.429
B19: S&G Exp % of sales | C19: =C18/C9 -> 0.069544338 | D19: =D18/D9 -> 0.040737718 | E19: =E18/E9 -> 0.043825684 | F19: =F18/F9 -> 0.04603896 | G19: =G18/G9 -> 0.046951259 | H19: =H18/H9 -> 0.043984294 | I19: =I18/I9 -> 0.045412818 | J19: =J18/J9 -> 0.042471666 | ... N19: =N18/N9 -> 0.04000412
B21: EBITDA | C21: =C15-C18 -> 22267 | D21: =D15-D18 -> 27889 | E21: =E15-E18 -> 31491 | F21: =F15-F18 -> 35130 | G21: =G15-G18 -> 36425 | H21: =H15-H18 -> 39236 | I21: =I15-I18 -> 42280 | J21: =J15-J18 -> 46055 | ... N21: =N15-N18 -> 58578.857
B22: EBITDA % OF SALES | C22: =C21/C9 -> 0.24525559 | D22: =D21/D9 -> 0.27757982 | E22: =E21/E9 -> 0.25888475 | F22: =F21/F9 -> 0.23935898 | G22: =G21/G9 -> 0.2370339 | H22: =H21/H9 -> 0.24072642 | I22: =I21/I9 -> 0.23666387 | J22: =J21/J9 -> 0.23435563 | ... N22: =N21/N9 -> 0.22828035
B24: Interest | C24: =IFERROR('Raw Data Sheet'!E27,0) -> 170 | D24: =IFERROR('Raw Data Sheet'!F27,0) -> 195 | E24: =IFERROR('Raw Data Sheet'!G27,0) -> 200 | F24: =IFERROR('Raw Data Sheet'!H27,0) -> 284 | G24: =IFERROR('Raw Data Sheet'!I27,0) -> 470 | H24: =IFERROR('Raw Data Sheet'!J27,0) -> 416 | I24: =IFERROR('Raw Data Sheet'!K27,0) -> 416 | J24: =FORECAST(J6,$C$24:$I$24,$C$6:$I$6) -> 514.42857 | K24: =FORECAST(K6,$C$24:$I$24,$C$6:$I$6) -> 566.21429 | L24: =FORECAST(L6,$C$24:$I$24,$C$6:$I$6) -> 618 | M24: =FORECAST(M6,$C$24:$I$24,$C$6:$I$6) -> 669.78571 | N24: =FORECAST(N6,$C$24:$I$24,$C$6:$I$6) -> 721.57143
B25: Interest % of sales | C25: =C24/C9 -> 0.0018724323 | D25: =D24/D9 -> 0.0019408392 | E25: =E24/E9 -> 0.0016441825 | F25: =F24/F9 -> 0.0019350399 | G25: =G24/G9 -> 0.003058502 | H25: =H24/H9 -> 0.0025523038 | I25: =I24/I9 -> 0.0023285754 | J25: =J24/J9 -> 0.002617723 | ... N25: =N24/N9 -> 0.0028119459
B27: Depreciation | C27: =IFERROR('Raw Data Sheet'!E26,0) -> 2893 | D27: =IFERROR('Raw Data Sheet'!F26,0) -> 3267 | E27: =IFERROR('Raw Data Sheet'!G26,0) -> 3476 | F27: =IFERROR('Raw Data Sheet'!H26,0) -> 4225 | G27: =IFERROR('Raw Data Sheet'!I26,0) -> 4678 | H27: =IFERROR('Raw Data Sheet'!J26,0) -> 4812 | I27: =IFERROR('Raw Data Sheet'!K26,0) -> 4902 | J27: =FORECAST(J6,$C$27:$I$27,$C$6:$I$6) -> 5510.2857 | K27: =FORECAST(K6,$C$27:$I$27,$C$6:$I$6) -> 5878.8214 | L27: =FORECAST(L6,$C$27:$I$27,$C$6:$I$6) -> 6247.3571 | M27: =FORECAST(M6,$C$27:$I$27,$C$6:$I$6) -> 6615.8929 | N27: =FORECAST(N6,$C$27:$I$27,$C$6:$I$6) -> 6984.4286
B28: Dep % of sales | C28: =C27/C9 -> 0.031864392 | D28: =D27/D9 -> 0.032516522 | E28: =E27/E9 -> 0.028575891 | F28: =F27/F9 -> 0.028787125 | G28: =G27/G9 -> 0.030441856 | H28: =H27/H9 -> 0.029523284 | I28: =I27/I9 -> 0.027439127 | J28: =J27/J9 -> 0.028039659 | ... N28: =N27/N9 -> 0.027218144
B30: Earnings before Tax | C30: =C21-SUM(C24+C27) -> 19204 | D30: =D21-SUM(D24+D27) -> 24427 | E30: =E21-SUM(E24+E27) -> 27815 | F30: =F21-SUM(F24+F27) -> 30621 | G30: =G21-SUM(G24+G27) -> 31277 | H30: =H21-SUM(H24+H27) -> 34008 | I30: =I21-SUM(I24+I27) -> 36962 | J30: =J21-SUM(J24+J27) -> 40030.286 | ... N30: =N21-SUM(N24+N27) -> 50872.857
B31: EBT % of sales | C31: =C30/C9 -> 0.21151876 | D31: =D30/D9 -> 0.24312246 | E31: =E30/E9 -> 0.22866468 | F31: =F30/F9 -> 0.20863682 | G31: =G30/G9 -> 0.20353355 | H31: =H30/H9 -> 0.20865084 | I31: =I30/I9 -> 0.20689617 | J31: =J30/J9 -> 0.20369825 | ... N31: =N30/N9 -> 0.19825026
B33: Tax | C33: =IFERROR('Raw Data Sheet'!E29,0) -> 5368 | D33: =IFERROR('Raw Data Sheet'!F29,0) -> 7205 | E33: =IFERROR('Raw Data Sheet'!G29,0) -> 7964 | F33: =IFERROR('Raw Data Sheet'!H29,0) -> 9214 | G33: =IFERROR('Raw Data Sheet'!I29,0) -> 9740 | H33: =IFERROR('Raw Data Sheet'!J29,0) -> 10858 | I33: =IFERROR('Raw Data Sheet'!K29,0) -> 10521 | J33: =FORECAST(J6,$C$33:$I$33,$C$6:$I$6) -> 12201.571 | K33: =FORECAST(K6,$C$33:$I$33,$C$6:$I$6) -> 13078.036 | L33: =FORECAST(L6,$C$33:$I$33,$C$6:$I$6) -> 13954.5 | M33: =FORECAST(M6,$C$33:$I$33,$C$6:$I$6) -> 14830.964 | N33: =FORECAST(N6,$C$33:$I$33,$C$6:$I$6) -> 15707.429
B34: Effective tax rate | C34: =C33/C30 -> 0.2795251 | D34: =D33/D30 -> 0.29496049 | E34: =E33/E30 -> 0.28632033 | F34: =F33/F30 -> 0.30090461 | G34: =G33/G30 -> 0.31141094 | H34: =H33/H30 -> 0.31927782 | I34: =I33/I30 -> 0.28464369 | J34: =J33/J30 -> 0.3048085 | ... N34: =N33/N30 -> 0.30875853
B36: Net profit | C36: =C30-C33 -> 13836 | D36: =D30-D33 -> 17222 | E36: =E30-E33 -> 19851 | F36: =F30-F33 -> 21407 | G36: =G30-G33 -> 21537 | H36: =H30-H33 -> 23150 | I36: =I30-I33 -> 26441 | J36: =J30-J33 -> 27828.714 | ... N36: =N30-N33 -> 35165.429
B37: Net Margin | C37: =C36/C9 -> 0.15239396 | D37: =D36/D9 -> 0.17141094 | E37: =E36/E9 -> 0.16319333 | F37: =F36/F9 -> 0.14585704 | G37: =G36/G9 -> 0.14015097 | H37: =H36/H9 -> 0.14203325 | I37: =I36/I9 -> 0.14800448 | J37: =J36/J9 -> 0.14160929 | ... N37: =N36/N9 -> 0.1370388
B39: No. of Equity Shares | C39: =IFERROR('Raw Data Sheet'!E93,0) -> 425.9 | D39: =IFERROR('Raw Data Sheet'!F93,0) -> 426.07 | E39: =IFERROR('Raw Data Sheet'!G93,0) -> 420.67 | F39: =IFERROR('Raw Data Sheet'!H93,0) -> 414.86 | G39: =IFERROR('Raw Data Sheet'!I93,0) -> 415.09 | H39: =IFERROR('Raw Data Sheet'!J93,0) -> 415.33 | I39: =IFERROR('Raw Data Sheet'!K93,0) -> 405.56 | J39: =FORECAST(J6,$C$39:$I$39,$C$6:$I$6) -> 405.05714 | K39: =FORECAST(K6,$C$39:$I$39,$C$6:$I$6) -> 401.91143 | L39: =FORECAST(L6,$C$39:$I$39,$C$6:$I$6) -> 398.76571 | M39: =FORECAST(M6,$C$39:$I$39,$C$6:$I$6) -> 395.62 | N39: =FORECAST(N6,$C$39:$I$39,$C$6:$I$6) -> 392.47429
B41: EPS | C41: =IFERROR(C36/C39,0) -> 32.486499 | D41: =IFERROR(D36/D39,0) -> 40.420588 | E41: =IFERROR(E36/E39,0) -> 47.189008 | F41: =IFERROR(F36/F39,0) -> 51.60054 | G41: =IFERROR(G36/G39,0) -> 51.885133 | H41: =IFERROR(H36/H39,0) -> 55.73881 | I41: =IFERROR(I36/I39,0) -> 65.196272 | J41: =IFERROR(J36/J39,0) -> 68.703181 | ... N41: =IFERROR(N36/N39,0) -> 89.599319
B42: EPS growth | D42: =D41/C41-1 -> 0.24422727 | E42: =E41/D41-1 -> 0.16744981 | F42: =F41/E41-1 -> 0.093486431 | G42: =G41/F41-1 -> 0.0055153183 | H42: =H41/G41-1 -> 0.074273236 | I42: =I41/H41-1 -> 0.16967463 | J42: =J41/I41-1 -> 0.05379003 | K42: =K41/J41-1 -> 0.07425232 | ... N42: =N41/M41-1 -> 0.063484941
B44: Dividend per share | C44: =IFERROR('Raw Data Sheet'!E31/C39,0) -> 17.438366 | D44: =IFERROR('Raw Data Sheet'!F31/D39,0) -> 26.91952 | E44: =IFERROR('Raw Data Sheet'!G31/E39,0) -> 30.92115 | F44: =IFERROR('Raw Data Sheet'!H31/F39,0) -> 33.913127 | G44: =IFERROR('Raw Data Sheet'!I31/G39,0) -> 45.901371 | H44: =IFERROR('Raw Data Sheet'!J31/H39,0) -> 42.924422 | I44: =IFERROR('Raw Data Sheet'!K31/I39,0) -> 47.91005 | J44: =FORECAST(J6,$C$44:$I$44,$C$6:$I$6) -> 54.904726 | K44: =FORECAST(K6,$C$44:$I$44,$C$6:$I$6) -> 59.847765 | L44: =FORECAST(L6,$C$44:$I$44,$C$6:$I$6) -> 64.790803 | M44: =FORECAST(M6,$C$44:$I$44,$C$6:$I$6) -> 69.733842 | N44: =FORECAST(N6,$C$44:$I$44,$C$6:$I$6) -> 74.67688
B45: D/D Payout Ratio | C45: =IFERROR(C44/C41,0) -> 0.53678809 | D45: =IFERROR(D44/D41,0) -> 0.66598537 | E45: =IFERROR(E44/E41,0) -> 0.6552617 | F45: =IFERROR(F44/F41,0) -> 0.65722427 | G45: =IFERROR(G44/G41,0) -> 0.88467289 | H45: =IFERROR(H44/H41,0) -> 0.77009935 | I45: =IFERROR(I44/I41,0) -> 0.73485874 | J45: =IFERROR(J44/J41,0) -> 0.79915843 | ... N45: =IFERROR(N44/N41,0) -> 0.83345366
B47: Retained Earnings | C47: =IFERROR(IF(C41>C44,1-C45,0),0) -> 0.46321191 | D47: =IFERROR(IF(D41>D44,1-D45,0),0) -> 0.33401463 | E47: =IFERROR(IF(E41>E44,1-E45,0),0) -> 0.3447383 | F47: =IFERROR(IF(F41>F44,1-F45,0),0) -> 0.34277573 | G47: =IFERROR(IF(G41>G44,1-G45,0),0) -> 0.11532711 | H47: =IFERROR(IF(H41>H44,1-H45,0),0) -> 0.22990065 | I47: =IFERROR(IF(I41>I44,1-I45,0),0) -> 0.26514126 | J47: =IFERROR(IF(J41>J44,1-J45,0),0) -> 0.20084157 | ... N47: =IFERROR(IF(N41>N44,1-N45,0),0) -> 0.16654634
B48: EBIT | C48: =IFERROR(C21-C27,0) -> 19374 | D48: =IFERROR(D21-D27,0) -> 24622 | E48: =IFERROR(E21-E27,0) -> 28015 | F48: =IFERROR(F21-F27,0) -> 30905 | G48: =IFERROR(G21-G27,0) -> 31747 | H48: =IFERROR(H21-H27,0) -> 34424 | I48: =IFERROR(I21-I27,0) -> 37378 | J48: =IFERROR(J21-J27,0) -> 40544.714 | ... N48: =IFERROR(N21-N27,0) -> 51594.429
B49: EBIT Margin | C49: =C48/C9 -> 0.2133912 | D49: =D48/D9 -> 0.2450633 | E49: =E48/E9 -> 0.23030886 | F49: =F48/F9 -> 0.21057186 | G49: =G48/G9 -> 0.20659205 | H49: =H48/H9 -> 0.21120314 | I49: =I48/I9 -> 0.20922474 | J49: =J48/J9 -> 0.20631597 | ... N49: =N48/N9 -> 0.2010622
A50: # | B50: Balance Sheet
B52: Equity Share Capital | C52: =IFERROR('Raw Data Sheet'!E57,0) -> 2122 | D52: =IFERROR('Raw Data Sheet'!F57,0) -> 2124 | E52: =IFERROR('Raw Data Sheet'!G57,0) -> 2098 | F52: =IFERROR('Raw Data Sheet'!H57,0) -> 2069 | G52: =IFERROR('Raw Data Sheet'!I57,0) -> 2071 | H52: =IFERROR('Raw Data Sheet'!J57,0) -> 2073 | I52: =IFERROR('Raw Data Sheet'!K57,0) -> 2024 | J52: =FORECAST(J6,$C$52:$I$52,$C$6:$I$6) -> 2022.5714 | K52: =FORECAST(K6,$C$52:$I$52,$C$6:$I$6) -> 2007.4643 | L52: =FORECAST(L6,$C$52:$I$52,$C$6:$I$6) -> 1992.3571 | M52: =FORECAST(M6,$C$52:$I$52,$C$6:$I$6) -> 1977.25 | N52: =FORECAST(N6,$C$52:$I$52,$C$6:$I$6) -> 1962.1429
B53: Reserves | C53: =IFERROR('Raw Data Sheet'!E58,0) -> 63328 | D53: =IFERROR('Raw Data Sheet'!F58,0) -> 74227 | E53: =IFERROR('Raw Data Sheet'!G58,0) -> 73252 | F53: =IFERROR('Raw Data Sheet'!H58,0) -> 73338 | G53: =IFERROR('Raw Data Sheet'!I58,0) -> 86045 | H53: =IFERROR('Raw Data Sheet'!J58,0) -> 93745 | I53: =IFERROR('Raw Data Sheet'!K58,0) -> 90828 | J53: =FORECAST($J$6,C53:I53,$C$6:$I$6) -> 98441.714 | K53: =FORECAST($J$6,D53:J53,$C$6:$I$6) -> 102582.84 | L53: =FORECAST($J$6,E53:K53,$C$6:$I$6) -> 108745.07 | M53: =FORECAST($J$6,F53:L53,$C$6:$I$6) -> 113959.89 | N53: =FORECAST($J$6,G53:M53,$C$6:$I$6) -> 117121.02
B54: Borrowings | C54: =IFERROR('Raw Data Sheet'!E59,0) -> 4633 | D54: =IFERROR('Raw Data Sheet'!F59,0) -> 5325 | E54: =IFERROR('Raw Data Sheet'!G59,0) -> 5474 | F54: =IFERROR('Raw Data Sheet'!H59,0) -> 8299 | G54: =IFERROR('Raw Data Sheet'!I59,0) -> 8359 | H54: =IFERROR('Raw Data Sheet'!J59,0) -> 8227 | I54: =IFERROR('Raw Data Sheet'!K59,0) -> 9176 | J54: =FORECAST($J$6,C54:I54,$C$6:$I$6) -> 10258.714 | K54: =FORECAST($J$6,D54:J54,$C$6:$I$6) -> 11035.98 | L54: =FORECAST($J$6,E54:K54,$C$6:$I$6) -> 11750.294 | M54: =FORECAST($J$6,F54:L54,$C$6:$I$6) -> 12120.792 | N54: =FORECAST($J$6,G54:M54,$C$6:$I$6) -> 13017.104
B55: Other Liabilities | C55: =IFERROR('Raw Data Sheet'!E60,0) -> 21717 | D55: =IFERROR('Raw Data Sheet'!F60,0) -> 25835 | E55: =IFERROR('Raw Data Sheet'!G60,0) -> 35905 | F55: =IFERROR('Raw Data Sheet'!H60,0) -> 40890 | G55: =IFERROR('Raw Data Sheet'!I60,0) -> 39545 | H55: =IFERROR('Raw Data Sheet'!J60,0) -> 43750 | I55: =IFERROR('Raw Data Sheet'!K60,0) -> 52260 | J55: =FORECAST($J$6,C55:I55,$C$6:$I$6) -> 55857.286 | K55: =FORECAST($J$6,D55:J55,$C$6:$I$6) -> 59954.163 | L55: =FORECAST($J$6,E55:K55,$C$6:$I$6) -> 63279.787 | M55: =FORECAST($J$6,F55:L55,$C$6:$I$6) -> 67947.316 | N55: =FORECAST($J$6,G55:M55,$C$6:$I$6) -> 73507.748
B56: Total Liabilities | C56: =SUM(C52:C55) -> 91800 | D56: =SUM(D52:D55) -> 107511 | E56: =SUM(E52:E55) -> 116729 | F56: =SUM(F52:F55) -> 124596 | G56: =SUM(G52:G55) -> 136020 | H56: =SUM(H52:H55) -> 147795 | I56: =SUM(I52:I55) -> 154288 | J56: =SUM(J52:J55) -> 166580.29 | ... N56: =SUM(N52:N55) -> 205608.02
B58: Fixed Assets Net Block | C58: =IFERROR('Raw Data Sheet'!E62,0) -> 23789 | D58: =IFERROR('Raw Data Sheet'!F62,0) -> 25505 | E58: =IFERROR('Raw Data Sheet'!G62,0) -> 25800 | F58: =IFERROR('Raw Data Sheet'!H62,0) -> 29225 | G58: =IFERROR('Raw Data Sheet'!I62,0) -> 27622 | H58: =IFERROR('Raw Data Sheet'!J62,0) -> 30961 | I58: =IFERROR('Raw Data Sheet'!K62,0) -> 33770 | J58: =FORECAST($J$6,C58:I58,$C$6:$I$6) -> 34192.714 | K58: =FORECAST($J$6,D58:J58,$C$6:$I$6) -> 35830.694 | L58: =FORECAST($J$6,E58:K58,$C$6:$I$6) -> 37653.845 | M58: =FORECAST($J$6,F58:L58,$C$6:$I$6) -> 39170.127 | N58: =FORECAST($J$6,G58:M58,$C$6:$I$6) -> 41327.307
B59: Capital Work in Progress | C59: =IFERROR('Raw Data Sheet'!E63,0) -> 954 | D59: =IFERROR('Raw Data Sheet'!F63,0) -> 922 | E59: =IFERROR('Raw Data Sheet'!G63,0) -> 416 | F59: =IFERROR('Raw Data Sheet'!H63,0) -> 288 | G59: =IFERROR('Raw Data Sheet'!I63,0) -> 293 | H59: =IFERROR('Raw Data Sheet'!J63,0) -> 814 | I59: =IFERROR('Raw Data Sheet'!K63,0) -> 526 | J59: =FORECAST($J$6,C59:I59,$C$6:$I$6) -> 370 | K59: =FORECAST($J$6,D59:J59,$C$6:$I$6) -> 388.42857 | L59: =FORECAST($J$6,E59:K59,$C$6:$I$6) -> 487.10204 | M59: =FORECAST($J$6,F59:L59,$C$6:$I$6) -> 501.5277 | N59: =FORECAST($J$6,G59:M59,$C$6:$I$6) -> 459.18201
B60: Investments | C60: =IFERROR('Raw Data Sheet'!E64,0) -> 8792 | D60: =IFERROR('Raw Data Sheet'!F64,0) -> 14205 | E60: =IFERROR('Raw Data Sheet'!G64,0) -> 20324 | F60: =IFERROR('Raw Data Sheet'!H64,0) -> 19478 | G60: =IFERROR('Raw Data Sheet'!I64,0) -> 24623 | H60: =IFERROR('Raw Data Sheet'!J64,0) -> 23541 | I60: =IFERROR('Raw Data Sheet'!K64,0) -> 21880 | J60: =FORECAST($J$6,C60:I60,$C$6:$I$6) -> 27868.286 | K60: =FORECAST($J$6,D60:J60,$C$6:$I$6) -> 28583.449 | L60: =FORECAST($J$6,E60:K60,$C$6:$I$6) -> 29301.95 | M60: =FORECAST($J$6,F60:L60,$C$6:$I$6) -> 30999.389 | N60: =FORECAST($J$6,G60:M60,$C$6:$I$6) -> 32021.656
B61: Other Assets | C61: =IFERROR('Raw Data Sheet'!E65-SUM('Raw Data Sheet'!E67:E69),0) -> 21129 | D61: =IFERROR('Raw Data Sheet'!F65-SUM('Raw Data Sheet'!F67:F69),0) -> 22871 | E61: =IFERROR('Raw Data Sheet'!G65-SUM('Raw Data Sheet'!G67:G69),0) -> 30019 | F61: =IFERROR('Raw Data Sheet'!H65-SUM('Raw Data Sheet'!H67:H69),0) -> 38008 | G61: =IFERROR('Raw Data Sheet'!I65-SUM('Raw Data Sheet'!I67:I69),0) -> 38503 | H61: =IFERROR('Raw Data Sheet'!J65-SUM('Raw Data Sheet'!J67:J69),0) -> 36866 | I61: =IFERROR('Raw Data Sheet'!K65-SUM('Raw Data Sheet'!K67:K69),0) -> 40677 | J61: =FORECAST($J$6,C61:I61,$C$6:$I$6) -> 46170.143 | K61: =FORECAST($J$6,D61:J61,$C$6:$I$6) -> 49026.51 | L61: =FORECAST($J$6,E61:K61,$C$6:$I$6) -> 50684.353 | M61: =FORECAST($J$6,F61:L61,$C$6:$I$6) -> 52616.461 | N61: =FORECAST($J$6,G61:M61,$C$6:$I$6) -> 56124.295
B62: Total Non-Current Assets | C62: =SUM(C58:C61) -> 54664 | D62: =SUM(D58:D61) -> 63503 | E62: =SUM(E58:E61) -> 76559 | F62: =SUM(F58:F61) -> 86999 | G62: =SUM(G58:G61) -> 91041 | H62: =SUM(H58:H61) -> 92182 | I62: =SUM(I58:I61) -> 96853 | J62: =SUM(J58:J61) -> 108601.14 | ... N62: =SUM(N58:N61) -> 129932.44
B64: Receivables | C64: =IFERROR('Raw Data Sheet'!E67,0) -> 18487 | D64: =IFERROR('Raw Data Sheet'!F67,0) -> 19294 | E64: =IFERROR('Raw Data Sheet'!G67,0) -> 22698 | F64: =IFERROR('Raw Data Sheet'!H67,0) -> 25424 | G64: =IFERROR('Raw Data Sheet'!I67,0) -> 30193 | H64: =IFERROR('Raw Data Sheet'!J67,0) -> 31158 | I64: =IFERROR('Raw Data Sheet'!K67,0) -> 35234 | J64: =FORECAST($J$6,C64:I64,$C$6:$I$6) -> 37707.429 | K64: =FORECAST($J$6,D64:J64,$C$6:$I$6) -> 41107.816 | L64: =FORECAST($J$6,E64:K64,$C$6:$I$6) -> 44051.364 | M64: =FORECAST($J$6,F64:L64,$C$6:$I$6) -> 47019.538 | N64: =FORECAST($J$6,G64:M64,$C$6:$I$6) -> 49801.615
B65: Inventory | C65: =IFERROR('Raw Data Sheet'!E68,0) -> 0 | D65: =IFERROR('Raw Data Sheet'!F68,0) -> 0 | E65: =IFERROR('Raw Data Sheet'!G68,0) -> 0 | F65: =IFERROR('Raw Data Sheet'!H68,0) -> 0 | G65: =IFERROR('Raw Data Sheet'!I68,0) -> 0 | H65: =IFERROR('Raw Data Sheet'!J68,0) -> 0 | I65: =IFERROR('Raw Data Sheet'!K68,0) -> 0 | J65: =FORECAST($J$6,C65:I65,$C$6:$I$6) -> 0 | K65: =FORECAST($J$6,D65:J65,$C$6:$I$6) -> 0 | L65: =FORECAST($J$6,E65:K65,$C$6:$I$6) -> 0 | M65: =FORECAST($J$6,F65:L65,$C$6:$I$6) -> 0 | N65: =FORECAST($J$6,G65:M65,$C$6:$I$6) -> 0
B66: Cash & Bank | C66: =IFERROR('Raw Data Sheet'!E69,0) -> 18649 | D66: =IFERROR('Raw Data Sheet'!F69,0) -> 24714 | E66: =IFERROR('Raw Data Sheet'!G69,0) -> 17472 | F66: =IFERROR('Raw Data Sheet'!H69,0) -> 12173 | G66: =IFERROR('Raw Data Sheet'!I69,0) -> 14786 | H66: =IFERROR('Raw Data Sheet'!J69,0) -> 24455 | I66: =IFERROR('Raw Data Sheet'!K69,0) -> 22201 | J66: =FORECAST($J$6,C66:I66,$C$6:$I$6) -> 20271.714 | K66: =FORECAST($J$6,D66:J66,$C$6:$I$6) -> 20640.837 | L66: =FORECAST($J$6,E66:K66,$C$6:$I$6) -> 23588.356 | M66: =FORECAST($J$6,F66:L66,$C$6:$I$6) -> 25698.337 | N66: =FORECAST($J$6,G66:M66,$C$6:$I$6) -> 25869.258
B67: Total Current Assets | C67: =SUM(C64:C66) -> 37136 | D67: =SUM(D64:D66) -> 44008 | E67: =SUM(E64:E66) -> 40170 | F67: =SUM(F64:F66) -> 37597 | G67: =SUM(G64:G66) -> 44979 | H67: =SUM(H64:H66) -> 55613 | I67: =SUM(I64:I66) -> 57435 | J67: =FORECAST($J$6,C67:I67,$C$6:$I$6) -> 57979.143 | K67: =FORECAST($J$6,D67:J67,$C$6:$I$6) -> 61748.653 | L67: =FORECAST($J$6,E67:K67,$C$6:$I$6) -> 67639.72 | M67: =FORECAST($J$6,F67:L67,$C$6:$I$6) -> 72717.875 | N67: =FORECAST($J$6,G67:M67,$C$6:$I$6) -> 75670.873
B69: Total Assets | C69: =SUM(C62,C67) -> 91800 | D69: =SUM(D62,D67) -> 107511 | E69: =SUM(E62,E67) -> 116729 | F69: =SUM(F62,F67) -> 124596 | G69: =SUM(G62,G67) -> 136020 | H69: =SUM(H62,H67) -> 147795 | I69: =SUM(I62,I67) -> 154288 | J69: =SUM(J62,J67) -> 166580.29 | ... N69: =SUM(N62,N67) -> 205603.31
B71: Check | C71: =C69=C56 -> TRUE | D71: =D69=D56 -> TRUE | E71: =E69=E56 -> TRUE | F71: =F69=F56 -> TRUE | G71: =G69=G56 -> TRUE | H71: =H69=H56 -> TRUE | I71: =I69=I56 -> TRUE | J71: =J69=J56 -> TRUE | K71: =IF((K56-K69)<5,TRUE, FALSE) -> TRUE | L71: =IF((L56-L69)<5,TRUE, FALSE) -> TRUE | M71: =IF((M56-M69)<5,TRUE, FALSE) -> TRUE | N71: =IF((N56-N69)<5,TRUE, FALSE) -> TRUE
A73: # | B73: Cash Flow Statement
B74: Operating Activities
B75: Profit from Operations | C75: =IFERROR('Raw Cash Flow '!H4,0) -> 23920 | D75: =IFERROR('Raw Cash Flow '!I4,0) -> 28845 | E75: =IFERROR('Raw Cash Flow '!J4,0) -> 32921 | F75: =IFERROR('Raw Cash Flow '!K4,0) -> 37605 | G75: =IFERROR('Raw Cash Flow '!L4,0) -> 39523 | H75: =IFERROR('Raw Cash Flow '!M4,0) -> 41591 | I75: =IFERROR('Raw Cash Flow '!N4,0) -> 45273 | J75: =FORECAST($J$6,C75:I75,$C$6:$I$6) -> 49404.429 | K75: =FORECAST($J$6,D75:J75,$C$6:$I$6) -> 52218.673 | L75: =FORECAST($J$6,E75:K75,$C$6:$I$6) -> 55111.14 | M75: =FORECAST($J$6,F75:L75,$C$6:$I$6) -> 58064.205 | N75: =FORECAST($J$6,G75:M75,$C$6:$I$6) -> 61542.145
B76: Receivables | C76: =IFERROR('Raw Cash Flow '!H5,0) -> -3861 | D76: =IFERROR('Raw Cash Flow '!I5,0) -> -1835 | E76: =IFERROR('Raw Cash Flow '!J5,0) -> -7937 | F76: =IFERROR('Raw Cash Flow '!K5,0) -> -7076 | G76: =IFERROR('Raw Cash Flow '!L5,0) -> -2667 | H76: =IFERROR('Raw Cash Flow '!M5,0) -> -1769 | I76: =IFERROR('Raw Cash Flow '!N5,0) -> -5177 | J76: =FORECAST($J$6,C76:I76,$C$6:$I$6) -> -4124 | K76: =FORECAST($J$6,D76:J76,$C$6:$I$6) -> -3803.5714 | L76: =FORECAST($J$6,E76:K76,$C$6:$I$6) -> -2394.1837 | M76: =FORECAST($J$6,F76:L76,$C$6:$I$6) -> -2513.3499 | N76: =FORECAST($J$6,G76:M76,$C$6:$I$6) -> -3123.4419
B77: Payables | C77: =IFERROR('Raw Cash Flow '!H6,0) -> -373 | D77: =IFERROR('Raw Cash Flow '!I6,0) -> -245 | E77: =IFERROR('Raw Cash Flow '!J6,0) -> 1489 | F77: =IFERROR('Raw Cash Flow '!K6,0) -> -279 | G77: =IFERROR('Raw Cash Flow '!L6,0) -> 91 | H77: =IFERROR('Raw Cash Flow '!M6,0) -> 176 | I77: =IFERROR('Raw Cash Flow '!N6,0) -> -26 | J77: =FORECAST($J$6,C77:I77,$C$6:$I$6) -> 188.28571 | K77: =FORECAST($J$6,D77:J77,$C$6:$I$6) -> 17.020408 | L77: =FORECAST($J$6,E77:K77,$C$6:$I$6) -> -277.43732 | M77: =FORECAST($J$6,F77:L77,$C$6:$I$6) -> -34.445231 | N77: =FORECAST($J$6,G77:M77,$C$6:$I$6) -> -157.96662
B78: Loans Advances | C78: =IFERROR('Raw Cash Flow '!H7,0) -> 0 | D78: =IFERROR('Raw Cash Flow '!I7,0) -> -534 | E78: =IFERROR('Raw Cash Flow '!J7,0) -> -1914 | F78: =IFERROR('Raw Cash Flow '!K7,0) -> -3108 | G78: =IFERROR('Raw Cash Flow '!L7,0) -> -1172 | H78: =IFERROR('Raw Cash Flow '!M7,0) -> -1024 | I78: =IFERROR('Raw Cash Flow '!N7,0) -> -2645 | J78: =FORECAST($J$6,C78:I78,$C$6:$I$6) -> -2652.8571 | K78: =FORECAST($J$6,D78:J78,$C$6:$I$6) -> -2683.4898 | L78: =FORECAST($J$6,E78:K78,$C$6:$I$6) -> -2581.5044 | M78: =FORECAST($J$6,F78:L78,$C$6:$I$6) -> -2705.6002 | N78: =FORECAST($J$6,G78:M78,$C$6:$I$6) -> -3316.9644
B79: Other WC items | C79: =IFERROR('Raw Cash Flow '!H8,0) -> 1867 | D79: =IFERROR('Raw Cash Flow '!I8,0) -> 3382 | E79: =IFERROR('Raw Cash Flow '!J8,0) -> 6938 | F79: =IFERROR('Raw Cash Flow '!K8,0) -> 4119 | G79: =IFERROR('Raw Cash Flow '!L8,0) -> -1334 | H79: =IFERROR('Raw Cash Flow '!M8,0) -> 2322 | I79: =IFERROR('Raw Cash Flow '!N8,0) -> 5209 | J79: =FORECAST($J$6,C79:I79,$C$6:$I$6) -> 3162.4286 | K79: =FORECAST($J$6,D79:J79,$C$6:$I$6) -> 2554.9592 | L79: =FORECAST($J$6,E79:K79,$C$6:$I$6) -> 2064.5889 | M79: =FORECAST($J$6,F79:L79,$C$6:$I$6) -> 2936.1558 | N79: =FORECAST($J$6,G79:M79,$C$6:$I$6) -> 3793.8195
B80: Working capital changes | C80: =IFERROR('Raw Cash Flow '!H9,0) -> -2367 | D80: =IFERROR('Raw Cash Flow '!I9,0) -> 768 | E80: =IFERROR('Raw Cash Flow '!J9,0) -> -1424 | F80: =IFERROR('Raw Cash Flow '!K9,0) -> -6344 | G80: =IFERROR('Raw Cash Flow '!L9,0) -> -5082 | H80: =IFERROR('Raw Cash Flow '!M9,0) -> -295 | I80: =IFERROR('Raw Cash Flow '!N9,0) -> -2639 | J80: =FORECAST($J$6,C80:I80,$C$6:$I$6) -> -3426.1429 | K80: =FORECAST($J$6,D80:J80,$C$6:$I$6) -> -3915.0816 | L80: =FORECAST($J$6,E80:K80,$C$6:$I$6) -> -3188.5364 | M80: =FORECAST($J$6,F80:L80,$C$6:$I$6) -> -2317.2395 | N80: =FORECAST($J$6,G80:M80,$C$6:$I$6) -> -2804.5533
B81: Direct taxes | C81: =IFERROR('Raw Cash Flow '!H10,0) -> -4550 | D81: =IFERROR('Raw Cash Flow '!I10,0) -> -6389 | E81: =IFERROR('Raw Cash Flow '!J10,0) -> -7612 | F81: =IFERROR('Raw Cash Flow '!K10,0) -> -8794 | G81: =IFERROR('Raw Cash Flow '!L10,0) -> -9231 | H81: =IFERROR('Raw Cash Flow '!M10,0) -> -5602 | I81: =IFERROR('Raw Cash Flow '!N10,0) -> -8648 | J81: =FORECAST($J$6,C81:I81,$C$6:$I$6) -> -9023.5714 | K81: =FORECAST($J$6,D81:J81,$C$6:$I$6) -> -8869.0408 | L81: =FORECAST($J$6,E81:K81,$C$6:$I$6) -> -8775.2682 | M81: =FORECAST($J$6,F81:L81,$C$6:$I$6) -> -8797.7626 | N81: =FORECAST($J$6,G81:M81,$C$6:$I$6) -> -9173.5012
B82: Cash From Operating Activities | C82: =SUM(C75:C79,C81) -> 17003 | D82: =SUM(D75:D79,D81) -> 23224 | E82: =SUM(E75:E79,E81) -> 23885 | F82: =SUM(F75:F79,F81) -> 22467 | G82: =SUM(G75:G79,G81) -> 25210 | H82: =SUM(H75:H79,H81) -> 35694 | I82: =SUM(I75:I79,I81) -> 33986 | J82: =SUM(J75:J79,J81) -> 36954.714 | ... N82: =SUM(N75:N79,N81) -> 49564.091
B84: Investing Activities
B85: Fixed assets purchased | C85: =IFERROR('Raw Cash Flow '!H12,0) -> -3307 | D85: =IFERROR('Raw Cash Flow '!I12,0) -> -2107 | E85: =IFERROR('Raw Cash Flow '!J12,0) -> -2161 | F85: =IFERROR('Raw Cash Flow '!K12,0) -> -2579 | G85: =IFERROR('Raw Cash Flow '!L12,0) -> -2201 | H85: =IFERROR('Raw Cash Flow '!M12,0) -> -2237 | I85: =IFERROR('Raw Cash Flow '!N12,0) -> -2727 | J85: =FORECAST($J$6,C85:I85,$C$6:$I$6) -> -2268.4286 | K85: =FORECAST($J$6,D85:J85,$C$6:$I$6) -> -2507.8163 | L85: =FORECAST($J$6,E85:K85,$C$6:$I$6) -> -2518.0787 | M85: =FORECAST($J$6,F85:L85,$C$6:$I$6) -> -2500.0887 | N85: =FORECAST($J$6,G85:M85,$C$6:$I$6) -> -2599.9503
B86: Investments purchased | C86: =IFERROR('Raw Cash Flow '!H13,0) -> -37482 | D86: =IFERROR('Raw Cash Flow '!I13,0) -> -46738 | E86: =IFERROR('Raw Cash Flow '!J13,0) -> -59951 | F86: =IFERROR('Raw Cash Flow '!K13,0) -> -75800 | G86: =IFERROR('Raw Cash Flow '!L13,0) -> -78092 | H86: =IFERROR('Raw Cash Flow '!M13,0) -> -82742 | I86: =IFERROR('Raw Cash Flow '!N13,0) -> -82617 | J86: =FORECAST($J$6,C86:I86,$C$6:$I$6) -> -98425.143 | K86: =FORECAST($J$6,D86:J86,$C$6:$I$6) -> -104528.65 | L86: =FORECAST($J$6,E86:K86,$C$6:$I$6) -> -109380.58 | M86: =FORECAST($J$6,F86:L86,$C$6:$I$6) -> -114411.94 | N86: =FORECAST($J$6,G86:M86,$C$6:$I$6) -> -122049.42
B87: Investments sold | C87: =IFERROR('Raw Cash Flow '!H14,0) -> 38861 | D87: =IFERROR('Raw Cash Flow '!I14,0) -> 40381 | E87: =IFERROR('Raw Cash Flow '!J14,0) -> 57356 | F87: =IFERROR('Raw Cash Flow '!K14,0) -> 76722 | G87: =IFERROR('Raw Cash Flow '!L14,0) -> 72930 | H87: =IFERROR('Raw Cash Flow '!M14,0) -> 84877 | I87: =IFERROR('Raw Cash Flow '!N14,0) -> 89699 | J87: =FORECAST($J$6,C87:I87,$C$6:$I$6) -> 102558 | K87: =FORECAST($J$6,D87:J87,$C$6:$I$6) -> 111985 | L87: =FORECAST($J$6,E87:K87,$C$6:$I$6) -> 118350.71 | M87: =FORECAST($J$6,F87:L87,$C$6:$I$6) -> 125399.84 | N87: =FORECAST($J$6,G87:M87,$C$6:$I$6) -> 136063.21
B88: Interest received | C88: =IFERROR('Raw Cash Flow '!H15,0) -> 0 | D88: =IFERROR('Raw Cash Flow '!I15,0) -> 0 | E88: =IFERROR('Raw Cash Flow '!J15,0) -> 0 | F88: =IFERROR('Raw Cash Flow '!K15,0) -> 0 | G88: =IFERROR('Raw Cash Flow '!L15,0) -> 0 | H88: =IFERROR('Raw Cash Flow '!M15,0) -> 0 | I88: =IFERROR('Raw Cash Flow '!N15,0) -> 0 | J88: =FORECAST($J$6,C88:I88,$C$6:$I$6) -> 0 | K88: =FORECAST($J$6,D88:J88,$C$6:$I$6) -> 0 | L88: =FORECAST($J$6,E88:K88,$C$6:$I$6) -> 0 | M88: =FORECAST($J$6,F88:L88,$C$6:$I$6) -> 0 | N88: =FORECAST($J$6,G88:M88,$C$6:$I$6) -> 0
B89: Dividends received | C89: =IFERROR('Raw Cash Flow '!H16,0) -> 1929 | D89: =IFERROR('Raw Cash Flow '!I16,0) -> 1418 | E89: =IFERROR('Raw Cash Flow '!J16,0) -> 1898 | F89: =IFERROR('Raw Cash Flow '!K16,0) -> 1525 | G89: =IFERROR('Raw Cash Flow '!L16,0) -> 1768 | H89: =IFERROR('Raw Cash Flow '!M16,0) -> 2040 | I89: =IFERROR('Raw Cash Flow '!N16,0) -> 2713 | J89: =FORECAST($J$6,C89:I89,$C$6:$I$6) -> 2393.8571 | K89: =FORECAST($J$6,D89:J89,$C$6:$I$6) -> 2689.7755 | L89: =FORECAST($J$6,E89:K89,$C$6:$I$6) -> 2869.3819 | M89: =FORECAST($J$6,F89:L89,$C$6:$I$6) -> 3175.6526 | N89: =FORECAST($J$6,G89:M89,$C$6:$I$6) -> 3358.3092
B90: Acquisition of companies | C90: =IFERROR('Raw Cash Flow '!H17,0) -> 0 | D90: =IFERROR('Raw Cash Flow '!I17,0) -> 0 | E90: =IFERROR('Raw Cash Flow '!J17,0) -> 0 | F90: =IFERROR('Raw Cash Flow '!K17,0) -> 0 | G90: =IFERROR('Raw Cash Flow '!L17,0) -> 0 | H90: =IFERROR('Raw Cash Flow '!M17,0) -> 0 | I90: =IFERROR('Raw Cash Flow '!N17,0) -> 0 | J90: =FORECAST($J$6,C90:I90,$C$6:$I$6) -> 0 | K90: =FORECAST($J$6,D90:J90,$C$6:$I$6) -> 0 | L90: =FORECAST($J$6,E90:K90,$C$6:$I$6) -> 0 | M90: =FORECAST($J$6,F90:L90,$C$6:$I$6) -> 0 | N90: =FORECAST($J$6,G90:M90,$C$6:$I$6) -> 0
B91: Inter corporate deposits | C91: =IFERROR('Raw Cash Flow '!H18,0) -> -108 | D91: =IFERROR('Raw Cash Flow '!I18,0) -> 0 | E91: =IFERROR('Raw Cash Flow '!J18,0) -> 0 | F91: =IFERROR('Raw Cash Flow '!K18,0) -> 0 | G91: =IFERROR('Raw Cash Flow '!L18,0) -> 0 | H91: =IFERROR('Raw Cash Flow '!M18,0) -> 0 | I91: =IFERROR('Raw Cash Flow '!N18,0) -> 0 | J91: =FORECAST($J$6,C91:I91,$C$6:$I$6) -> 30.857143 | K91: =FORECAST($J$6,D91:J91,$C$6:$I$6) -> 17.632653 | L91: =FORECAST($J$6,E91:K91,$C$6:$I$6) -> 23.300292 | M91: =FORECAST($J$6,F91:L91,$C$6:$I$6) -> 29.68763 | N91: =FORECAST($J$6,G91:M91,$C$6:$I$6) -> 36.396263
B92: Other investing items | C92: =IFERROR('Raw Cash Flow '!H19,0) -> -224 | D92: =IFERROR('Raw Cash Flow '!I19,0) -> -327 | E92: =IFERROR('Raw Cash Flow '!J19,0) -> -3627 | F92: =IFERROR('Raw Cash Flow '!K19,0) -> -939 | G92: =IFERROR('Raw Cash Flow '!L19,0) -> 502 | H92: =IFERROR('Raw Cash Flow '!M19,0) -> -3802 | I92: =IFERROR('Raw Cash Flow '!N19,0) -> -3522 | J92: =FORECAST($J$6,C92:I92,$C$6:$I$6) -> -3522 | K92: =FORECAST($J$6,D92:J92,$C$6:$I$6) -> -3925 | L92: =FORECAST($J$6,E92:K92,$C$6:$I$6) -> -4131.2857 | M92: =FORECAST($J$6,F92:L92,$C$6:$I$6) -> -5355.7347 | N92: =FORECAST($J$6,G92:M92,$C$6:$I$6) -> -6055.828
B93: Cash Flow from Investing Activities | C93: =SUM(C85:C92) -> -331 | D93: =SUM(D85:D92) -> -7373 | E93: =SUM(E85:E92) -> -6485 | F93: =SUM(F85:F92) -> -1071 | G93: =SUM(G85:G92) -> -5093 | H93: =SUM(H85:H92) -> -1864 | I93: =SUM(I85:I92) -> 3546 | J93: =SUM(J85:J92) -> 767.14286 | ... N93: =SUM(N85:N92) -> 8752.722
B95: Financing Activities
B96: Proceeds from shares | C96: =IFERROR('Raw Cash Flow '!H21,0) -> 6 | D96: =IFERROR('Raw Cash Flow '!I21,0) -> 15 | E96: =IFERROR('Raw Cash Flow '!J21,0) -> 21 | F96: =IFERROR('Raw Cash Flow '!K21,0) -> 35 | G96: =IFERROR('Raw Cash Flow '!L21,0) -> 5 | H96: =IFERROR('Raw Cash Flow '!M21,0) -> 6 | I96: =IFERROR('Raw Cash Flow '!N21,0) -> 2 | J96: =FORECAST($J$6,C96:I96,$C$6:$I$6) -> 6.2857143 | K96: =FORECAST($J$6,D96:J96,$C$6:$I$6) -> -0.40816327 | L96: =FORECAST($J$6,E96:K96,$C$6:$I$6) -> -7.1107872 | M96: =FORECAST($J$6,F96:L96,$C$6:$I$6) -> -12.870887 | N96: =FORECAST($J$6,G96:M96,$C$6:$I$6) -> -11.906646
B97: Proceeds from borrowings | C97: =IFERROR('Raw Cash Flow '!H22,0) -> 0 | D97: =IFERROR('Raw Cash Flow '!I22,0) -> 0 | E97: =IFERROR('Raw Cash Flow '!J22,0) -> 0 | F97: =IFERROR('Raw Cash Flow '!K22,0) -> 0 | G97: =IFERROR('Raw Cash Flow '!L22,0) -> 0 | H97: =IFERROR('Raw Cash Flow '!M22,0) -> -985 | I97: =IFERROR('Raw Cash Flow '!N22,0) -> 0 | J97: =FORECAST($J$6,C97:I97,$C$6:$I$6) -> -422.14286 | K97: =FORECAST($J$6,D97:J97,$C$6:$I$6) -> -522.65306 | L97: =FORECAST($J$6,E97:K97,$C$6:$I$6) -> -620.29155 | M97: =FORECAST($J$6,F97:L97,$C$6:$I$6) -> -699.05873 | N97: =FORECAST($J$6,G97:M97,$C$6:$I$6) -> -734.22265
B98: Dividends paid | C98: =IFERROR('Raw Cash Flow '!H23,0) -> -9548 | D98: =IFERROR('Raw Cash Flow '!I23,0) -> -9137 | E98: =IFERROR('Raw Cash Flow '!J23,0) -> -12731 | F98: =IFERROR('Raw Cash Flow '!K23,0) -> -13653 | G98: =IFERROR('Raw Cash Flow '!L23,0) -> -14731 | H98: =IFERROR('Raw Cash Flow '!M23,0) -> -20289 | I98: =IFERROR('Raw Cash Flow '!N23,0) -> -18656 | J98: =FORECAST($J$6,C98:I98,$C$6:$I$6) -> -21481.857 | K98: =FORECAST($J$6,D98:J98,$C$6:$I$6) -> -23742.776 | L98: =FORECAST($J$6,E98:K98,$C$6:$I$6) -> -25414.668 | M98: =FORECAST($J$6,F98:L98,$C$6:$I$6) -> -27495.673 | N98: =FORECAST($J$6,G98:M98,$C$6:$I$6) -> -29349.015
B99: Financial liabilities | C99: =IFERROR('Raw Cash Flow '!H24,0) -> -571 | D99: =IFERROR('Raw Cash Flow '!I24,0) -> -698 | E99: =IFERROR('Raw Cash Flow '!J24,0) -> -915 | F99: =IFERROR('Raw Cash Flow '!K24,0) -> -1231 | G99: =IFERROR('Raw Cash Flow '!L24,0) -> -2024 | H99: =IFERROR('Raw Cash Flow '!M24,0) -> -2355 | I99: =IFERROR('Raw Cash Flow '!N24,0) -> -2824 | J99: =FORECAST($J$6,C99:I99,$C$6:$I$6) -> -3114.2857 | K99: =FORECAST($J$6,D99:J99,$C$6:$I$6) -> -3621.7347 | L99: =FORECAST($J$6,E99:K99,$C$6:$I$6) -> -4110.2566 | M99: =FORECAST($J$6,F99:L99,$C$6:$I$6) -> -4553.2574 | N99: =FORECAST($J$6,G99:M99,$C$6:$I$6) -> -4928.3649
B100: Other financing items | C100: =IFERROR('Raw Cash Flow '!H25,0) -> -7478 | D100: =IFERROR('Raw Cash Flow '!I25,0) -> 34 | E100: =IFERROR('Raw Cash Flow '!J25,0) -> -11017 | F100: =IFERROR('Raw Cash Flow '!K25,0) -> -11846 | G100: =IFERROR('Raw Cash Flow '!L25,0) -> -754 | H100: =IFERROR('Raw Cash Flow '!M25,0) -> -538 | I100: =IFERROR('Raw Cash Flow '!N25,0) -> -18308 | J100: =FORECAST($J$6,C100:I100,$C$6:$I$6) -> -10468.286 | K100: =FORECAST($J$6,D100:J100,$C$6:$I$6) -> -12525.449 | L100: =FORECAST($J$6,E100:K100,$C$6:$I$6) -> -12111.522 | M100: =FORECAST($J$6,F100:L100,$C$6:$I$6) -> -14403.001 | N100: =FORECAST($J$6,G100:M100,$C$6:$I$6) -> -18202.822
B101: Cash Flow from Financing Activities | C101: =SUM(C96:C100) -> -17591 | D101: =SUM(D96:D100) -> -9786 | E101: =SUM(E96:E100) -> -24642 | F101: =SUM(F96:F100) -> -26695 | G101: =SUM(G96:G100) -> -17504 | H101: =SUM(H96:H100) -> -24161 | I101: =SUM(I96:I100) -> -39786 | J101: =SUM(J96:J100) -> -35480.286 | ... N101: =SUM(N96:N100) -> -53226.331
B103: Net Cash Flow | C103: =IFERROR(C82+C93+C101,0) -> -919 | D103: =IFERROR(D82+D93+D101,0) -> 6065 | E103: =IFERROR(E82+E93+E101,0) -> -7242 | F103: =IFERROR(F82+F93+F101,0) -> -5299 | G103: =IFERROR(G82+G93+G101,0) -> 2613 | H103: =IFERROR(H82+H93+H101,0) -> 9669 | I103: =IFERROR(I82+I93+I101,0) -> -2254 | J103: =IFERROR(J82+J93+J101,0) -> 2241.5714 | ... N103: =IFERROR(N82+N93+N101,0) -> 5090.482

Sheet Ratio Analysis
B2: ="Ratio Analysis - "& 'Raw Data Sheet'!B1 -> Ratio Analysis - INFOSYS LTD
B3: Years | C3: ='Raw Data Sheet'!E16 -> 43921 | D3: ='Raw Data Sheet'!F16 -> 44286 | E3: ='Raw Data Sheet'!G16 -> 44651 | F3: ='Raw Data Sheet'!H16 -> 45016 | G3: ='Raw Data Sheet'!I16 -> 45382 | H3: ='Raw Data Sheet'!J16 -> 45747 | I3: ='Raw Data Sheet'!K16 -> 46112 | J3: Trend | K3: Mean | L3: Median
B5: SalesGrowth | D5: =IFERROR((' Forecasted FS>'!D9/' Forecasted FS>'!C9)-1,0) -> 0.10662951 | E5: =IFERROR((' Forecasted FS>'!E9/' Forecasted FS>'!D9)-1,0) -> 0.21069552 | F5: =IFERROR((' Forecasted FS>'!F9/' Forecasted FS>'!E9)-1,0) -> 0.20655864 | G5: =IFERROR((' Forecasted FS>'!G9/' Forecasted FS>'!F9)-1,0) -> 0.047033734 | H5: =IFERROR((' Forecasted FS>'!H9/' Forecasted FS>'!G9)-1,0) -> 0.060649444 | I5: =IFERROR((' Forecasted FS>'!I9/' Forecasted FS>'!H9)-1,0) -> 0.096079514 | K5: =IFERROR(AVERAGE(D5:I5),0) -> 0.12127439 | L5: =IFERROR(MEDIAN(C5:I5),0) -> 0.10135451
B6: EBITDA Growth | D6: =IFERROR((' Forecasted FS>'!D21/' Forecasted FS>'!C21)-1,0) -> 0.25248125 | E6: =IFERROR((' Forecasted FS>'!E21/' Forecasted FS>'!D21)-1,0) -> 0.12915486 | F6: =IFERROR((' Forecasted FS>'!F21/' Forecasted FS>'!E21)-1,0) -> 0.11555683 | G6: =IFERROR((' Forecasted FS>'!G21/' Forecasted FS>'!F21)-1,0) -> 0.03686308 | H6: =IFERROR((' Forecasted FS>'!H21/' Forecasted FS>'!G21)-1,0) -> 0.077172272 | I6: =IFERROR((' Forecasted FS>'!I21/' Forecasted FS>'!H21)-1,0) -> 0.077581813 | K6: =IFERROR(AVERAGE(D6:I6),0) -> 0.11480168 | L6: =IFERROR(MEDIAN(C6:I6),0) -> 0.096569319
B7: EBIT Growth | D7: =IFERROR((' Forecasted FS>'!D48/' Forecasted FS>'!C48)-1,0) -> 0.2708785 | E7: =IFERROR((' Forecasted FS>'!E48/' Forecasted FS>'!D48)-1,0) -> 0.13780359 | F7: =IFERROR((' Forecasted FS>'!F48/' Forecasted FS>'!E48)-1,0) -> 0.10315902 | G7: =IFERROR((' Forecasted FS>'!G48/' Forecasted FS>'!F48)-1,0) -> 0.027244782 | H7: =IFERROR((' Forecasted FS>'!H48/' Forecasted FS>'!G48)-1,0) -> 0.084322928 | I7: =IFERROR((' Forecasted FS>'!I48/' Forecasted FS>'!H48)-1,0) -> 0.085812224 | K7: =IFERROR(AVERAGE(D7:I7),0) -> 0.11820351 | L7: =IFERROR(MEDIAN(C7:I7),0) -> 0.094485623
B8: Net Profit Growth | D8: =IFERROR((' Forecasted FS>'!D30/' Forecasted FS>'!C30)-1,0) -> 0.27197459 | E8: =IFERROR((' Forecasted FS>'!E30/' Forecasted FS>'!D30)-1,0) -> 0.13869898 | F8: =IFERROR((' Forecasted FS>'!F30/' Forecasted FS>'!E30)-1,0) -> 0.10088082 | G8: =IFERROR((' Forecasted FS>'!G30/' Forecasted FS>'!F30)-1,0) -> 0.021423206 | H8: =IFERROR((' Forecasted FS>'!H30/' Forecasted FS>'!G30)-1,0) -> 0.087316558 | I8: =IFERROR((' Forecasted FS>'!I30/' Forecasted FS>'!H30)-1,0) -> 0.086861915 | K8: =IFERROR(AVERAGE(D8:I8),0) -> 0.11785934 | L8: =IFERROR(MEDIAN(C8:I8),0) -> 0.094098689
B9: Dividend Growth | D9: =IFERROR((' Forecasted FS>'!D44/' Forecasted FS>'!C44)-1,0) -> 0.54369512 | E9: =IFERROR((' Forecasted FS>'!E44/' Forecasted FS>'!D44)-1,0) -> 0.14865158 | F9: =IFERROR((' Forecasted FS>'!F44/' Forecasted FS>'!E44)-1,0) -> 0.096761529 | G9: =IFERROR((' Forecasted FS>'!G44/' Forecasted FS>'!F44)-1,0) -> 0.35349861 | H9: =IFERROR((' Forecasted FS>'!H44/' Forecasted FS>'!G44)-1,0) -> -0.064855345 | I9: =IFERROR((' Forecasted FS>'!I44/' Forecasted FS>'!H44)-1,0) -> 0.116149 | K9: =IFERROR(AVERAGE(D9:I9),0) -> 0.19898342 | L9: =IFERROR(MEDIAN(C9:I9),0) -> 0.13240029
B11: Gross Margin | C11: =IFERROR(' Forecasted FS>'!C16,0) -> 0.31479993 | D11: =IFERROR(' Forecasted FS>'!D16,0) -> 0.31831754 | E11: =IFERROR(' Forecasted FS>'!E16,0) -> 0.30271043 | F11: =IFERROR(' Forecasted FS>'!F16,0) -> 0.28539794 | G11: =IFERROR(' Forecasted FS>'!G16,0) -> 0.28398516 | H11: =IFERROR(' Forecasted FS>'!H16,0) -> 0.28471072 | I11: =IFERROR(' Forecasted FS>'!I16,0) -> 0.28207669 | K11: =IFERROR(AVERAGE(C11:I11),0) -> 0.29599977 | L11: =IFERROR(MEDIAN(C11:I11),0) -> 0.28539794
B12: EBITDA Margin | C12: =IFERROR(' Forecasted FS>'!C22,0) -> 0.24525559 | D12: =IFERROR(' Forecasted FS>'!D22,0) -> 0.27757982 | E12: =IFERROR(' Forecasted FS>'!E22,0) -> 0.25888475 | F12: =IFERROR(' Forecasted FS>'!F22,0) -> 0.23935898 | G12: =IFERROR(' Forecasted FS>'!G22,0) -> 0.2370339 | H12: =IFERROR(' Forecasted FS>'!H22,0) -> 0.24072642 | I12: =IFERROR(' Forecasted FS>'!I22,0) -> 0.23666387 | K12: =IFERROR(AVERAGE(C12:I12),0) -> 0.24792905 | L12: =IFERROR(MEDIAN(C12:I12),0) -> 0.24072642
B13: EBIT Margin | C13: =IFERROR(' Forecasted FS>'!C49,0) -> 0.2133912 | D13: =IFERROR(' Forecasted FS>'!D49,0) -> 0.2450633 | E13: =IFERROR(' Forecasted FS>'!E49,0) -> 0.23030886 | F13: =IFERROR(' Forecasted FS>'!F49,0) -> 0.21057186 | G13: =IFERROR(' Forecasted FS>'!G49,0) -> 0.20659205 | H13: =IFERROR(' Forecasted FS>'!H49,0) -> 0.21120314 | I13: =IFERROR(' Forecasted FS>'!I49,0) -> 0.20922474 | K13: =IFERROR(AVERAGE(C13:I13),0) -> 0.21805074 | L13: =IFERROR(MEDIAN(C13:I13),0) -> 0.21120314
B14: EBT Margin | C14: =IFERROR(' Forecasted FS>'!C31,0) -> 0.21151876 | D14: =IFERROR(' Forecasted FS>'!D31,0) -> 0.24312246 | E14: =IFERROR(' Forecasted FS>'!E31,0) -> 0.22866468 | F14: =IFERROR(' Forecasted FS>'!F31,0) -> 0.20863682 | G14: =IFERROR(' Forecasted FS>'!G31,0) -> 0.20353355 | H14: =IFERROR(' Forecasted FS>'!H31,0) -> 0.20865084 | I14: =IFERROR(' Forecasted FS>'!I31,0) -> 0.20689617 | K14: =IFERROR(AVERAGE(C14:I14),0) -> 0.21586047 | L14: =IFERROR(MEDIAN(C14:I14),0) -> 0.20865084
B15: Net Profit Margin | C15: =IFERROR(' Forecasted FS>'!C37,0) -> 0.15239396 | D15: =IFERROR(' Forecasted FS>'!D37,0) -> 0.17141094 | E15: =IFERROR(' Forecasted FS>'!E37,0) -> 0.16319333 | F15: =IFERROR(' Forecasted FS>'!F37,0) -> 0.14585704 | G15: =IFERROR(' Forecasted FS>'!G37,0) -> 0.14015097 | H15: =IFERROR(' Forecasted FS>'!H37,0) -> 0.14203325 | I15: =IFERROR(' Forecasted FS>'!I37,0) -> 0.14800448 | K15: =IFERROR(AVERAGE(C15:I15),0) -> 0.15186342 | L15: =IFERROR(MEDIAN(C15:I15),0) -> 0.14800448
B17: SalesExpenses%Sales | C17: =IFERROR(' Forecasted FS>'!C19,0) -> 0.069544338 | D17: =IFERROR(' Forecasted FS>'!D19,0) -> 0.040737718 | E17: =IFERROR(' Forecasted FS>'!E19,0) -> 0.043825684 | F17: =IFERROR(' Forecasted FS>'!F19,0) -> 0.04603896 | G17: =IFERROR(' Forecasted FS>'!G19,0) -> 0.046951259 | H17: =IFERROR(' Forecasted FS>'!H19,0) -> 0.043984294 | I17: =IFERROR(' Forecasted FS>'!I19,0) -> 0.045412818 | K17: =IFERROR(AVERAGE(C17:I17),0) -> 0.048070724 | L17: =IFERROR(MEDIAN(C17:I17),0) -> 0.045412818
B18: Depreciation%Sales | C18: =IFERROR(' Forecasted FS>'!C28,0) -> 0.031864392 | D18: =IFERROR(' Forecasted FS>'!D28,0) -> 0.032516522 | E18: =IFERROR(' Forecasted FS>'!E28,0) -> 0.028575891 | F18: =IFERROR(' Forecasted FS>'!F28,0) -> 0.028787125 | G18: =IFERROR(' Forecasted FS>'!G28,0) -> 0.030441856 | H18: =IFERROR(' Forecasted FS>'!H28,0) -> 0.029523284 | I18: =IFERROR(' Forecasted FS>'!I28,0) -> 0.027439127 | K18: =IFERROR(AVERAGE(C18:I18),0) -> 0.029878314 | L18: =IFERROR(MEDIAN(C18:I18),0) -> 0.029523284
B19: OperatingIncome%Sales | C19: =IFERROR(C13,0) -> 0.2133912 | D19: =IFERROR(D13,0) -> 0.2450633 | E19: =IFERROR(E13,0) -> 0.23030886 | F19: =IFERROR(F13,0) -> 0.21057186 | G19: =IFERROR(G13,0) -> 0.20659205 | H19: =IFERROR(H13,0) -> 0.21120314 | I19: =IFERROR(I13,0) -> 0.20922474 | K19: =IFERROR(AVERAGE(C19:I19),0) -> 0.21805074 | L19: =IFERROR(MEDIAN(C19:I19),0) -> 0.21120314
B21: Return on Capital Employed | C21: =(' Forecasted FS>'!C21-' Forecasted FS>'!C27)/(SUM(' Forecasted FS>'!C52:C54)) -> 0.27644365 | D21: =(' Forecasted FS>'!D21-' Forecasted FS>'!D27)/(SUM(' Forecasted FS>'!D52:D54)) -> 0.30145943 | E21: =(' Forecasted FS>'!E21-' Forecasted FS>'!E27)/(SUM(' Forecasted FS>'!E52:E54)) -> 0.34661734 | F21: =(' Forecasted FS>'!F21-' Forecasted FS>'!F27)/(SUM(' Forecasted FS>'!F52:F54)) -> 0.3692089 | G21: =(' Forecasted FS>'!G21-' Forecasted FS>'!G27)/(SUM(' Forecasted FS>'!G52:G54)) -> 0.32906971 | H21: =(' Forecasted FS>'!H21-' Forecasted FS>'!H27)/(SUM(' Forecasted FS>'!H52:H54)) -> 0.33085684 | I21: =(' Forecasted FS>'!I21-' Forecasted FS>'!I27)/(SUM(' Forecasted FS>'!I52:I54)) -> 0.36635041 | K21: =IFERROR(AVERAGE(C21:I21),0) -> 0.33142947 | L21: =IFERROR(MEDIAN(C21:I21),0) -> 0.33085684
B22: Retained Earnings% | C22: =IFERROR(' Forecasted FS>'!C47,0) -> 0.46321191 | D22: =IFERROR(' Forecasted FS>'!D47,0) -> 0.33401463 | E22: =IFERROR(' Forecasted FS>'!E47,0) -> 0.3447383 | F22: =IFERROR(' Forecasted FS>'!F47,0) -> 0.34277573 | G22: =IFERROR(' Forecasted FS>'!G47,0) -> 0.11532711 | H22: =IFERROR(' Forecasted FS>'!H47,0) -> 0.22990065 | I22: =IFERROR(' Forecasted FS>'!I47,0) -> 0.26514126 | K22: =IFERROR(AVERAGE(C22:I22),0) -> 0.29930137 | L22: =IFERROR(MEDIAN(C22:I22),0) -> 0.33401463
B23: Return on Equity% | C23: =IFERROR(' Forecasted FS>'!C36/(SUM(' Forecasted FS>'!C52:C53)),0) -> 0.21139801 | D23: =IFERROR(' Forecasted FS>'!D36/(SUM(' Forecasted FS>'!D52:D53)),0) -> 0.22556352 | E23: =IFERROR(' Forecasted FS>'!E36/(SUM(' Forecasted FS>'!E52:E53)),0) -> 0.26345056 | F23: =IFERROR(' Forecasted FS>'!F36/(SUM(' Forecasted FS>'!F52:F53)),0) -> 0.28388611 | G23: =IFERROR(' Forecasted FS>'!G36/(SUM(' Forecasted FS>'!G52:G53)),0) -> 0.24441645 | H23: =IFERROR(' Forecasted FS>'!H36/(SUM(' Forecasted FS>'!H52:H53)),0) -> 0.24160387 | I23: =IFERROR(' Forecasted FS>'!I36/(SUM(' Forecasted FS>'!I52:I53)),0) -> 0.284765 | K23: =IFERROR(AVERAGE(C23:I23),0) -> 0.25072622 | L23: =IFERROR(MEDIAN(C23:I23),0) -> 0.24441645
B24: Self Sustained Growth Rate | C24: =IFERROR(C22*C23,0) -> 0.097922078 | D24: =IFERROR(D22*D23,0) -> 0.075341515 | E24: =IFERROR(E22*E23,0) -> 0.0908215 | F24: =IFERROR(F22*F23,0) -> 0.097309268 | G24: =IFERROR(G22*G23,0) -> 0.028187843 | H24: =IFERROR(H22*H23,0) -> 0.055544887 | I24: =IFERROR(I22*I23,0) -> 0.075502951 | K24: =IFERROR(AVERAGE(C24:I24),0) -> 0.07437572 | L24: =IFERROR(MEDIAN(C24:I24),0) -> 0.075502951
B25: Interest Coverage Ratio | C25: =' Forecasted FS>'!C21/' Forecasted FS>'!C24 -> 130.98235 | D25: =' Forecasted FS>'!D21/' Forecasted FS>'!D24 -> 143.02051 | E25: =' Forecasted FS>'!E21/' Forecasted FS>'!E24 -> 157.455 | F25: =' Forecasted FS>'!F21/' Forecasted FS>'!F24 -> 123.69718 | G25: =' Forecasted FS>'!G21/' Forecasted FS>'!G24 -> 77.5 | H25: =' Forecasted FS>'!H21/' Forecasted FS>'!H24 -> 94.317308 | I25: =' Forecasted FS>'!I21/' Forecasted FS>'!I24 -> 101.63462 | K25: =IFERROR(AVERAGE(C25:I25),0) -> 118.37242 | L25: =IFERROR(MEDIAN(C25:I25),0) -> 123.69718
B27: Debtor Turnover Ratio | C27: =' Forecasted FS>'!C9/' Forecasted FS>'!C64 -> 4.9110726 | D27: =' Forecasted FS>'!D9/' Forecasted FS>'!D64 -> 5.207422 | E27: =' Forecasted FS>'!E9/' Forecasted FS>'!E64 -> 5.3591065 | F27: =' Forecasted FS>'!F9/' Forecasted FS>'!F64 -> 5.7727738 | G27: =' Forecasted FS>'!G9/' Forecasted FS>'!G64 -> 5.0895903 | H27: =' Forecasted FS>'!H9/' Forecasted FS>'!H64 -> 5.2310803 | I27: =' Forecasted FS>'!I9/' Forecasted FS>'!I64 -> 5.0703866 | K27: =IFERROR(AVERAGE(C27:I27),0) -> 5.2344903 | L27: =IFERROR(MEDIAN(C27:I27),0) -> 5.207422
B28: Creditor Turnover Ratio | C28: =' Forecasted FS>'!C9/' Forecasted FS>'!C55 -> 4.1806419 | D28: =' Forecasted FS>'!D9/' Forecasted FS>'!D55 -> 3.8889878 | E28: =' Forecasted FS>'!E9/' Forecasted FS>'!E55 -> 3.3878568 | F28: =' Forecasted FS>'!F9/' Forecasted FS>'!F55 -> 3.5893128 | G28: =' Forecasted FS>'!G9/' Forecasted FS>'!G55 -> 3.8859527 | H28: =' Forecasted FS>'!H9/' Forecasted FS>'!H55 -> 3.7254857 | I28: =' Forecasted FS>'!I9/' Forecasted FS>'!I55 -> 3.4184845 | K28: =IFERROR(AVERAGE(C28:I28),0) -> 3.725246 | L28: =IFERROR(MEDIAN(C28:I28),0) -> 3.7254857
B29: Inventory Turnover | C29: =IFERROR(' Forecasted FS>'!C9/' Forecasted FS>'!C65,0) -> 0 | D29: =IFERROR(' Forecasted FS>'!D9/' Forecasted FS>'!D65,0) -> 0 | E29: =IFERROR(' Forecasted FS>'!E9/' Forecasted FS>'!E65,0) -> 0 | F29: =IFERROR(' Forecasted FS>'!F9/' Forecasted FS>'!F65,0) -> 0 | G29: =IFERROR(' Forecasted FS>'!G9/' Forecasted FS>'!G65,0) -> 0 | H29: =IFERROR(' Forecasted FS>'!H9/' Forecasted FS>'!H65,0) -> 0 | I29: =IFERROR(' Forecasted FS>'!I9/' Forecasted FS>'!I65,0) -> 0 | K29: =IFERROR(AVERAGE(C29:I29),0) -> 0 | L29: =IFERROR(MEDIAN(C29:I29),0) -> 0
B30: Fixed Asset Turnover | C30: =' Forecasted FS>'!C9/' Forecasted FS>'!C58 -> 3.8165118 | D30: =' Forecasted FS>'!D9/' Forecasted FS>'!D58 -> 3.939306 | E30: =' Forecasted FS>'!E9/' Forecasted FS>'!E58 -> 4.7147674 | F30: =' Forecasted FS>'!F9/' Forecasted FS>'!F58 -> 5.0219675 | G30: =' Forecasted FS>'!G9/' Forecasted FS>'!G58 -> 5.5633191 | H30: =' Forecasted FS>'!H9/' Forecasted FS>'!H58 -> 5.2643648 | I30: =' Forecasted FS>'!I9/' Forecasted FS>'!I58 -> 5.2901984 | K30: =IFERROR(AVERAGE(C30:I30),0) -> 4.8014907 | L30: =IFERROR(MEDIAN(C30:I30),0) -> 5.0219675
B31: Capital Turnover Ratio | C31: =' Forecasted FS>'!C9/' Forecasted FS>'!C52 -> 42.78558 | D31: =' Forecasted FS>'!D9/' Forecasted FS>'!D52 -> 47.303202 | E31: =' Forecasted FS>'!E9/' Forecasted FS>'!E52 -> 57.979504 | F31: =' Forecasted FS>'!F9/' Forecasted FS>'!F52 -> 70.936201 | G31: =' Forecasted FS>'!G9/' Forecasted FS>'!G52 -> 74.200869 | H31: =' Forecasted FS>'!H9/' Forecasted FS>'!H52 -> 78.625181 | I31: =' Forecasted FS>'!I9/' Forecasted FS>'!I52 -> 88.26581 | K31: =IFERROR(AVERAGE(C31:I31),0) -> 65.72805 | L31: =IFERROR(MEDIAN(C31:I31),0) -> 70.936201
B33: Debtor Days | C33: =365/C27 -> 74.321849 | D33: =365/D27 -> 70.092265 | E33: =365/E27 -> 68.108368 | F33: =365/F27 -> 63.227837 | G33: =365/G27 -> 71.715006 | H33: =365/H27 -> 69.775262 | I33: =365/I27 -> 71.986622 | K33: =IFERROR(AVERAGE(C33:I33),0) -> 69.889601 | L33: =IFERROR(MEDIAN(C33:I33),0) -> 70.092265
B34: Payable Days | C34: =365/C28 -> 87.307167 | D34: =365/D28 -> 93.854756 | E34: =365/E28 -> 107.73773 | F34: =365/F28 -> 101.69078 | G34: =365/G28 -> 93.92806 | H34: =365/H28 -> 97.973802 | I34: =365/I28 -> 106.77246 | K34: =IFERROR(AVERAGE(C34:I34),0) -> 98.466393 | L34: =IFERROR(MEDIAN(C34:I34),0) -> 97.973802
B35: Inventory Days | C35: =IFERROR(365/C29,0) -> 0 | D35: =IFERROR(365/D29,0) -> 0 | E35: =IFERROR(365/E29,0) -> 0 | F35: =IFERROR(365/F29,0) -> 0 | G35: =IFERROR(365/G29,0) -> 0 | H35: =IFERROR(365/H29,0) -> 0 | I35: =IFERROR(365/I29,0) -> 0 | K35: =IFERROR(AVERAGE(C35:I35),0) -> 0 | L35: =IFERROR(MEDIAN(C35:I35),0) -> 0
B36: Cash Conversion Cycle (in days) | C36: =C33+C35-C34 -> -12.985318 | D36: =D33+D35-D34 -> -23.762491 | E36: =E33+E35-E34 -> -39.62936 | F36: =F33+F35-F34 -> -38.462938 | G36: =G33+G35-G34 -> -22.213054 | H36: =H33+H35-H34 -> -28.19854 | I36: =I33+I35-I34 -> -34.785838 | K36: =IFERROR(AVERAGE(C36:I36),0) -> -28.576791 | L36: =IFERROR(MEDIAN(C36:I36),0) -> -28.19854
B38: CFO/Sales | C38: =' Forecasted FS>'!C82/' Forecasted FS>'!C9 -> 0.18727627 | D38: =' Forecasted FS>'!D82/' Forecasted FS>'!D9 -> 0.23114898 | E38: =' Forecasted FS>'!E82/' Forecasted FS>'!E9 -> 0.19635649 | F38: =' Forecasted FS>'!F82/' Forecasted FS>'!F9 -> 0.15307937 | G38: =' Forecasted FS>'!G82/' Forecasted FS>'!G9 -> 0.16405284 | H38: =' Forecasted FS>'!H82/' Forecasted FS>'!H9 -> 0.21899503 | I38: =' Forecasted FS>'!I82/' Forecasted FS>'!I9 -> 0.1902379 | K38: =IFERROR(AVERAGE(C38:I38),0) -> 0.19159241 | L38: =IFERROR(MEDIAN(C38:I38),0) -> 0.1902379
B39: CFO/Total Assets | C39: =' Forecasted FS>'!C9/' Forecasted FS>'!C69 -> 0.98900871 | D39: =' Forecasted FS>'!D9/' Forecasted FS>'!D69 -> 0.93452763 | E39: =' Forecasted FS>'!E9/' Forecasted FS>'!E69 -> 1.0420804 | F39: =' Forecasted FS>'!F9/' Forecasted FS>'!F69 -> 1.1779431 | G39: =' Forecasted FS>'!G9/' Forecasted FS>'!G69 -> 1.1297603 | H39: =' Forecasted FS>'!H9/' Forecasted FS>'!H69 -> 1.1028113 | I39: =' Forecasted FS>'!I9/' Forecasted FS>'!I69 -> 1.1578995 | K39: =IFERROR(AVERAGE(C39:I39),0) -> 1.0762901 | L39: =IFERROR(MEDIAN(C39:I39),0) -> 1.1028113
B40: CFO/Total Debt | C40: =' Forecasted FS>'!C9/(SUM(' Forecasted FS>'!C54:C55)) -> 3.4455787 | D40: =' Forecasted FS>'!D9/(SUM(' Forecasted FS>'!D54:D55)) -> 3.2243902 | E40: =' Forecasted FS>'!E9/(SUM(' Forecasted FS>'!E54:E55)) -> 2.9396795 | F40: =' Forecasted FS>'!F9/(SUM(' Forecasted FS>'!F54:F55)) -> 2.9837362 | G40: =' Forecasted FS>'!G9/(SUM(' Forecasted FS>'!G54:G55)) -> 3.2078741 | H40: =' Forecasted FS>'!H9/(SUM(' Forecasted FS>'!H54:H55)) -> 3.1358101 | I40: =' Forecasted FS>'!I9/(SUM(' Forecasted FS>'!I54:I55)) -> 2.9079042 | K40: =IFERROR(AVERAGE(C40:I40),0) -> 3.1207104 | L40: =IFERROR(MEDIAN(C40:I40),0) -> 3.1358101

Sheet Forecasted Key Drivers
B2: ='Raw Data Sheet'!B1& " - "& ' Forecasted FS>'!B9& " Forecasting" -> INFOSYS LTD - Sales Forecasting | G2: ='Raw Data Sheet'!B1 & "-" & ' Forecasted FS>'!B21& " Forecasting" -> INFOSYS LTD-EBITDA Forecasting | L2: ='Raw Data Sheet'!B1& "-" & ' Forecasted FS>'!B41& " Forecasting" -> INFOSYS LTD-EPS Forecasting
B3: Year Weight | C3: Year | D3: Sales | E3: Sales Growth | G3: Year Weight | H3: Year | I3: EBITDA | J3: EBITDA Growth | L3: Year Weight | M3: Year | N3: EPS | O3: EPS Growth
B4: 1 | C4: =' Forecasted FS>'!C5 -> 43921 | D4: {=TRANSPOSE('Raw Data Sheet'!E17:K17)} -> 90791 | G4: 1 | H4: =' Forecasted FS>'!C5 -> 43921 | I4: {=TRANSPOSE(' Forecasted FS>'!C21:J21)} -> 22267 | L4: 1 | M4: =' Forecasted FS>'!C5 -> 43921 | N4: {=TRANSPOSE(' Forecasted FS>'!C41:J41)} -> 32.486499
B5: =B4+1 -> 2 | C5: =C4+365 -> 44286 | D5: 100472 | E5: =D5/D4-1 -> 0.10662951 | G5: =G4+1 -> 2 | H5: =H4+365 -> 44286 | I5: 27889 | J5: =I5/I4-1 -> 0.25248125 | L5: =L4+1 -> 2 | M5: =M4+365 -> 44286 | N5: 40.420588 | O5: =N5/N4-1 -> 0.24422727
B6: =B5+1 -> 3 | C6: =C5+365 -> 44651 | D6: 121641 | E6: =D6/D5-1 -> 0.21069552 | G6: =G5+1 -> 3 | H6: =H5+365 -> 44651 | I6: 31491 | J6: =I6/I5-1 -> 0.12915486 | L6: =L5+1 -> 3 | M6: =M5+365 -> 44651 | N6: 47.189008 | O6: =N6/N5-1 -> 0.16744981
B7: =B6+1 -> 4 | C7: =C6+365 -> 45016 | D7: 146767 | E7: =D7/D6-1 -> 0.20655864 | G7: =G6+1 -> 4 | H7: =H6+365 -> 45016 | I7: 35130 | J7: =I7/I6-1 -> 0.11555683 | L7: =L6+1 -> 4 | M7: =M6+365 -> 45016 | N7: 51.60054 | O7: =N7/N6-1 -> 0.093486431
B8: =B7+1 -> 5 | C8: =C7+365 -> 45381 | D8: 153670 | E8: =D8/D7-1 -> 0.047033734 | G8: =G7+1 -> 5 | H8: =H7+365 -> 45381 | I8: 36425 | J8: =I8/I7-1 -> 0.03686308 | L8: =L7+1 -> 5 | M8: =M7+365 -> 45381 | N8: 51.885133 | O8: =N8/N7-1 -> 0.0055153183
B9: =B8+1 -> 6 | C9: =C8+365 -> 45746 | D9: 162990 | E9: =D9/D8-1 -> 0.060649444 | G9: =G8+1 -> 6 | H9: =H8+365 -> 45746 | I9: 39236 | J9: =I9/I8-1 -> 0.077172272 | L9: =L8+1 -> 6 | M9: =M8+365 -> 45746 | N9: 55.73881 | O9: =N9/N8-1 -> 0.074273236
B10: =B9+1 -> 7 | C10: =C9+365 -> 46111 | D10: 178650 | E10: =D10/D9-1 -> 0.096079514 | G10: =G9+1 -> 7 | H10: =H9+365 -> 46111 | I10: 42280 | J10: =I10/I9-1 -> 0.077581813 | L10: =L9+1 -> 7 | M10: =M9+365 -> 46111 | N10: 65.196272 | O10: =N10/N9-1 -> 0.16967463
B11: =B10+1 -> 8 | C11: =C10+365 -> 46476 | D11: =FORECAST(B11,$D$4:$D$10,$B$4:$B$10) -> 196517.57 | E11: =D11/D10-1 -> 0.10001439 | G11: =G10+1 -> 8 | H11: =H10+365 -> 46476 | I11: =FORECAST(G11,$I$4:$I$10,$G$4:$G$10) -> 46055 | J11: =I11/I10-1 -> 0.089285714 | L11: =L10+1 -> 8 | M11: =M10+365 -> 46476 | N11: =FORECAST(L11,$N$4:$N$10,$L$4:$L$10) -> 68.282677 | O11: =N11/N10-1 -> 0.047340207
B12: =B11+1 -> 9 | C12: =C11+365 -> 46841 | D12: =FORECAST(B12,$D$4:$D$10,$B$4:$B$10) -> 211540.5 | E12: =D12/D11-1 -> 0.076445727 | G12: =G11+1 -> 9 | H12: =H11+365 -> 46841 | I12: =FORECAST(G12,$I$4:$I$10,$G$4:$G$10) -> 49185.964 | J12: =I12/I11-1 -> 0.067983157 | L12: =L11+1 -> 9 | M12: =M11+365 -> 46841 | N12: =FORECAST(L12,$N$4:$N$10,$L$4:$L$10) -> 73.049173 | O12: =N12/N11-1 -> 0.069805347
B13: =B12+1 -> 10 | C13: =C12+365 -> 47206 | D13: =FORECAST(B13,$D$4:$D$10,$B$4:$B$10) -> 226563.43 | E13: =D13/D12-1 -> 0.071016796 | G13: =G12+1 -> 10 | H13: =H12+365 -> 47206 | I13: =FORECAST(G13,$I$4:$I$10,$G$4:$G$10) -> 52316.929 | J13: =I13/I12-1 -> 0.063655645 | L13: =L12+1 -> 10 | M13: =M12+365 -> 47206 | N13: =FORECAST(L13,$N$4:$N$10,$L$4:$L$10) -> 77.815669 | O13: =N13/N12-1 -> 0.065250513
B14: =B13+1 -> 11 | C14: =C13+365 -> 47571 | D14: =FORECAST(B14,$D$4:$D$10,$B$4:$B$10) -> 241586.36 | E14: =D14/D13-1 -> 0.066307827 | G14: =G13+1 -> 11 | H14: =H13+365 -> 47571 | I14: =FORECAST(G14,$I$4:$I$10,$G$4:$G$10) -> 55447.893 | J14: =I14/I13-1 -> 0.059846103 | L14: =L13+1 -> 11 | M14: =M13+365 -> 47571 | N14: =FORECAST(L14,$N$4:$N$10,$L$4:$L$10) -> 82.582165 | O14: =N14/N13-1 -> 0.061253679
B15: =B14+1 -> 12 | C15: =C14+365 -> 47936 | D15: =FORECAST(B15,$D$4:$D$10,$B$4:$B$10) -> 256609.29 | E15: =D15/D14-1 -> 0.062184507 | G15: =G14+1 -> 12 | H15: =H14+365 -> 47936 | I15: =FORECAST(G15,$I$4:$I$10,$G$4:$G$10) -> 58578.857 | J15: =I15/I14-1 -> 0.056466786 | L15: =L14+1 -> 12 | M15: =M14+365 -> 47936 | N15: =FORECAST(L15,$N$4:$N$10,$L$4:$L$10) -> 87.348661 | O15: =N15/N14-1 -> 0.057718225

Sheet Raw Data Sheet
A1: COMPANY NAME | B1: INFOSYS LTD
A2: LATEST VERSION | B2: 2.1 | E2: PLEASE DO NOT MAKE ANY CHANGES TO THIS SHEET
A3: CURRENT VERSION | B3: 2.1
A5: META
A6: Number of shares | B6: =IF(B9>0, B9/B8, 0) -> 404.06048
A7: Face Value | B7: 5
A8: Current Price | B8: 1040.9
A9: Market Capitalization | B9: 420586.55
A15: PROFIT & LOSS
A16: Report Date | B16: 42825 | C16: 43190 | D16: 43555 | E16: 43921 | F16: 44286 | G16: 44651 | H16: 45016 | I16: 45382 | J16: 45747 | K16: 46112
A17: Sales | B17: 68484 | C17: 70522 | D17: 82675 | E17: 90791 | F17: 100472 | G17: 121641 | H17: 146767 | I17: 153670 | J17: 162990 | K17: 178650
A18: Raw Material Cost
A19: Change in Inventory
A20: Power and Fuel | B20: 228 | C20: 207 | D20: 221 | E20: 229 | F20: 143 | G20: 132 | H20: 176 | I20: 199 | J20: 222 | K20: 223
A21: Other Mfr. Exp | B21: 6712 | C21: 7286 | D21: 9902 | E21: 11086 | F21: 12800 | G21: 20690 | H21: 26330 | I21: 27195 | J21: 30395 | K21: 32922
A22: Employee Cost | B22: 37669 | C22: 38902 | D22: 45323 | E22: 50895 | F22: 55547 | G22: 63997 | H22: 78374 | I22: 82636 | J22: 85968 | K22: 95112
A23: Selling and admin | B23: 4584 | C23: 4585 | D23: 5553 | E23: 5375 | F23: 3194 | G23: 4305 | H23: 5300 | I23: 5705 | J23: 6039 | K23: 6784
A24: Other Expenses | B24: 687 | C24: 720 | D24: 1506 | E24: 939 | F24: 899 | G24: 1026 | H24: 1457 | I24: 1510 | J24: 1130 | K24: 1329
A25: Other Income | B25: 3050 | C25: 3311 | D25: 2882 | E25: 2803 | F25: 2201 | G25: 2295 | H25: 2701 | I25: 4711 | J25: 3600 | K25: 3033
A26: Depreciation | B26: 1703 | C26: 1863 | D26: 2011 | E26: 2893 | F26: 3267 | G26: 3476 | H26: 4225 | I26: 4678 | J26: 4812 | K26: 4902
A27: Interest | E27: 170 | F27: 195 | G27: 200 | H27: 284 | I27: 470 | J27: 416 | K27: 416
A28: Profit before tax | B28: 19951 | C28: 20270 | D28: 21041 | E28: 22007 | F28: 26628 | G28: 30110 | H28: 33322 | I28: 35988 | J28: 37608 | K28: 39995
A29: Tax | B29: 5598 | C29: 4241 | D29: 5631 | E29: 5368 | F29: 7205 | G29: 7964 | H29: 9214 | I29: 9740 | J29: 10858 | K29: 10521
A30: Net profit | B30: 14353 | C30: 16029 | D30: 15404 | E30: 16594 | F30: 19351 | G30: 22110 | H30: 24095 | I30: 26233 | J30: 26713 | K30: 29440
A31: Dividend Amount | B31: 5891.6 | C31: 9465.6 | D31: 9222.5 | E31: 7427 | F31: 11469.6 | G31: 13007.6 | H31: 14069.2 | I31: 19053.2 | J31: 17827.8 | K31: 19430.4
A40: Quarters
A41: Report Date | B41: 45382 | C41: 45473 | D41: 45565 | E41: 45657 | F41: 45747 | G41: 45838 | H41: 45930 | I41: 46022 | J41: 46112 | K41: 46203
A42: Sales | B42: 37923 | C42: 39315 | D42: 40986 | E42: 41764 | F42: 40925 | G42: 42279 | H42: 44490 | I42: 45479 | J42: 46402 | K42: 48211
A43: Expenses | B43: 29139 | C43: 29878 | D43: 31177 | E43: 31649 | F43: 31051 | G43: 32336 | H43: 33955 | I43: 34845 | J43: 35235 | K43: 36802
A44: Other Income | B44: 2729 | C44: 838 | D44: 712 | E44: 859 | F44: 1190 | G44: 1042 | H44: 982 | I44: -150 | J44: 1159 | K44: 984
A45: Depreciation | B45: 1163 | C45: 1149 | D45: 1160 | E45: 1203 | F45: 1299 | G45: 1140 | H45: 1182 | I45: 1155 | J45: 1424 | K45: 1246
A46: Interest | B46: 110 | C46: 105 | D46: 108 | E46: 101 | F46: 102 | G46: 105 | H46: 106 | I46: 100 | J46: 105 | K46: 119
A47: Profit before tax | B47: 10240 | C47: 9021 | D47: 9253 | E47: 9670 | F47: 9663 | G47: 9740 | H47: 10229 | I47: 9229 | J47: 10797 | K47: 11028
A48: Tax | B48: 2265 | C48: 2647 | D48: 2737 | E48: 2848 | F48: 2625 | G48: 2816 | H48: 2854 | I48: 2563 | J48: 2288 | K48: 3253
A49: Net profit | B49: 7969 | C49: 6368 | D49: 6506 | E49: 6806 | F49: 7033 | G49: 6921 | H49: 7364 | I49: 6654 | J49: 8501 | K49: 7769
A50: Operating Profit | B50: 8784 | C50: 9437 | D50: 9809 | E50: 10115 | F50: 9874 | G50: 9943 | H50: 10535 | I50: 10634 | J50: 11167 | K50: 11409
A55: BALANCE SHEET
A56: Report Date | B56: 42825 | C56: 43190 | D56: 43555 | E56: 43921 | F56: 44286 | G56: 44651 | H56: 45016 | I56: 45382 | J56: 45747 | K56: 46112
A57: Equity Share Capital | B57: 1144 | C57: 1088 | D57: 2170 | E57: 2122 | F57: 2124 | G57: 2098 | H57: 2069 | I57: 2071 | J57: 2073 | K57: 2024
A58: Reserves | B58: 67838 | C58: 63835 | D58: 62778 | E58: 63328 | F58: 74227 | G58: 73252 | H58: 73338 | I58: 86045 | J58: 93745 | K58: 90828
A59: Borrowings | E59: 4633 | F59: 5325 | G59: 5474 | H59: 8299 | I59: 8359 | J59: 8227 | K59: 9176
A60: Other Liabilities | B60: 14166 | C60: 14426 | D60: 19118 | E60: 21717 | F60: 25835 | G60: 35905 | H60: 40890 | I60: 39545 | J60: 43750 | K60: 52260
A61: Total | B61: 83148 | C61: 79349 | D61: 84066 | E61: 91800 | F61: 107511 | G61: 116729 | H61: 124596 | I61: 136020 | J61: 147795 | K61: 154288
A62: Net Block | B62: 14179 | C62: 12574 | D62: 15710 | E62: 23789 | F62: 25505 | G62: 25800 | H62: 29225 | I62: 27622 | J62: 30961 | K62: 33770
A63: Capital Work in Progress | B63: 1365 | C63: 1606 | D63: 1388 | E63: 954 | F63: 922 | G63: 416 | H63: 288 | I63: 293 | J63: 814 | K63: 526
A64: Investments | B64: 16423 | C64: 12163 | D64: 11261 | E64: 8792 | F64: 14205 | G64: 20324 | H64: 19478 | I64: 24623 | J64: 23541 | K64: 21880
A65: Other Assets | B65: 51181 | C65: 53006 | D65: 55707 | E65: 58265 | F65: 66879 | G65: 70189 | H65: 75605 | I65: 83482 | J65: 92479 | K65: 98112
A66: Total | B66: 83148 | C66: 79349 | D66: 84066 | E66: 91800 | F66: 107511 | G66: 116729 | H66: 124596 | I66: 136020 | J66: 147795 | K66: 154288
A67: Receivables | B67: 12322 | C67: 13142 | D67: 14827 | E67: 18487 | F67: 19294 | G67: 22698 | H67: 25424 | I67: 30193 | J67: 31158 | K67: 35234
A68: Inventory
A69: Cash & Bank | B69: 22625 | C69: 19818 | D69: 19568 | E69: 18649 | F69: 24714 | G69: 17472 | H69: 12173 | I69: 14786 | J69: 24455 | K69: 22201
A70: No. of Equity Shares | B70: 2285655150 | C70: 2173312301 | D70: 4335954462 | E70: 4240753210 | F70: 4245146114 | G70: 4193012929 | H70: 4136387925 | I70: 4139950635 | J70: 4143607528 | K70: 4046940812
A71: New Bonus Shares | D71: 2184191490
A72: Face value | B72: 5 | C72: 5 | D72: 5 | E72: 5 | F72: 5 | G72: 5 | H72: 5 | I72: 5 | J72: 5 | K72: 5
A80: CASH FLOW:
A81: Report Date | B81: 42825 | C81: 43190 | D81: 43555 | E81: 43921 | F81: 44286 | G81: 44651 | H81: 45016 | I81: 45382 | J81: 45747 | K81: 46112
A82: Cash from Operating Activity | B82: 11531 | C82: 13218 | D82: 14841 | E82: 17003 | F82: 23224 | G82: 23885 | H82: 22467 | I82: 25210 | J82: 35694 | K82: 33986
A83: Cash from Investing Activity | B83: -14664 | C83: 4533 | D83: -632 | E83: -331 | F83: -7373 | G83: -6485 | H83: -1071 | I83: -5093 | J83: -1864 | K83: 3546
A84: Cash from Financing Activity | B84: -6939 | C84: -20505 | D84: -14512 | E84: -17591 | F84: -9786 | G84: -24642 | H84: -26695 | I84: -17504 | J84: -24161 | K84: -39786
A85: Net Cash Flow | B85: -10072 | C85: -2754 | D85: -303 | E85: -919 | F85: 6065 | G85: -7242 | H85: -5299 | I85: 2613 | J85: 9669 | K85: -2254
A90: PRICE: | B90: 511.13 | C90: 565.9 | D90: 743.85 | E90: 641.5 | F90: 1368.05 | G90: 1906.85 | H90: 1427.95 | I90: 1498.05 | J90: 1570.65 | K90: 1250.6
A92: DERIVED:
A93: Adjusted Equity Shares in Cr | B93: 459.39 | C93: 436.82 | D93: 436.89 | E93: 425.9 | F93: 426.07 | G93: 420.67 | H93: 414.86 | I93: 415.09 | J93: 415.33 | K93: 405.56

Sheet Raw Cash Flow 
B2: Particulars | C2: 42064 | D2: 42430 | E2: 42795 | F2: 43160 | G2: 43525 | H2: 43891 | I2: 44256 | J2: 44621 | K2: 44986 | L2: 45352 | M2: 45717 | N2: 46082
A3: # | B3: Cash from Operating Activity - | C3: 8353 | D3: 10028 | E3: 11531 | F3: 13218 | G3: 14841 | H3: 17003 | I3: 23224 | J3: 23885 | K3: 22467 | L3: 25210 | M3: 35694 | N3: 33986
B4: Profit from operations | C4: 15946 | D4: 17839 | E4: 19340 | F4: 19963 | G4: 22126 | H4: 23920 | I4: 28845 | J4: 32921 | K4: 37605 | L4: 39523 | M4: 41591 | N4: 45273
B5: Receivables | C5: -1475 | D5: -1654 | E5: -1743 | F5: -1523 | G5: -2881 | H5: -3861 | I5: -1835 | J5: -7937 | K5: -7076 | L5: -2667 | M5: -1769 | N5: -5177
B6: Payables | C6: 0 | D6: 242 | E6: -19 | F6: 328 | G6: 916 | H6: -373 | I6: -245 | J6: 1489 | K6: -279 | L6: 91 | M6: 176 | N6: -26
B7: Loans Advances | C7: -221 | D7: -1134 | E7: 0 | F7: 0 | G7: 0 | H7: 0 | I7: -534 | J7: -1914 | K7: -3108 | L7: -1172 | M7: -1024 | N7: -2645
B8: Other WC items | C8: 854 | D8: 600 | E8: -394 | F8: 1279 | G8: 1512 | H8: 1867 | I8: 3382 | J8: 6938 | K8: 4119 | L8: -1334 | M8: 2322 | N8: 5209
B9: Working capital changes | C9: -842 | D9: -1946 | E9: -2156 | F9: 84 | G9: -453 | H9: -2367 | I9: 768 | J9: -1424 | K9: -6344 | L9: -5082 | M9: -295 | N9: -2639
B10: Direct taxes | C10: -6751 | D10: -5865 | E10: -5653 | F10: -6829 | G10: -6832 | H10: -4550 | I10: -6389 | J10: -7612 | K10: -8794 | L10: -9231 | M10: -5602 | N10: -8648
A11: # | B11: Cash from Investing Activity - | C11: 999 | D11: -885 | E11: -14664 | F11: 4533 | G11: -632 | H11: -331 | I11: -7373 | J11: -6485 | K11: -1071 | L11: -5093 | M11: -1864 | N11: 3546
B12: Fixed assets purchased | C12: -2247 | D12: -2723 | E12: -2760 | F12: -1998 | G12: -2445 | H12: -3307 | I12: -2107 | J12: -2161 | K12: -2579 | L12: -2201 | M12: -2237 | N12: -2727
B13: Investments purchased | C13: -23923 | D13: -24577 | E13: -66410 | F13: -69159 | G13: -79410 | H13: -37482 | I13: -46738 | J13: -59951 | K13: -75800 | L13: -78092 | M13: -82742 | N13: -82617
B14: Investments sold | C14: 25253 | D14: 24980 | E14: 52048 | F14: 74003 | G14: 78098 | H14: 38861 | I14: 40381 | J14: 57356 | K14: 76722 | L14: 72930 | M14: 84877 | N14: 89699
B15: Interest received | C15: 2551 | D15: 2383 | E15: 0 | F15: 0 | G15: 0 | H15: 0 | I15: 0 | J15: 0 | K15: 0 | L15: 0 | M15: 0 | N15: 0
B16: Dividends received | C16: 0 | D16: 0 | E16: 2753 | F16: 1768 | G16: 1557 | H16: 1929 | I16: 1418 | J16: 1898 | K16: 1525 | L16: 1768 | M16: 2040 | N16: 2713
B17: Acquisition of companies | C17: -1376 | D17: -747 | E17: 0 | F17: 0 | G17: 0 | H17: 0 | I17: 0 | J17: 0 | K17: 0 | L17: 0 | M17: 0 | N17: 0
B18: Inter corporate deposits | C18: 0 | D18: -142 | E18: -164 | F18: -130 | G18: -24 | H18: -108 | I18: 0 | J18: 0 | K18: 0 | L18: 0 | M18: 0 | N18: 0
B19: Other investing items | C19: 741 | D19: -59 | E19: -131 | F19: 49 | G19: 1592 | H19: -224 | I19: -327 | J19: -3627 | K19: -939 | L19: 502 | M19: -3802 | N19: -3522
A20: # | B20: Cash from Financing Activity - | C20: -4935 | D20: -6813 | E20: -6939 | F20: -20505 | G20: -14512 | H20: -17591 | I20: -9786 | J20: -24642 | K20: -26695 | L20: -17504 | M20: -24161 | N20: -39786
B21: Proceeds from shares | C21: 0 | D21: 0 | E21: 0 | F21: 5 | G21: 6 | H21: 6 | I21: 15 | J21: 21 | K21: 35 | L21: 5 | M21: 6 | N21: 2
B22: Repayment of borrowings | C22: 0 | D22: 0 | E22: 0 | F22: 0 | G22: 0 | H22: 0 | I22: 0 | J22: 0 | K22: 0 | L22: 0 | M22: -985 | N22: 0
B23: Dividends paid | C23: -4935 | D23: -6813 | E23: -6939 | F23: -7464 | G23: -13705 | H23: -9548 | I23: -9137 | J23: -12731 | K23: -13653 | L23: -14731 | M23: -20289 | N23: -18656
B24: Financial liabilities | C24: 0 | D24: 0 | E24: 0 | F24: 0 | G24: 0 | H24: -571 | I24: -698 | J24: -915 | K24: -1231 | L24: -2024 | M24: -2355 | N24: -2824
B25: Other financing items | C25: 0 | D25: 0 | E25: 0 | F25: -13046 | G25: -813 | H25: -7478 | I25: 34 | J25: -11017 | K25: -11846 | L25: -754 | M25: -538 | N25: -18308
A26: # | B26: Net Cash Flow | C26: 4417 | D26: 2330 | E26: -10072 | F26: -2754 | G26: -303 | H26: -919 | I26: 6065 | J26: -7242 | K26: -5299 | L26: 2613 | M26: 9669 | N26: -2254
B27: Free Cash Flow | C27: 6106 | D27: 7305 | E27: 8771 | F27: 11220 | G27: 12396 | H27: 13696 | I27: 21117 | J27: 21724 | K27: 19888 | L27: 23009 | M27: 33457 | N27: 31259

Sheet WACC>
B2: Calculation Of WACC
B5: Weighted Average Cost of Capital
B7: All Figures are in INR(Crores) unless stated otherwise
B9: Peer Comps
H10: Debt/ | I10: Debt/ | J10: Levered | K10: Unlevered
B11: Name of the Comp | D11: Country | E11: Total Debt | F11: Total Equity | G11: Tax Rate 1 | H11: Equity | I11: Capital | J11: Beta 2 | K11: Beta 3
B13: ='Data - Comps'!C3 -> Infosys | D13: India | E13: ='Data - Comps'!F3 -> 8737 | F13: ='Data - Comps'!E3 -> 468958.99 | G13: 0.3 | H13: =E13/F13 -> 0.018630627 | I13: =E13/(E13+F13) -> 0.018289875 | J13: ='Infosys - Beta'!J8 -> 0.67533945 | K13: =J13/(1+(1-G13)*H13) -> 0.66664543
B14: ='Data - Comps'!C4 -> TCS | D14: India | E14: ='Data - Comps'!F4 -> 11283 | F14: ='Data - Comps'!E4 -> 885374.85 | G14: 0.3 | H14: =E14/F14 -> 0.012743755 | I14: =E14/(E14+F14) -> 0.012583395 | J14: ='TCS - Beta'!J8 -> -0.077447364 | K14: =J14/(1+(1-G14)*H14) -> -0.076762594
B15: ='Data - Comps'!C5 -> HCL Technologies | D15: India | E15: ='Data - Comps'!F5 -> 5215 | F15: ='Data - Comps'!E5 -> 364812.07 | G15: 0.3 | H15: =E15/F15 -> 0.014295031 | I15: =E15/(E15+F15) -> 0.014093563 | J15: ='HCL Technologies - Beta'!J8 -> 0.7844093 | K15: =J15/(1+(1-G15)*H15) -> 0.77663786
B16: ='Data - Comps'!C6 -> Wipro | D16: India | E16: ='Data - Comps'!F6 -> 20291 | F16: ='Data - Comps'!E6 -> 181880.46 | G16: 0.3 | H16: =E16/F16 -> 0.11156229 | I16: =E16/(E16+F16) -> 0.1003653 | J16: ='WIPRO - Beta'!J8 -> 1.4755079 | K16: =J16/(1+(1-G16)*H16) -> 1.3686269
B17: ='Data - Comps'!C7 -> Tech Mahindra | D17: India | E17: ='Data - Comps'!F7 -> 2186.2 | F17: ='Data - Comps'!E7 -> 161201.84 | G17: 0.3 | H17: =E17/F17 -> 0.01356188 | I17: =E17/(E17+F17) -> 0.013380416 | J17: ='Tech Mahindra - Beta'!J8 -> 0.6902984 | K17: =J17/(1+(1-G17)*H17) -> 0.68380681
F19: Average | G19: =AVERAGE(G13:G17) -> 0.3 | H19: =AVERAGE(H13:H17) -> 0.034158716 | I19: =AVERAGE(I13:I17) -> 0.031742511 | J19: =AVERAGE(J13:J17) -> 0.70962154 | K19: =AVERAGE(K13:K17) -> 0.68379088
F20: Median | G20: =MEDIAN(G13:G17) -> 0.3 | H20: =MEDIAN(H13:H17) -> 0.014295031 | I20: =MEDIAN(I13:I17) -> 0.014093563 | J20: =MEDIAN(J13:J17) -> 0.6902984 | K20: =MEDIAN(K13:K17) -> 0.68380681
B23: Cost of Debt | G23: Cost of Equity
B25: Pre-Tax Cost of Debt | E25: 0.1037 | G25: Risk Free Rate | K25: 0.0658
B26: Tax rate | E26: =G20 -> 0.3 | G26: Equity Risk Premium | K26: =Rm!G9-'WACC>'!K25 -> 0.098692308
B27: Post-Tax Cost of Debt | E27: =E25*(1-E26) -> 0.07259 | G27: Levered Beta 4 | K27: =K36 -> 0.69949894
G28: Cost of Equity | K28: =K25+K27*K26 -> 0.13483516
B31: Capital Structure | G31: Levered Beta
D33: Current | E33: Target | G33: Comps Median Unlevered Data | K33: =K20 -> 0.68380681
B34: Total Debt | C34: =E13 -> 8737 | D34: =C34/$C$36 -> 0.018289875 | E34: =I19 -> 0.031742511 | G34: Target Debt/Equity | K34: =E38 -> 0.03278313
B35: Market Capitalization | C35: =F13 -> 468958.99 | D35: =C35/$C$36 -> 0.98171012 | E35: =E36-E34 -> 0.96825749 | G35: Tax Rate | K35: =E26 -> 0.3
B36: Total Capital | C36: =SUM(C34:C35) -> 477695.99 | D36: =C36/$C$36 -> 1 | E36: =D36 -> 1 | G36: Levered Beta | K36: =K33*(1+(1-K35)*K34) -> 0.69949894
B38: Debt/Equity | D38: =D34/D35 -> 0.018630627 | E38: =E34/E35 -> 0.03278313 | G38: Weighted Average Cost of Capital
B40: Notes: | J40: Total Cost | K40: Total Weight
B41: 1. Tax Rate considered as marginal rate of country | G41: Debt | J41: =E27 -> 0.07259 | K41: =E34 -> 0.031742511
B42: 2. Levered Beta is based on monthly data | G42: Equity | J42: =K28 -> 0.13483516 | K42: =E35 -> 0.96825749
B43: 3. Unlevered Beta = Levered Beta/(1+(1-Tax rate)*Debt/Equity) | G43: Weighted Average Cost of Capital | K43: =SUMPRODUCT(J41:J42,K41:K42) -> 0.13285935
B44: 4. Levered Beta = UnLevered Beta*(1+(1-Tax rate)*Debt/Equity)

Sheet Data - Comps
B2: S.No. | C2: Name | D2: CMP Rs. | E2: Mar Cap Rs.Cr. | F2: Debt Rs.Cr. | G2: Debt / Eq
B3: 1 | C3: Infosys | D3: 1155.6 | E3: 468958.99 | F3: 8737 | G3: 0.1
B4: 2 | C4: TCS | D4: 2446.6 | E4: 885374.85 | F4: 11283 | G4: 0.11
B5: 3 | C5: HCL Technologies | D5: 1344.3 | E5: 364812.07 | F5: 5215 | G5: 0.07
B6: 4 | C6: Wipro | D6: 183.61 | E6: 181880.46 | F6: 20291 | G6: 0.23
B7: 5 | C7: Tech Mahindra | D7: 1644.2 | E7: 161201.84 | F7: 2186.2 | G7: 0.07
B9: Source: Screener.in

Sheet Infosys - Beta
B2: Source: Investing.com
B4: Regression Beta - 2 Years Weekly
B6: Infosys Weekly Returns | F6: NIFTY Returns | I6: Beta Drifting
B8: Date | C8: Closing Price | D8: Return | F8: Closing Price | G8: Return | I8: Levered Raw Beta | J8: =SLOPE(D10:D112,G10:G112) -> 0.67533945
B9: 07/28/2024 | C9: 1821.2 | F9: 24717.7 | I9: Raw Beta Weight | J9: 0.75
B10: 45390 | C10: 1770.75 | D10: =C10/C9-1 -> -0.027701515 | F10: 24367.5 | G10: =F10/F9-1 -> -0.014167985
B11: 45604 | C11: 1858.95 | D11: =C11/C10-1 -> 0.049809403 | F11: 24541.15 | G11: =F11/F10-1 -> 0.0071262953 | I11: Market Beta | J11: 1
B12: 08/18/2024 | C12: 1862.1 | D12: =C12/C11-1 -> 0.001694505 | F12: 24823.15 | G12: =F12/F11-1 -> 0.011490904 | I12: Market Beta Weight | J12: =100%-J9 -> 0.25
B13: 08/25/2024 | C13: 1943.7 | D13: =C13/C12-1 -> 0.043821492 | F13: 25235.9 | G13: =F13/F12-1 -> 0.016627624
B14: 45300 | C14: 1901.85 | D14: =C14/C13-1 -> -0.0215311 | F14: 24852.15 | G14: =F14/F13-1 -> -0.015206511 | I14: Adjusted Beta | J14: =(J8*J9)+(J11*J12) -> 0.75650459
B15: 45513 | C15: 1944.1 | D15: =C15/C14-1 -> 0.022215212 | F15: 25356.5 | G15: =F15/F14-1 -> 0.020294019
B16: 09/15/2024 | C16: 1905.75 | D16: =C16/C15-1 -> -0.019726352 | F16: 25790.95 | G16: =F16/F15-1 -> 0.017133674
B17: 09/22/2024 | C17: 1906.75 | D17: =C17/C16-1 -> 0.0005247278 | F17: 26178.95 | G17: =F17/F16-1 -> 0.015044037
B18: 09/29/2024 | C18: 1918.15 | D18: =C18/C17-1 -> 0.0059787597 | F18: 25014.6 | G18: =F18/F17-1 -> -0.044476574
B19: 45453 | C19: 1935.1 | D19: =C19/C18-1 -> 0.0088366395 | F19: 24964.25 | G19: =F19/F18-1 -> -0.0020128245
B20: 10/13/2024 | C20: 1879.6 | D20: =C20/C19-1 -> -0.028680688 | F20: 24854.05 | G20: =F20/F19-1 -> -0.0044143125
B21: 10/20/2024 | C21: 1862.05 | D21: =C21/C20-1 -> -0.009337093 | F21: 24180.8 | G21: =F21/F20-1 -> -0.027088141
B22: 10/27/2024 | C22: 1760.85 | D22: =C22/C21-1 -> -0.054348702 | F22: 24304.35 | G22: =F22/F21-1 -> 0.0051094257
B23: 45362 | C23: 1829.95 | D23: =C23/C22-1 -> 0.039242411 | F23: 24148.2 | G23: =F23/F22-1 -> -0.0064247758
B24: 45576 | C24: 1864.55 | D24: =C24/C23-1 -> 0.01890762 | F24: 23532.7 | G24: =F24/F23-1 -> -0.025488442
B25: 11/17/2024 | C25: 1902.25 | D25: =C25/C24-1 -> 0.020219356 | F25: 23907.25 | G25: =F25/F24-1 -> 0.015916151
B26: 11/24/2024 | C26: 1857.85 | D26: =C26/C25-1 -> -0.023340781 | F26: 24131.1 | G26: =F26/F25-1 -> 0.0093632685
B27: 45303 | C27: 1922.4 | D27: =C27/C26-1 -> 0.034744463 | F27: 24677.8 | G27: =F27/F26-1 -> 0.022655411
B28: 45516 | C28: 1999.7 | D28: =C28/C27-1 -> 0.040210154 | F28: 24768.3 | G28: =F28/F27-1 -> 0.0036672637
B29: 12/15/2024 | C29: 1922.15 | D29: =C29/C28-1 -> -0.038780817 | F29: 23587.5 | G29: =F29/F28-1 -> -0.047673841
B30: 12/22/2024 | C30: 1916.75 | D30: =C30/C29-1 -> -0.0028093541 | F30: 23813.4 | G30: =F30/F29-1 -> 0.0095771065
B31: 12/29/2024 | C31: 1938.75 | D31: =C31/C30-1 -> 0.011477762 | F31: 24004.75 | G31: =F31/F30-1 -> 0.0080353918
B32: 45778 | C32: 1966.95 | D32: =C32/C31-1 -> 0.014545455 | F32: 23431.5 | G32: =F32/F31-1 -> -0.02388069
B33: 45992 | C33: 1815.45 | D33: =C33/C32-1 -> -0.077022802 | F33: 23203.2 | G33: =F33/F32-1 -> -0.0097432943
B34: 01/19/2025 | C34: 1875.45 | D34: =C34/C33-1 -> 0.033049657 | F34: 23092.2 | G34: =F34/F33-1 -> -0.0047838229
B35: 01/26/2025 | C35: 1879.8 | D35: =C35/C34-1 -> 0.0023194433 | F35: 23508.4 | G35: =F35/F34-1 -> 0.018023402
B36: 45690 | C36: 1903.65 | D36: =C36/C35-1 -> 0.01268752 | F36: 23559.95 | G36: =F36/F35-1 -> 0.0021928332
B37: 45902 | C37: 1856.4 | D37: =C37/C36-1 -> -0.024820739 | F37: 22929.25 | G37: =F37/F36-1 -> -0.026770006
B38: 02/16/2025 | C38: 1815 | D38: =C38/C37-1 -> -0.022301228 | F38: 22795.9 | G38: =F38/F37-1 -> -0.0058157157
B39: 02/23/2025 | C39: 1687.7 | D39: =C39/C38-1 -> -0.070137741 | F39: 22124.7 | G39: =F39/F38-1 -> -0.029443891
B40: 45691 | C40: 1686 | D40: =C40/C39-1 -> -0.001007288 | F40: 22552.5 | G40: =F40/F39-1 -> 0.019335855
B41: 45903 | C41: 1579.85 | D41: =C41/C40-1 -> -0.062959668 | F41: 22397.2 | G41: =F41/F40-1 -> -0.0068861545
B42: 03/16/2025 | C42: 1592.55 | D42: =C42/C41-1 -> 0.0080387379 | F42: 23350.4 | G42: =F42/F41-1 -> 0.042558891
B43: 03/23/2025 | C43: 1570.65 | D43: =C43/C42-1 -> -0.013751531 | F43: 23519.35 | G43: =F43/F42-1 -> 0.0072354221
B44: 03/30/2025 | C44: 1451.65 | D44: =C44/C43-1 -> -0.075764811 | F44: 22904.45 | G44: =F44/F43-1 -> -0.02614443
B45: 45812 | C45: 1409.45 | D45: =C45/C44-1 -> -0.029070368 | F45: 22828.55 | G45: =F45/F44-1 -> -0.0033137665
B46: 04/13/2025 | C46: 1419.5 | D46: =C46/C45-1 -> 0.007130441 | F46: 23851.65 | G46: =F46/F45-1 -> 0.044816688
B47: 04/20/2025 | C47: 1480.2 | D47: =C47/C46-1 -> 0.042761536 | F47: 24039.35 | G47: =F47/F46-1 -> 0.0078694765
B48: 04/27/2025 | C48: 1506.8 | D48: =C48/C47-1 -> 0.017970545 | F48: 24346.7 | G48: =F48/F47-1 -> 0.012785287
B49: 45752 | C49: 1507.6 | D49: =C49/C48-1 -> 0.00053092647 | F49: 24008 | G49: =F49/F48-1 -> -0.013911536
B50: 45966 | C50: 1589.9 | D50: =C50/C49-1 -> 0.054590077 | F50: 25019.8 | G50: =F50/F49-1 -> 0.042144285
B51: 05/18/2025 | C51: 1564.8 | D51: =C51/C50-1 -> -0.015787156 | F51: 24853.15 | G51: =F51/F50-1 -> -0.0066607247
B52: 05/25/2025 | C52: 1562.7 | D52: =C52/C51-1 -> -0.0013420245 | F52: 24750.7 | G52: =F52/F51-1 -> -0.0041222139
B53: 45663 | C53: 1563.8 | D53: =C53/C52-1 -> 0.0007039099 | F53: 25003.05 | G53: =F53/F52-1 -> 0.010195671
B54: 45875 | C54: 1602 | D54: =C54/C53-1 -> 0.024427676 | F54: 24718.6 | G54: =F54/F53-1 -> -0.011376612
B55: 06/15/2025 | C55: 1622.9 | D55: =C55/C54-1 -> 0.013046192 | F55: 25112.4 | G55: =F55/F54-1 -> 0.015931323
B56: 06/22/2025 | C56: 1608 | D56: =C56/C55-1 -> -0.0091810956 | F56: 25637.8 | G56: =F56/F55-1 -> 0.020921935
B57: 06/29/2025 | C57: 1640.7 | D57: =C57/C56-1 -> 0.020335821 | F57: 25461 | G57: =F57/F56-1 -> -0.0068960675
B58: 45815 | C58: 1594.9 | D58: =C58/C57-1 -> -0.027914914 | F58: 25149.85 | G58: =F58/F57-1 -> -0.012220651
B59: 07/13/2025 | C59: 1586.1 | D59: =C59/C58-1 -> -0.0055175873 | F59: 24968.4 | G59: =F59/F58-1 -> -0.0072147548
B60: 07/20/2025 | C60: 1515.7 | D60: =C60/C59-1 -> -0.0443856 | F60: 24837 | G60: =F60/F59-1 -> -0.005262652
B61: 07/27/2025 | C61: 1469.6 | D61: =C61/C60-1 -> -0.03041499 | F61: 24565.35 | G61: =F61/F60-1 -> -0.010937311
B62: 45724 | C62: 1423.1 | D62: =C62/C61-1 -> -0.031641263 | F62: 24363.3 | G62: =F62/F61-1 -> -0.0082249998
B63: 45938 | C63: 1447.7 | D63: =C63/C62-1 -> 0.017286206 | F63: 24631.3 | G63: =F63/F62-1 -> 0.011000152
B64: 08/17/2025 | C64: 1487.5 | D64: =C64/C63-1 -> 0.027491884 | F64: 24870.1 | G64: =F64/F63-1 -> 0.0096949816
B65: 08/24/2025 | C65: 1469.6 | D65: =C65/C64-1 -> -0.012033613 | F65: 24426.85 | G65: =F65/F64-1 -> -0.017822606
B66: 08/31/2025 | C66: 1444.6 | D66: =C66/C65-1 -> -0.017011432 | F66: 24741 | G66: =F66/F65-1 -> 0.012860848
B67: 45847 | C67: 1525.6 | D67: =C67/C66-1 -> 0.056070885 | F67: 25114 | G67: =F67/F66-1 -> 0.015076189
B68: 09/14/2025 | C68: 1540.2 | D68: =C68/C67-1 -> 0.0095700052 | F68: 25327.05 | G68: =F68/F67-1 -> 0.0084833161
B69: 09/21/2025 | C69: 1448.9 | D69: =C69/C68-1 -> -0.059278016 | F69: 24654.7 | G69: =F69/F68-1 -> -0.026546716
B70: 09/28/2025 | C70: 1446.6 | D70: =C70/C69-1 -> -0.0015874111 | F70: 24894.25 | G70: =F70/F69-1 -> 0.0097162002
B71: 45787 | C71: 1514.9 | D71: =C71/C70-1 -> 0.047214157 | F71: 25285.35 | G71: =F71/F70-1 -> 0.015710455
B72: 46001 | C72: 1441.1 | D72: =C72/C71-1 -> -0.048716087 | F72: 25709.85 | G72: =F72/F71-1 -> 0.016788377
B73: 10/19/2025 | C73: 1525.4 | D73: =C73/C72-1 -> 0.058496981 | F73: 25795.15 | G73: =F73/F72-1 -> 0.0033177945
B74: 10/26/2025 | C74: 1482.3 | D74: =C74/C73-1 -> -0.028254884 | F74: 25722.1 | G74: =F74/F73-1 -> -0.0028319277
B75: 45699 | C75: 1476.8 | D75: =C75/C74-1 -> -0.00371045 | F75: 25492.3 | G75: =F75/F74-1 -> -0.0089339517
B76: 45911 | C76: 1502.8 | D76: =C76/C75-1 -> 0.017605634 | F76: 25910.05 | G76: =F76/F75-1 -> 0.016387301
B77: 11/16/2025 | C77: 1545 | D77: =C77/C76-1 -> 0.028080916 | F77: 26068.15 | G77: =F77/F76-1 -> 0.0061018794
B78: 11/23/2025 | C78: 1560.1 | D78: =C78/C77-1 -> 0.0097734628 | F78: 26202.95 | G78: =F78/F77-1 -> 0.0051710612
B79: 11/30/2025 | C79: 1616.2 | D79: =C79/C78-1 -> 0.035959233 | F79: 26186.45 | G79: =F79/F78-1 -> -0.00062970009
B80: 45850 | C80: 1598.2 | D80: =C80/C79-1 -> -0.011137235 | F80: 26046.95 | G80: =F80/F79-1 -> -0.0053271826
B81: 12/14/2025 | C81: 1638.7 | D81: =C81/C80-1 -> 0.025341009 | F81: 25966.4 | G81: =F81/F80-1 -> -0.0030924926
B82: 12/21/2025 | C82: 1656.1 | D82: =C82/C81-1 -> 0.010618173 | F82: 26042.3 | G82: =F82/F81-1 -> 0.0029230082
B83: 12/28/2025 | C83: 1640.4 | D83: =C83/C82-1 -> -0.0094801039 | F83: 26328.55 | G83: =F83/F82-1 -> 0.010991733
B84: 46113 | C84: 1614.1 | D84: =C84/C83-1 -> -0.016032675 | F84: 25683.3 | G84: =F84/F83-1 -> -0.024507616
B85: 46327 | C85: 1689.8 | D85: =C85/C84-1 -> 0.046899201 | F85: 25694.35 | G85: =F85/F84-1 -> 0.00043024066
B86: 01/18/2026 | C86: 1670.8 | D86: =C86/C85-1 -> -0.011243934 | F86: 25048.65 | G86: =F86/F85-1 -> -0.025130038
B87: 01/25/2026 | C87: 1641 | D87: =C87/C86-1 -> -0.017835767 | F87: 25320.65 | G87: =F87/F86-1 -> 0.010858869
B88: 46024 | C88: 1507.1 | D88: =C88/C87-1 -> -0.081596587 | F88: 25693.7 | G88: =F88/F87-1 -> 0.014733034
B89: 46236 | C89: 1369.1 | D89: =C89/C88-1 -> -0.091566585 | F89: 25471.1 | G89: =F89/F88-1 -> -0.0086636024
B90: 02/15/2026 | C90: 1353.2 | D90: =C90/C89-1 -> -0.011613469 | F90: 25571.25 | G90: =F90/F89-1 -> 0.0039319071
B91: 02/22/2026 | C91: 1300.1 | D91: =C91/C90-1 -> -0.039240319 | F91: 25178.65 | G91: =F91/F90-1 -> -0.01535318
B92: 46025 | C92: 1308.4 | D92: =C92/C91-1 -> 0.0063841243 | F92: 24450.45 | G92: =F92/F91-1 -> -0.028921328
B93: 46237 | C93: 1248.3 | D93: =C93/C92-1 -> -0.045933965 | F93: 23151.1 | G93: =F93/F92-1 -> -0.053142171
B94: 03/15/2026 | C94: 1255.9 | D94: =C94/C93-1 -> 0.0060882801 | F94: 23114.5 | G94: =F94/F93-1 -> -0.0015809184
B95: 03/22/2026 | C95: 1269.7 | D95: =C95/C94-1 -> 0.010988136 | F95: 22819.6 | G95: =F95/F94-1 -> -0.012758225
B96: 03/29/2026 | C96: 1300.8 | D96: =C96/C95-1 -> 0.024493975 | F96: 22713.1 | G96: =F96/F95-1 -> -0.0046670406
B97: 46146 | C97: 1292.5 | D97: =C97/C96-1 -> -0.0063806888 | F97: 24050.6 | G97: =F97/F96-1 -> 0.058886722
B98: 46360 | C98: 1318.7 | D98: =C98/C97-1 -> 0.020270793 | F98: 24353.55 | G98: =F98/F97-1 -> 0.012596359
B99: 04/19/2026 | C99: 1154.6 | D99: =C99/C98-1 -> -0.12444074 | F99: 23897.95 | G99: =F99/F98-1 -> -0.018707745
B100: 04/26/2026 | C100: 1181.8 | D100: =C100/C99-1 -> 0.023557942 | F100: 23997.55 | G100: =F100/F99-1 -> 0.0041677215
B101: 46086 | C101: 1179.2 | D101: =C101/C100-1 -> -0.0022000338 | F101: 24176.15 | G101: =F101/F100-1 -> 0.0074424264
B102: 46300 | C102: 1119 | D102: =C102/C101-1 -> -0.05105156 | F102: 23643.5 | G102: =F102/F101-1 -> -0.022032044
B103: 05/17/2026 | C103: 1174.5 | D103: =C103/C102-1 -> 0.049597855 | F103: 23719.3 | G103: =F103/F102-1 -> 0.0032059551
B104: 05/24/2026 | C104: 1160.9 | D104: =C104/C103-1 -> -0.011579395 | F104: 23547.75 | G104: =F104/F103-1 -> -0.0072325069
...

Sheet TCS - Beta
B2: Source: Investing.com
B4: Regression Beta - 2 Years Weekly
B6: TCS Weekly Returns | F6: NIFTY Returns | I6: Beta Drifting
L7: Beta 2 | M7: =_xlfn.COVARIANCE.S(D10:D113,G10:G113)/_xlfn.VAR.S(G10:G113) -> -0.077447364
B8: Date | C8: Closing Price | D8: Return | F8: Closing Price | G8: Return | I8: Levered Raw Beta | J8: =SLOPE(D10:D113,G10:G113) -> -0.077447364
B9: 07/28/2024 | C9: 4215.85 | F9: 14529.2 | I9: Raw Beta Weight | J9: 0.75 | L9: Beta | M9: =M28 -> 1.2421252
B10: 45390 | C10: 4162.4 | D10: =C10/C9-1 -> -0.012678345 | F10: 14938.1 | G10: =F10/F9-1 -> 0.028143325
B11: 45604 | C11: 4346.76 | D11: =C11/C10-1 -> 0.044291755 | F11: 15031 | G11: =F11/F10-1 -> 0.0062189971 | I11: Market Beta | J11: 1 | L11: SUMMARY OUTPUT
B12: 08/18/2024 | C12: 4393.86 | D12: =C12/C11-1 -> 0.010835657 | F12: 14744 | G12: =F12/F11-1 -> -0.019093873 | I12: Market Beta Weight | J12: =100%-J9 -> 0.25
B13: 08/25/2024 | C13: 4482.3 | D13: =C13/C12-1 -> 0.020128088 | F13: 14507.3 | G13: =F13/F12-1 -> -0.016053988 | L13: Regression Statistics
B14: 45300 | C14: 4386.82 | D14: =C14/C13-1 -> -0.021301564 | F14: 14867.3 | G14: =F14/F13-1 -> 0.024815093 | I14: Adjusted Beta | J14: =(J8*J9)+(J11*J12) -> 0.19191448 | L14: Multiple R | M14: 0.51109438
B15: 45513 | C15: 4451.64 | D15: =C15/C14-1 -> 0.014776079 | F15: 14834.8 | G15: =F15/F14-1 -> -0.0021860055 | L15: R Square | M15: 0.26121746
B16: 09/15/2024 | C16: 4217.67 | D16: =C16/C15-1 -> -0.052558158 | F16: 14617.8 | G16: =F16/F15-1 -> -0.014627767 | L16: Adjusted R Square | M16: 0.2539745
B17: 09/22/2024 | C17: 4241.09 | D17: =C17/C16-1 -> 0.0055528289 | F17: 14341.3 | G17: =F17/F16-1 -> -0.018915295 | L17: Standard Error | M17: 0.04228496
B18: 09/29/2024 | C18: 4185.53 | D18: =C18/C17-1 -> -0.013100406 | F18: 14631.1 | G18: =F18/F17-1 -> 0.020207373 | L18: Observations | M18: 104
B19: 45453 | C19: 4084.09 | D19: =C19/C18-1 -> -0.024235879 | F19: 14823.2 | G19: =F19/F18-1 -> 0.013129566
B20: 10/13/2024 | C20: 4058.35 | D20: =C20/C19-1 -> -0.0063025056 | F20: 14677.8 | G20: =F20/F19-1 -> -0.0098089481 | L20: ANOVA
B21: 10/20/2024 | C21: 3993.88 | D21: =C21/C20-1 -> -0.015885766 | F21: 15175.3 | G21: =F21/F20-1 -> 0.033894725 | M21: df | N21: SS | O21: MS | P21: F | Q21: Significance F
B22: 10/27/2024 | C22: 3921.68 | D22: =C22/C21-1 -> -0.018077659 | F22: 15435.7 | G22: =F22/F21-1 -> 0.017159463 | L22: Regression | M22: 1 | N22: 0.064484836 | O22: 0.064484836 | P22: 36.064985 | Q22: 2.9601287e-08
B23: 45362 | C23: 4081.93 | D23: =C23/C22-1 -> 0.04086259 | F23: 15670.3 | G23: =F23/F22-1 -> 0.015198533 | L23: Residual | M23: 102 | N23: 0.18237782 | O23: 0.0017880178
B24: 45576 | C24: 4080.85 | D24: =C24/C23-1 -> -0.00026458073 | F24: 15799.3 | G24: =F24/F23-1 -> 0.0082321334 | L24: Total | M24: 103 | N24: 0.24686265
B25: 11/17/2024 | C25: 4178 | D25: =C25/C24-1 -> 0.023806315 | F25: 15683.3 | G25: =F25/F24-1 -> -0.0073420974
B26: 11/24/2024 | C26: 4203.84 | D26: =C26/C25-1 -> 0.0061847774 | F26: 15860.3 | G26: =F26/F25-1 -> 0.01128589 | M26: Coefficients | N26: Standard Error | O26: t Stat | P26: P-value | Q26: Lower 95% | R26: Upper 95% | S26: Lower 95.0% | T26: Upper 95.0%
B27: 45303 | C27: 4375.75 | D27: =C27/C26-1 -> 0.040893564 | F27: 15722.2 | G27: =F27/F26-1 -> -0.0087072754 | L27: Intercept | M27: 0.0001068556 | N27: 0.004170824 | O27: 0.025619781 | P27: 0.97961066 | Q27: -0.0081659541 | R27: 0.0083796653 | S27: -0.0081659541 | T27: 0.0083796653
B28: 45516 | C28: 4403.7 | D28: =C28/C27-1 -> 0.0063874764 | F28: 15689.8 | G28: =F28/F27-1 -> -0.0020607803 | L28: X Variable 1 | M28: 1.2421252 | N28: 0.20683427 | O28: 6.005413 | P28: 2.9601287e-08 | Q28: 0.83187043 | R28: 1.65238 | S28: 0.83187043 | T28: 1.65238
B29: 12/15/2024 | C29: 4104.86 | D29: =C29/C28-1 -> -0.067861117 | F29: 15923.4 | G29: =F29/F28-1 -> 0.014888654
B30: 12/22/2024 | C30: 4099.5 | D30: =C30/C29-1 -> -0.0013057693 | F30: 15856 | G30: =F30/F29-1 -> -0.0042327644
B31: 12/29/2024 | C31: 4035.57 | D31: =C31/C30-1 -> -0.015594585 | F31: 15763 | G31: =F31/F30-1 -> -0.0058652876
B32: 45778 | C32: 4198.72 | D32: =C32/C31-1 -> 0.040427994 | F32: 16238.2 | G32: =F32/F31-1 -> 0.030146546
B33: 45992 | C33: 4124.3 | D33: =C33/C32-1 -> -0.017724449 | F33: 16529.1 | G33: =F33/F32-1 -> 0.017914547
B34: 01/19/2025 | C34: 4152.35 | D34: =C34/C33-1 -> 0.0068011541 | F34: 16450.5 | G34: =F34/F33-1 -> -0.0047552498
B35: 01/26/2025 | C35: 4112.4 | D35: =C35/C34-1 -> -0.009621058 | F35: 16705.2 | G35: =F35/F34-1 -> 0.015482812
B36: 45690 | C36: 4029.4 | D36: =C36/C35-1 -> -0.020182862 | F36: 17323.6 | G36: =F36/F35-1 -> 0.037018413
B37: 45902 | C37: 3934.85 | D37: =C37/C36-1 -> -0.023465032 | F37: 17369.3 | G37: =F37/F36-1 -> 0.0026380198
B38: 02/16/2025 | C38: 3786 | D38: =C38/C37-1 -> -0.037828634 | F38: 17585.2 | G38: =F38/F37-1 -> 0.012429977
B39: 02/23/2025 | C39: 3483.25 | D39: =C39/C38-1 -> -0.079965663 | F39: 17853.2 | G39: =F39/F38-1 -> 0.015240088
B40: 45691 | C40: 3611.2 | D40: =C40/C39-1 -> 0.036732936 | F40: 17532.1 | G40: =F40/F39-1 -> -0.017985571
B41: 45903 | C41: 3511.05 | D41: =C41/C40-1 -> -0.027733163 | F41: 17895.2 | G41: =F41/F40-1 -> 0.020710582
B42: 03/16/2025 | C42: 3578.1 | D42: =C42/C41-1 -> 0.019096851 | F42: 18338.6 | G42: =F42/F41-1 -> 0.024777594
B43: 03/23/2025 | C43: 3606.15 | D43: =C43/C42-1 -> 0.0078393561 | F43: 18114.9 | G43: =F43/F42-1 -> -0.012198314
B44: 03/30/2025 | C44: 3299.4 | D44: =C44/C43-1 -> -0.085063017 | F44: 17671.7 | G44: =F44/F43-1 -> -0.024466047
B45: 45812 | C45: 3231.5 | D45: =C45/C44-1 -> -0.020579499 | F45: 17916.8 | G45: =F45/F44-1 -> 0.013869633
B46: 04/13/2025 | C46: 3298.9 | D46: =C46/C45-1 -> 0.020857187 | F46: 18102.8 | G46: =F46/F45-1 -> 0.010381318
B47: 04/20/2025 | C47: 3448 | D47: =C47/C46-1 -> 0.045196884 | F47: 17764.8 | G47: =F47/F46-1 -> -0.018671145
B48: 04/27/2025 | C48: 3444.7 | D48: =C48/C47-1 -> -0.00095707657 | F48: 17026.4 | G48: =F48/F47-1 -> -0.041565343
B49: 45752 | C49: 3440.3 | D49: =C49/C48-1 -> -0.0012773246 | F49: 17196.7 | G49: =F49/F48-1 -> 0.010002114
B50: 45966 | C50: 3561.3 | D50: =C50/C49-1 -> 0.035171351 | F50: 17511.3 | G50: =F50/F49-1 -> 0.018294208
B51: 05/18/2025 | C51: 3514.6 | D51: =C51/C50-1 -> -0.013113189 | F51: 16985.2 | G51: =F51/F50-1 -> -0.030043458
B52: 05/25/2025 | C52: 3463.4 | D52: =C52/C51-1 -> -0.014567803 | F52: 17003.8 | G52: =F52/F51-1 -> 0.001095071
B53: 45663 | C53: 3384.2 | D53: =C53/C52-1 -> -0.022867702 | F53: 17354.1 | G53: =F53/F52-1 -> 0.020601277
B54: 45875 | C54: 3445.7 | D54: =C54/C53-1 -> 0.018172685 | F54: 17812.7 | G54: =F54/F53-1 -> 0.026426032
B55: 06/15/2025 | C55: 3435.7 | D55: =C55/C54-1 -> -0.0029021679 | F55: 18255.8 | G55: =F55/F54-1 -> 0.02487551
B56: 06/22/2025 | C56: 3441.1 | D56: =C56/C55-1 -> 0.0015717321 | F56: 17617.2 | G56: =F56/F55-1 -> -0.034980664
B57: 06/29/2025 | C57: 3419.8 | D57: =C57/C56-1 -> -0.0061898811 | F57: 17101.9 | G57: =F57/F56-1 -> -0.029249824
B58: 45815 | C58: 3266 | D58: =C58/C57-1 -> -0.04497339 | F58: 17516.3 | G58: =F58/F57-1 -> 0.024231226
B59: 07/13/2025 | C59: 3189.9 | D59: =C59/C58-1 -> -0.023300674 | F59: 17374.8 | G59: =F59/F58-1 -> -0.00807819
B60: 07/20/2025 | C60: 3135.8 | D60: =C60/C59-1 -> -0.016959779 | F60: 17276.3 | G60: =F60/F59-1 -> -0.00566913
B61: 07/27/2025 | C61: 3003 | D61: =C61/C60-1 -> -0.04234964 | F61: 16658.4 | G61: =F61/F60-1 -> -0.03576576
B62: 45724 | C62: 3036.4 | D62: =C62/C61-1 -> 0.011122211 | F62: 16245.3 | G62: =F62/F61-1 -> -0.0247983
B63: 45938 | C63: 3022.3 | D63: =C63/C62-1 -> -0.004643657 | F63: 16630.4 | G63: =F63/F62-1 -> 0.023705318
B64: 08/17/2025 | C64: 3054 | D64: =C64/C63-1 -> 0.010488701 | F64: 17287.1 | G64: =F64/F63-1 -> 0.039487926
B65: 08/24/2025 | C65: 3084.7 | D65: =C65/C64-1 -> 0.01005239 | F65: 17153 | G65: =F65/F64-1 -> -0.0077572294
B66: 08/31/2025 | C66: 3048.3 | D66: =C66/C65-1 -> -0.011800175 | F66: 17670.4 | G66: =F66/F65-1 -> 0.03016382
B67: 45847 | C67: 3133.4 | D67: =C67/C66-1 -> 0.0279172 | F67: 17784.3 | G67: =F67/F66-1 -> 0.0064458077
B68: 09/14/2025 | C68: 3169.2 | D68: =C68/C67-1 -> 0.011425289 | F68: 17475.7 | G68: =F68/F67-1 -> -0.017352384
B69: 09/21/2025 | C69: 2899.1 | D69: =C69/C68-1 -> -0.085226556 | F69: 17171.9 | G69: =F69/F68-1 -> -0.017384139
B70: 09/28/2025 | C70: 2901.9 | D70: =C70/C69-1 -> 0.00096581698 | F70: 17102.6 | G70: =F70/F69-1 -> -0.0040356629
B71: 45787 | C71: 3028.3 | D71: =C71/C70-1 -> 0.043557669 | F71: 16411.3 | G71: =F71/F70-1 -> -0.040420755
B72: 46001 | C72: 2962.2 | D72: =C72/C71-1 -> -0.021827428 | F72: 15782.2 | G72: =F72/F71-1 -> -0.038333343
B73: 10/19/2025 | C73: 3063.2 | D73: =C73/C72-1 -> 0.03409628 | F73: 16266.2 | G73: =F73/F72-1 -> 0.030667461
B74: 10/26/2025 | C74: 3058 | D74: =C74/C73-1 -> -0.0016975712 | F74: 16352.5 | G74: =F74/F73-1 -> 0.0053054801
B75: 45699 | C75: 2991.8 | D75: =C75/C74-1 -> -0.021648136 | F75: 16584.3 | G75: =F75/F74-1 -> 0.014175203
B76: 45911 | C76: 3106 | D76: =C76/C75-1 -> 0.038171001 | F76: 16201.8 | G76: =F76/F75-1 -> -0.023063982
B77: 11/16/2025 | C77: 3150.6 | D77: =C77/C76-1 -> 0.014359305 | F77: 15293.5 | G77: =F77/F76-1 -> -0.056061672
B78: 11/23/2025 | C78: 3137.5 | D78: =C78/C77-1 -> -0.0041579382 | F78: 15699.3 | G78: =F78/F77-1 -> 0.026534148
B79: 11/30/2025 | C79: 3238.2 | D79: =C79/C78-1 -> 0.032095618 | F79: 15752 | G79: =F79/F78-1 -> 0.0033568376
B80: 45850 | C80: 3220.5 | D80: =C80/C79-1 -> -0.0054659996 | F80: 16220.6 | G80: =F80/F79-1 -> 0.029748603
B81: 12/14/2025 | C81: 3282 | D81: =C81/C80-1 -> 0.019096414 | F81: 16049.2 | G81: =F81/F80-1 -> -0.01056681
B82: 12/21/2025 | C82: 3232.74 | D82: =C82/C81-1 -> -0.015009141 | F82: 16719.4 | G82: =F82/F81-1 -> 0.041759091
B83: 12/28/2025 | C83: 3203.86 | D83: =C83/C82-1 -> -0.0089335981 | F83: 17158.3 | G83: =F83/F82-1 -> 0.026250942
B84: 46113 | C84: 3161.58 | D84: =C84/C83-1 -> -0.013196582 | F84: 17397.5 | G84: =F84/F83-1 -> 0.013940775
B85: 46327 | C85: 3206.7 | D85: =C85/C84-1 -> 0.014271345 | F85: 17698.2 | G85: =F85/F84-1 -> 0.017284093
B86: 01/18/2026 | C86: 3162.5 | D86: =C86/C85-1 -> -0.013783641 | F86: 17758.4 | G86: =F86/F85-1 -> 0.0034014759
B87: 01/25/2026 | C87: 3123.9 | D87: =C87/C86-1 -> -0.012205534 | F87: 17558.9 | G87: =F87/F86-1 -> -0.01123412
B88: 46024 | C88: 2941.6 | D88: =C88/C87-1 -> -0.058356542 | F88: 17539.4 | G88: =F88/F87-1 -> -0.0011105479
B89: 46236 | C89: 2692.2 | D89: =C89/C88-1 -> -0.084783791 | F89: 17833.3 | G89: =F89/F88-1 -> 0.01675656
B90: 02/15/2026 | C90: 2686.2 | D90: =C90/C89-1 -> -0.0022286606 | F90: 17530.8 | G90: =F90/F89-1 -> -0.016962649
B91: 02/22/2026 | C91: 2637.4 | D91: =C91/C90-1 -> -0.018166927 | F91: 17327.3 | G91: =F91/F90-1 -> -0.011608141
B92: 46025 | C92: 2557.6 | D92: =C92/C91-1 -> -0.030257071 | F92: 17094.3 | G92: =F92/F91-1 -> -0.013446988
B93: 46237 | C93: 2410.5 | D93: =C93/C92-1 -> -0.057514858 | F93: 17314.7 | G93: =F93/F92-1 -> 0.012893187
B94: 03/15/2026 | C94: 2390.6 | D94: =C94/C93-1 -> -0.0082555486 | F94: 17185.7 | G94: =F94/F93-1 -> -0.0074503168
B95: 03/22/2026 | C95: 2389.8 | D95: =C95/C94-1 -> -0.00033464402 | F95: 17576.3 | G95: =F95/F94-1 -> 0.022728198
B96: 03/29/2026 | C96: 2450.7 | D96: =C96/C95-1 -> 0.025483304 | F96: 17786.8 | G96: =F96/F95-1 -> 0.011976355
B97: 46146 | C97: 2524.3 | D97: =C97/C96-1 -> 0.030032236 | F97: 18117.2 | G97: =F97/F96-1 -> 0.018575573
B98: 46360 | C98: 2581.5 | D98: =C98/C97-1 -> 0.022659747 | F98: 18349.7 | G98: =F98/F97-1 -> 0.012833109
B99: 04/19/2026 | C99: 2396.9 | D99: =C99/C98-1 -> -0.071508813 | F99: 18307.7 | G99: =F99/F98-1 -> -0.0022888658
B100: 04/26/2026 | C100: 2473.9 | D100: =C100/C99-1 -> 0.032124828 | F100: 18512.8 | G100: =F100/F99-1 -> 0.011202936
B101: 46086 | C101: 2394.4 | D101: =C101/C100-1 -> -0.032135495 | F101: 18696.1 | G101: =F101/F100-1 -> 0.0099012575
B102: 46300 | C102: 2264 | D102: =C102/C101-1 -> -0.054460408 | F102: 18496.6 | G102: =F102/F101-1 -> -0.010670675
B103: 05/17/2026 | C103: 2317.3 | D103: =C103/C102-1 -> 0.023542403 | F103: 18269 | G103: =F103/F102-1 -> -0.012304964
...

Sheet HCL Technologies - Beta
B2: Source: Investing.com
B4: Regression Beta - 2 Years Weekly
B6: HCL Technologies Weekly Returns | F6: NIFTY Returns | I6: Beta Drifting
B8: Date | C8: Closing Price | D8: Return | F8: Closing Price | G8: Return | I8: Levered Raw Beta | J8: =SLOPE(D10:D112,G10:G112) -> 0.7844093
B9: 07/28/2024 | C9: 1603.91 | F9: 24717.7 | I9: Raw Beta Weight | J9: 0.75
B10: 45390 | C10: 1584.63 | D10: =C10/C9-1 -> -0.012020625 | F10: 24367.5 | G10: =F10/F9-1 -> -0.014167985
B11: 45604 | C11: 1662.67 | D11: =C11/C10-1 -> 0.049248089 | F11: 24541.15 | G11: =F11/F10-1 -> 0.0071262953 | I11: Market Beta | J11: 1
B12: 08/18/2024 | C12: 1655.89 | D12: =C12/C11-1 -> -0.0040777785 | F12: 24823.15 | G12: =F12/F11-1 -> 0.011490904 | I12: Market Beta Weight | J12: =100%-J9 -> 0.25
B13: 08/25/2024 | C13: 1747.38 | D13: =C13/C12-1 -> 0.055251255 | F13: 25235.9 | G13: =F13/F12-1 -> 0.016627624
B14: 45300 | C14: 1750.22 | D14: =C14/C13-1 -> 0.0016252904 | F14: 24852.15 | G14: =F14/F13-1 -> -0.015206511 | I14: Adjusted Beta | J14: =(J8*J9)+(J11*J12) -> 0.83830698
B15: 45513 | C15: 1806.73 | D15: =C15/C14-1 -> 0.03228737 | F15: 25356.5 | G15: =F15/F14-1 -> 0.020294019
B16: 09/15/2024 | C16: 1754.16 | D16: =C16/C15-1 -> -0.029096766 | F16: 25790.95 | G16: =F16/F15-1 -> 0.017133674
B17: 09/22/2024 | C17: 1802.34 | D17: =C17/C16-1 -> 0.027466138 | F17: 26178.95 | G17: =F17/F16-1 -> 0.015044037
B18: 09/29/2024 | C18: 1770.65 | D18: =C18/C17-1 -> -0.017582698 | F18: 25014.6 | G18: =F18/F17-1 -> -0.044476574
B19: 45453 | C19: 1833.49 | D19: =C19/C18-1 -> 0.035489792 | F19: 24964.25 | G19: =F19/F18-1 -> -0.0020128245
B20: 10/13/2024 | C20: 1851.48 | D20: =C20/C19-1 -> 0.0098118888 | F20: 24854.05 | G20: =F20/F19-1 -> -0.0044143125
B21: 10/20/2024 | C21: 1846.15 | D21: =C21/C20-1 -> -0.0028787781 | F21: 24180.8 | G21: =F21/F20-1 -> -0.027088141
B22: 10/27/2024 | C22: 1751.52 | D22: =C22/C21-1 -> -0.051258023 | F22: 24304.35 | G22: =F22/F21-1 -> 0.0051094257
B23: 45362 | C23: 1831.35 | D23: =C23/C22-1 -> 0.045577555 | F23: 24148.2 | G23: =F23/F22-1 -> -0.0064247758
B24: 45576 | C24: 1852.73 | D24: =C24/C23-1 -> 0.011674448 | F24: 23532.7 | G24: =F24/F23-1 -> -0.025488442
B25: 11/17/2024 | C25: 1892.04 | D25: =C25/C24-1 -> 0.021217339 | F25: 23907.25 | G25: =F25/F24-1 -> 0.015916151
B26: 11/24/2024 | C26: 1841.86 | D26: =C26/C25-1 -> -0.026521638 | F26: 24131.1 | G26: =F26/F25-1 -> 0.0093632685
B27: 45303 | C27: 1916.26 | D27: =C27/C26-1 -> 0.04039395 | F27: 24677.8 | G27: =F27/F26-1 -> 0.022655411
B28: 45516 | C28: 1962.21 | D28: =C28/C27-1 -> 0.023979001 | F28: 24768.3 | G28: =F28/F27-1 -> 0.0036672637
B29: 12/15/2024 | C29: 1904.95 | D29: =C29/C28-1 -> -0.029181382 | F29: 23587.5 | G29: =F29/F28-1 -> -0.047673841
B30: 12/22/2024 | C30: 1885.67 | D30: =C30/C29-1 -> -0.010121001 | F30: 23813.4 | G30: =F30/F29-1 -> 0.0095771065
B31: 12/29/2024 | C31: 1940.13 | D31: =C31/C30-1 -> 0.028880981 | F31: 24004.75 | G31: =F31/F30-1 -> 0.0080353918
B32: 45778 | C32: 1988.42 | D32: =C32/C31-1 -> 0.024890085 | F32: 23431.5 | G32: =F32/F31-1 -> -0.02388069
B33: 45992 | C33: 1788.9 | D33: =C33/C32-1 -> -0.10034097 | F33: 23203.2 | G33: =F33/F32-1 -> -0.0097432943
B34: 01/19/2025 | C34: 1792.85 | D34: =C34/C33-1 -> 0.0022080608 | F34: 23092.2 | G34: =F34/F33-1 -> -0.0047838229
B35: 01/26/2025 | C35: 1725.45 | D35: =C35/C34-1 -> -0.037593775 | F35: 23508.4 | G35: =F35/F34-1 -> 0.018023402
B36: 45690 | C36: 1725.65 | D36: =C36/C35-1 -> 0.00011591179 | F36: 23559.95 | G36: =F36/F35-1 -> 0.0021928332
B37: 45902 | C37: 1711.25 | D37: =C37/C36-1 -> -0.0083446817 | F37: 22929.25 | G37: =F37/F36-1 -> -0.026770006
B38: 02/16/2025 | C38: 1700.7 | D38: =C38/C37-1 -> -0.006165084 | F38: 22795.9 | G38: =F38/F37-1 -> -0.0058157157
B39: 02/23/2025 | C39: 1575.05 | D39: =C39/C38-1 -> -0.073881343 | F39: 22124.7 | G39: =F39/F38-1 -> -0.029443891
B40: 45691 | C40: 1557.95 | D40: =C40/C39-1 -> -0.010856798 | F40: 22552.5 | G40: =F40/F39-1 -> 0.019335855
B41: 45903 | C41: 1534.75 | D41: =C41/C40-1 -> -0.014891364 | F41: 22397.2 | G41: =F41/F40-1 -> -0.0068861545
B42: 03/16/2025 | C42: 1566.7 | D42: =C42/C41-1 -> 0.020817723 | F42: 23350.4 | G42: =F42/F41-1 -> 0.042558891
B43: 03/23/2025 | C43: 1592.5 | D43: =C43/C42-1 -> 0.016467735 | F43: 23519.35 | G43: =F43/F42-1 -> 0.0072354221
B44: 03/30/2025 | C44: 1422.1 | D44: =C44/C43-1 -> -0.10700157 | F44: 22904.45 | G44: =F44/F43-1 -> -0.02614443
B45: 45812 | C45: 1390.55 | D45: =C45/C44-1 -> -0.0221855 | F45: 22828.55 | G45: =F45/F44-1 -> -0.0033137665
B46: 04/13/2025 | C46: 1438 | D46: =C46/C45-1 -> 0.034123189 | F46: 23851.65 | G46: =F46/F45-1 -> 0.044816688
B47: 04/20/2025 | C47: 1578.2 | D47: =C47/C46-1 -> 0.097496523 | F47: 24039.35 | G47: =F47/F46-1 -> 0.0078694765
B48: 04/27/2025 | C48: 1576.5 | D48: =C48/C47-1 -> -0.0010771765 | F48: 24346.7 | G48: =F48/F47-1 -> 0.012785287
B49: 45752 | C49: 1569.4 | D49: =C49/C48-1 -> -0.0045036473 | F49: 24008 | G49: =F49/F48-1 -> -0.013911536
B50: 45966 | C50: 1659.9 | D50: =C50/C49-1 -> 0.05766535 | F50: 25019.8 | G50: =F50/F49-1 -> 0.042144285
B51: 05/18/2025 | C51: 1648.2 | D51: =C51/C50-1 -> -0.0070486174 | F51: 24853.15 | G51: =F51/F50-1 -> -0.0066607247
B52: 05/25/2025 | C52: 1636.6 | D52: =C52/C51-1 -> -0.0070379808 | F52: 24750.7 | G52: =F52/F51-1 -> -0.0041222139
B53: 45663 | C53: 1637.7 | D53: =C53/C52-1 -> 0.00067212514 | F53: 25003.05 | G53: =F53/F52-1 -> 0.010195671
B54: 45875 | C54: 1695.3 | D54: =C54/C53-1 -> 0.035171277 | F54: 24718.6 | G54: =F54/F53-1 -> -0.011376612
B55: 06/15/2025 | C55: 1739.9 | D55: =C55/C54-1 -> 0.026308028 | F55: 25112.4 | G55: =F55/F54-1 -> 0.015931323
B56: 06/22/2025 | C56: 1723.3 | D56: =C56/C55-1 -> -0.0095407782 | F56: 25637.8 | G56: =F56/F55-1 -> 0.020921935
B57: 06/29/2025 | C57: 1725.9 | D57: =C57/C56-1 -> 0.0015087332 | F57: 25461 | G57: =F57/F56-1 -> -0.0068960675
B58: 45815 | C58: 1638.3 | D58: =C58/C57-1 -> -0.050756127 | F58: 25149.85 | G58: =F58/F57-1 -> -0.012220651
B59: 07/13/2025 | C59: 1548.8 | D59: =C59/C58-1 -> -0.054629799 | F59: 24968.4 | G59: =F59/F58-1 -> -0.0072147548
B60: 07/20/2025 | C60: 1490.1 | D60: =C60/C59-1 -> -0.03790031 | F60: 24837 | G60: =F60/F59-1 -> -0.005262652
B61: 07/27/2025 | C61: 1452.1 | D61: =C61/C60-1 -> -0.025501644 | F61: 24565.35 | G61: =F61/F60-1 -> -0.010937311
B62: 45724 | C62: 1475.7 | D62: =C62/C61-1 -> 0.016252324 | F62: 24363.3 | G62: =F62/F61-1 -> -0.0082249998
B63: 45938 | C63: 1489.8 | D63: =C63/C62-1 -> 0.0095547876 | F63: 24631.3 | G63: =F63/F62-1 -> 0.011000152
B64: 08/17/2025 | C64: 1466.3 | D64: =C64/C63-1 -> -0.015773929 | F64: 24870.1 | G64: =F64/F63-1 -> 0.0096949816
B65: 08/24/2025 | C65: 1454.8 | D65: =C65/C64-1 -> -0.0078428698 | F65: 24426.85 | G65: =F65/F64-1 -> -0.017822606
B66: 08/31/2025 | C66: 1419 | D66: =C66/C65-1 -> -0.024608194 | F66: 24741 | G66: =F66/F65-1 -> 0.012860848
B67: 45847 | C67: 1467.2 | D67: =C67/C66-1 -> 0.033967583 | F67: 25114 | G67: =F67/F66-1 -> 0.015076189
B68: 09/14/2025 | C68: 1467.4 | D68: =C68/C67-1 -> 0.00013631407 | F68: 25327.05 | G68: =F68/F67-1 -> 0.0084833161
B69: 09/21/2025 | C69: 1395.3 | D69: =C69/C68-1 -> -0.049134524 | F69: 24654.7 | G69: =F69/F68-1 -> -0.026546716
B70: 09/28/2025 | C70: 1393.5 | D70: =C70/C69-1 -> -0.0012900452 | F70: 24894.25 | G70: =F70/F69-1 -> 0.0097162002
B71: 45787 | C71: 1495.5 | D71: =C71/C70-1 -> 0.073196986 | F71: 25285.35 | G71: =F71/F70-1 -> 0.015710455
B72: 46001 | C72: 1486.2 | D72: =C72/C71-1 -> -0.006218656 | F72: 25709.85 | G72: =F72/F71-1 -> 0.016788377
B73: 10/19/2025 | C73: 1523.8 | D73: =C73/C72-1 -> 0.025299421 | F73: 25795.15 | G73: =F73/F72-1 -> 0.0033177945
B74: 10/26/2025 | C74: 1541.5 | D74: =C74/C73-1 -> 0.011615698 | F74: 25722.1 | G74: =F74/F73-1 -> -0.0028319277
B75: 45699 | C75: 1512.4 | D75: =C75/C74-1 -> -0.018877717 | F75: 25492.3 | G75: =F75/F74-1 -> -0.0089339517
B76: 45911 | C76: 1594.6 | D76: =C76/C75-1 -> 0.054350701 | F76: 25910.05 | G76: =F76/F75-1 -> 0.016387301
B77: 11/16/2025 | C77: 1608 | D77: =C77/C76-1 -> 0.0084033613 | F77: 26068.15 | G77: =F77/F76-1 -> 0.0061018794
B78: 11/23/2025 | C78: 1624.2 | D78: =C78/C77-1 -> 0.010074627 | F78: 26202.95 | G78: =F78/F77-1 -> 0.0051710612
B79: 11/30/2025 | C79: 1683 | D79: =C79/C78-1 -> 0.036202438 | F79: 26186.45 | G79: =F79/F78-1 -> -0.00062970009
B80: 45850 | C80: 1673.2 | D80: =C80/C79-1 -> -0.0058229352 | F80: 26046.95 | G80: =F80/F79-1 -> -0.0053271826
B81: 12/14/2025 | C81: 1642.4 | D81: =C81/C80-1 -> -0.018407841 | F81: 25966.4 | G81: =F81/F80-1 -> -0.0030924926
B82: 12/21/2025 | C82: 1660.9 | D82: =C82/C81-1 -> 0.011264004 | F82: 26042.3 | G82: =F82/F81-1 -> 0.0029230082
B83: 12/28/2025 | C83: 1640.2 | D83: =C83/C82-1 -> -0.012463122 | F83: 26328.55 | G83: =F83/F82-1 -> 0.010991733
B84: 46113 | C84: 1661.4 | D84: =C84/C83-1 -> 0.012925253 | F84: 25683.3 | G84: =F84/F83-1 -> -0.024507616
B85: 46327 | C85: 1698 | D85: =C85/C84-1 -> 0.022029614 | F85: 25694.35 | G85: =F85/F84-1 -> 0.00043024066
B86: 01/18/2026 | C86: 1707 | D86: =C86/C85-1 -> 0.0053003534 | F86: 25048.65 | G86: =F86/F85-1 -> -0.025130038
B87: 01/25/2026 | C87: 1695.6 | D87: =C87/C86-1 -> -0.0066783831 | F87: 25320.65 | G87: =F87/F86-1 -> 0.010858869
B88: 46024 | C88: 1593.7 | D88: =C88/C87-1 -> -0.060096721 | F88: 25693.7 | G88: =F88/F87-1 -> 0.014733034
B89: 46236 | C89: 1455.2 | D89: =C89/C88-1 -> -0.086904687 | F89: 25471.1 | G89: =F89/F88-1 -> -0.0086636024
B90: 02/15/2026 | C90: 1436.5 | D90: =C90/C89-1 -> -0.012850467 | F90: 25571.25 | G90: =F90/F89-1 -> 0.0039319071
B91: 02/22/2026 | C91: 1389.1 | D91: =C91/C90-1 -> -0.032996867 | F91: 25178.65 | G91: =F91/F90-1 -> -0.01535318
B92: 46025 | C92: 1356.7 | D92: =C92/C91-1 -> -0.023324455 | F92: 24450.45 | G92: =F92/F91-1 -> -0.028921328
B93: 46237 | C93: 1325.4 | D93: =C93/C92-1 -> -0.023070686 | F93: 23151.1 | G93: =F93/F92-1 -> -0.053142171
B94: 03/15/2026 | C94: 1333.7 | D94: =C94/C93-1 -> 0.0062622604 | F94: 23114.5 | G94: =F94/F93-1 -> -0.0015809184
B95: 03/22/2026 | C95: 1364.4 | D95: =C95/C94-1 -> 0.02301867 | F95: 22819.6 | G95: =F95/F94-1 -> -0.012758225
B96: 03/29/2026 | C96: 1402.2 | D96: =C96/C95-1 -> 0.027704485 | F96: 22713.1 | G96: =F96/F95-1 -> -0.0046670406
B97: 46146 | C97: 1451.2 | D97: =C97/C96-1 -> 0.034945086 | F97: 24050.6 | G97: =F97/F96-1 -> 0.058886722
B98: 46360 | C98: 1442.3 | D98: =C98/C97-1 -> -0.0061328556 | F98: 24353.55 | G98: =F98/F97-1 -> 0.012596359
B99: 04/19/2026 | C99: 1203.2 | D99: =C99/C98-1 -> -0.16577688 | F99: 23897.95 | G99: =F99/F98-1 -> -0.018707745
B100: 04/26/2026 | C100: 1199.1 | D100: =C100/C99-1 -> -0.0034075798 | F100: 23997.55 | G100: =F100/F99-1 -> 0.0041677215
B101: 46086 | C101: 1198.4 | D101: =C101/C100-1 -> -0.00058377116 | F101: 24176.15 | G101: =F101/F100-1 -> 0.0074424264
B102: 46300 | C102: 1132.6 | D102: =C102/C101-1 -> -0.054906542 | F102: 23643.5 | G102: =F102/F101-1 -> -0.022032044
B103: 05/17/2026 | C103: 1164 | D103: =C103/C102-1 -> 0.027723821 | F103: 23719.3 | G103: =F103/F102-1 -> 0.0032059551
B104: 05/24/2026 | C104: 1183.8 | D104: =C104/C103-1 -> 0.017010309 | F104: 23547.75 | G104: =F104/F103-1 -> -0.0072325069
...

Sheet WIPRO - Beta
B2: Source: Investing.com
B4: Regression Beta - 2 Years Weekly
B6: WIPRO Returns | F6: NIFTY Returns | I6: Beta Drifting
B8: Date | C8: Closing Price | D8: Return | F8: Closing Price | G8: Return | I8: Levered Raw Beta | J8: =SLOPE(D10:D183,G10:G183) -> 1.4755079
B9: 07/28/2024 | C9: 251.07 | F9: 24717.7 | I9: Raw Beta Weight | J9: 0.75
B10: 45390 | C10: 245.65 | D10: =C10/C9-1 -> -0.021587605 | F10: 24367.5 | G10: =F10/F9-1 -> -0.014167985
B11: 45604 | C11: 258.13 | D11: =C11/C10-1 -> 0.050803989 | F11: 24541.15 | G11: =F11/F10-1 -> 0.0071262953 | I11: Market Beta | J11: 1
B12: 08/18/2024 | C12: 256.2 | D12: =C12/C11-1 -> -0.0074768527 | F12: 24823.15 | G12: =F12/F11-1 -> 0.011490904 | I12: Market Beta Weight | J12: =100%-J9 -> 0.25
B13: 08/25/2024 | C13: 269.2 | D13: =C13/C12-1 -> 0.050741608 | F13: 25235.9 | G13: =F13/F12-1 -> 0.016627624
B14: 45300 | C14: 260.3 | D14: =C14/C13-1 -> -0.033060921 | F14: 24852.15 | G14: =F14/F13-1 -> -0.015206511 | I14: Adjusted Beta | J14: =(J8*J9)+(J11*J12) -> 1.3566309
B15: 45513 | C15: 275.3 | D15: =C15/C14-1 -> 0.057625816 | F15: 25356.5 | G15: =F15/F14-1 -> 0.020294019
B16: 09/15/2024 | C16: 269.55 | D16: =C16/C15-1 -> -0.020886306 | F16: 25790.95 | G16: =F16/F15-1 -> 0.017133674
B17: 09/22/2024 | C17: 270.9 | D17: =C17/C16-1 -> 0.0050083472 | F17: 26178.95 | G17: =F17/F16-1 -> 0.015044037
B18: 09/29/2024 | C18: 266.77 | D18: =C18/C17-1 -> -0.015245478 | F18: 25014.6 | G18: =F18/F17-1 -> -0.044476574
B19: 45453 | C19: 264.15 | D19: =C19/C18-1 -> -0.0098211943 | F19: 24964.25 | G19: =F19/F18-1 -> -0.0020128245
B20: 10/13/2024 | C20: 274.33 | D20: =C20/C19-1 -> 0.038538709 | F20: 24854.05 | G20: =F20/F19-1 -> -0.0044143125
B21: 10/20/2024 | C21: 271.73 | D21: =C21/C20-1 -> -0.0094776364 | F21: 24180.8 | G21: =F21/F20-1 -> -0.027088141
B22: 10/27/2024 | C22: 275.67 | D22: =C22/C21-1 -> 0.014499687 | F22: 24304.35 | G22: =F22/F21-1 -> 0.0051094257
B23: 45362 | C23: 284.5 | D23: =C23/C22-1 -> 0.032031052 | F23: 24148.2 | G23: =F23/F22-1 -> -0.0064247758
B24: 45576 | C24: 283.35 | D24: =C24/C23-1 -> -0.0040421793 | F24: 23532.7 | G24: =F24/F23-1 -> -0.025488442
B25: 11/17/2024 | C25: 285.83 | D25: =C25/C24-1 -> 0.0087524263 | F25: 23907.25 | G25: =F25/F24-1 -> 0.015916151
B26: 11/24/2024 | C26: 288.92 | D26: =C26/C25-1 -> 0.010810622 | F26: 24131.1 | G26: =F26/F25-1 -> 0.0093632685
B27: 45303 | C27: 297.35 | D27: =C27/C26-1 -> 0.029177627 | F27: 24677.8 | G27: =F27/F26-1 -> 0.022655411
B28: 45516 | C28: 309.95 | D28: =C28/C27-1 -> 0.042374306 | F28: 24768.3 | G28: =F28/F27-1 -> 0.0036672637
B29: 12/15/2024 | C29: 305.2 | D29: =C29/C28-1 -> -0.015325052 | F29: 23587.5 | G29: =F29/F28-1 -> -0.047673841
B30: 12/22/2024 | C30: 309.1 | D30: =C30/C29-1 -> 0.012778506 | F30: 23813.4 | G30: =F30/F29-1 -> 0.0095771065
B31: 12/29/2024 | C31: 294.45 | D31: =C31/C30-1 -> -0.047395665 | F31: 24004.75 | G31: =F31/F30-1 -> 0.0080353918
B32: 45778 | C32: 300.55 | D32: =C32/C31-1 -> 0.02071659 | F32: 23431.5 | G32: =F32/F31-1 -> -0.02388069
B33: 45992 | C33: 281.95 | D33: =C33/C32-1 -> -0.061886541 | F33: 23203.2 | G33: =F33/F32-1 -> -0.0097432943
B34: 01/19/2025 | C34: 320.1 | D34: =C34/C33-1 -> 0.13530768 | F34: 23092.2 | G34: =F34/F33-1 -> -0.0047838229
B35: 01/26/2025 | C35: 311.9 | D35: =C35/C34-1 -> -0.025616995 | F35: 23508.4 | G35: =F35/F34-1 -> 0.018023402
B36: 45690 | C36: 318 | D36: =C36/C35-1 -> 0.01955755 | F36: 23559.95 | G36: =F36/F35-1 -> 0.0021928332
B37: 45902 | C37: 308.1 | D37: =C37/C36-1 -> -0.031132075 | F37: 22929.25 | G37: =F37/F36-1 -> -0.026770006
B38: 02/16/2025 | C38: 306.35 | D38: =C38/C37-1 -> -0.005679974 | F38: 22795.9 | G38: =F38/F37-1 -> -0.0058157157
B39: 02/23/2025 | C39: 277.65 | D39: =C39/C38-1 -> -0.093683695 | F39: 22124.7 | G39: =F39/F38-1 -> -0.029443891
B40: 45691 | C40: 284.8 | D40: =C40/C39-1 -> 0.025751846 | F40: 22552.5 | G40: =F40/F39-1 -> 0.019335855
B41: 45903 | C41: 264 | D41: =C41/C40-1 -> -0.073033708 | F41: 22397.2 | G41: =F41/F40-1 -> -0.0068861545
B42: 03/16/2025 | C42: 264.3 | D42: =C42/C41-1 -> 0.0011363636 | F42: 23350.4 | G42: =F42/F41-1 -> 0.042558891
B43: 03/23/2025 | C43: 262.25 | D43: =C43/C42-1 -> -0.0077563375 | F43: 23519.35 | G43: =F43/F42-1 -> 0.0072354221
B44: 03/30/2025 | C44: 246.3 | D44: =C44/C43-1 -> -0.060819828 | F44: 22904.45 | G44: =F44/F43-1 -> -0.02614443
B45: 45812 | C45: 239.75 | D45: =C45/C44-1 -> -0.026593585 | F45: 22828.55 | G45: =F45/F44-1 -> -0.0033137665
B46: 04/13/2025 | C46: 236.9 | D46: =C46/C45-1 -> -0.011887383 | F46: 23851.65 | G46: =F46/F45-1 -> 0.044816688
B47: 04/20/2025 | C47: 240.9 | D47: =C47/C46-1 -> 0.016884762 | F47: 24039.35 | G47: =F47/F46-1 -> 0.0078694765
B48: 04/27/2025 | C48: 242.87 | D48: =C48/C47-1 -> 0.0081776671 | F48: 24346.7 | G48: =F48/F47-1 -> 0.012785287
B49: 45752 | C49: 242.01 | D49: =C49/C48-1 -> -0.003540989 | F49: 24008 | G49: =F49/F48-1 -> -0.013911536
B50: 45966 | C50: 254.31 | D50: =C50/C49-1 -> 0.050824346 | F50: 25019.8 | G50: =F50/F49-1 -> 0.042144285
B51: 05/18/2025 | C51: 247.36 | D51: =C51/C50-1 -> -0.027328851 | F51: 24853.15 | G51: =F51/F50-1 -> -0.0066607247
B52: 05/25/2025 | C52: 249.67 | D52: =C52/C51-1 -> 0.0093386158 | F52: 24750.7 | G52: =F52/F51-1 -> -0.0041222139
B53: 45663 | C53: 248.59 | D53: =C53/C52-1 -> -0.0043257099 | F53: 25003.05 | G53: =F53/F52-1 -> 0.010195671
B54: 45875 | C54: 260.21 | D54: =C54/C53-1 -> 0.046743634 | F54: 24718.6 | G54: =F54/F53-1 -> -0.011376612
B55: 06/15/2025 | C55: 266.54 | D55: =C55/C54-1 -> 0.024326506 | F55: 25112.4 | G55: =F55/F54-1 -> 0.015931323
B56: 06/22/2025 | C56: 265.05 | D56: =C56/C55-1 -> -0.0055901553 | F56: 25637.8 | G56: =F56/F55-1 -> 0.020921935
B57: 06/29/2025 | C57: 270.05 | D57: =C57/C56-1 -> 0.018864365 | F57: 25461 | G57: =F57/F56-1 -> -0.0068960675
B58: 45815 | C58: 258.3 | D58: =C58/C57-1 -> -0.043510461 | F58: 25149.85 | G58: =F58/F57-1 -> -0.012220651
B59: 07/13/2025 | C59: 266.95 | D59: =C59/C58-1 -> 0.033488192 | F59: 24968.4 | G59: =F59/F58-1 -> -0.0072147548
B60: 07/20/2025 | C60: 259.2 | D60: =C60/C59-1 -> -0.029031654 | F60: 24837 | G60: =F60/F59-1 -> -0.005262652
B61: 07/27/2025 | C61: 242.75 | D61: =C61/C60-1 -> -0.063464506 | F61: 24565.35 | G61: =F61/F60-1 -> -0.010937311
B62: 45724 | C62: 239.05 | D62: =C62/C61-1 -> -0.015242019 | F62: 24363.3 | G62: =F62/F61-1 -> -0.0082249998
B63: 45938 | C63: 246.81 | D63: =C63/C62-1 -> 0.032461828 | F63: 24631.3 | G63: =F63/F62-1 -> 0.011000152
B64: 08/17/2025 | C64: 248.64 | D64: =C64/C63-1 -> 0.0074146104 | F64: 24870.1 | G64: =F64/F63-1 -> 0.0096949816
B65: 08/24/2025 | C65: 249.41 | D65: =C65/C64-1 -> 0.0030968468 | F65: 24426.85 | G65: =F65/F64-1 -> -0.017822606
B66: 08/31/2025 | C66: 243.67 | D66: =C66/C65-1 -> -0.023014314 | F66: 24741 | G66: =F66/F65-1 -> 0.012860848
B67: 45847 | C67: 251.94 | D67: =C67/C66-1 -> 0.033939344 | F67: 25114 | G67: =F67/F66-1 -> 0.015076189
B68: 09/14/2025 | C68: 255.88 | D68: =C68/C67-1 -> 0.015638644 | F68: 25327.05 | G68: =F68/F67-1 -> 0.0084833161
B69: 09/21/2025 | C69: 235.75 | D69: =C69/C68-1 -> -0.078669689 | F69: 24654.7 | G69: =F69/F68-1 -> -0.026546716
B70: 09/28/2025 | C70: 240.98 | D70: =C70/C69-1 -> 0.022184517 | F70: 24894.25 | G70: =F70/F69-1 -> 0.0097162002
B71: 45787 | C71: 248.7 | D71: =C71/C70-1 -> 0.032035854 | F71: 25285.35 | G71: =F71/F70-1 -> 0.015710455
B72: 46001 | C72: 240.9 | D72: =C72/C71-1 -> -0.031363088 | F72: 25709.85 | G72: =F72/F71-1 -> 0.016788377
B73: 10/19/2025 | C73: 242.98 | D73: =C73/C72-1 -> 0.0086342881 | F73: 25795.15 | G73: =F73/F72-1 -> 0.0033177945
B74: 10/26/2025 | C74: 240.67 | D74: =C74/C73-1 -> -0.0095069553 | F74: 25722.1 | G74: =F74/F73-1 -> -0.0028319277
B75: 45699 | C75: 236.49 | D75: =C75/C74-1 -> -0.01736818 | F75: 25492.3 | G75: =F75/F74-1 -> -0.0089339517
B76: 45911 | C76: 244.37 | D76: =C76/C75-1 -> 0.033320648 | F76: 25910.05 | G76: =F76/F75-1 -> 0.016387301
B77: 11/16/2025 | C77: 244.49 | D77: =C77/C76-1 -> 0.00049105864 | F77: 26068.15 | G77: =F77/F76-1 -> 0.0061018794
B78: 11/23/2025 | C78: 249.53 | D78: =C78/C77-1 -> 0.02061434 | F78: 26202.95 | G78: =F78/F77-1 -> 0.0051710612
B79: 11/30/2025 | C79: 259.91 | D79: =C79/C78-1 -> 0.041598205 | F79: 26186.45 | G79: =F79/F78-1 -> -0.00062970009
B80: 45850 | C80: 260.6 | D80: =C80/C79-1 -> 0.0026547651 | F80: 26046.95 | G80: =F80/F79-1 -> -0.0053271826
B81: 12/14/2025 | C81: 264.45 | D81: =C81/C80-1 -> 0.014773599 | F81: 25966.4 | G81: =F81/F80-1 -> -0.0030924926
B82: 12/21/2025 | C82: 266.3 | D82: =C82/C81-1 -> 0.0069956514 | F82: 26042.3 | G82: =F82/F81-1 -> 0.0029230082
B83: 12/28/2025 | C83: 269 | D83: =C83/C82-1 -> 0.010138941 | F83: 26328.55 | G83: =F83/F82-1 -> 0.010991733
B84: 46113 | C84: 261.95 | D84: =C84/C83-1 -> -0.026208178 | F84: 25683.3 | G84: =F84/F83-1 -> -0.024507616
B85: 46327 | C85: 267.45 | D85: =C85/C84-1 -> 0.020996373 | F85: 25694.35 | G85: =F85/F84-1 -> 0.00043024066
B86: 01/18/2026 | C86: 238.4 | D86: =C86/C85-1 -> -0.10861843 | F86: 25048.65 | G86: =F86/F85-1 -> -0.025130038
B87: 01/25/2026 | C87: 236.9 | D87: =C87/C86-1 -> -0.0062919463 | F87: 25320.65 | G87: =F87/F86-1 -> 0.010858869
B88: 46024 | C88: 230.72 | D88: =C88/C87-1 -> -0.026086957 | F88: 25693.7 | G88: =F88/F87-1 -> 0.014733034
B89: 46236 | C89: 214.09 | D89: =C89/C88-1 -> -0.07207871 | F89: 25471.1 | G89: =F89/F88-1 -> -0.0086636024
B90: 02/15/2026 | C90: 209.86 | D90: =C90/C89-1 -> -0.019758046 | F90: 25571.25 | G90: =F90/F89-1 -> 0.0039319071
B91: 02/22/2026 | C91: 200.96 | D91: =C91/C90-1 -> -0.042409225 | F91: 25178.65 | G91: =F91/F90-1 -> -0.01535318
B92: 46025 | C92: 195.4 | D92: =C92/C91-1 -> -0.027667197 | F92: 24450.45 | G92: =F92/F91-1 -> -0.028921328
B93: 46237 | C93: 197.58 | D93: =C93/C92-1 -> 0.011156602 | F93: 23151.1 | G93: =F93/F92-1 -> -0.053142171
B94: 03/15/2026 | C94: 190.9 | D94: =C94/C93-1 -> -0.03380909 | F94: 23114.5 | G94: =F94/F93-1 -> -0.0015809184
B95: 03/22/2026 | C95: 191.6 | D95: =C95/C94-1 -> 0.0036668413 | F95: 22819.6 | G95: =F95/F94-1 -> -0.012758225
B96: 03/29/2026 | C96: 194.91 | D96: =C96/C95-1 -> 0.017275574 | F96: 22713.1 | G96: =F96/F95-1 -> -0.0046670406
B97: 46146 | C97: 204.88 | D97: =C97/C96-1 -> 0.051151814 | F97: 24050.6 | G97: =F97/F96-1 -> 0.058886722
B98: 46360 | C98: 204.32 | D98: =C98/C97-1 -> -0.0027333073 | F98: 24353.55 | G98: =F98/F97-1 -> 0.012596359
B99: 04/19/2026 | C99: 199.36 | D99: =C99/C98-1 -> -0.024275646 | F99: 23897.95 | G99: =F99/F98-1 -> -0.018707745
B100: 04/26/2026 | C100: 200.65 | D100: =C100/C99-1 -> 0.0064707063 | F100: 23997.55 | G100: =F100/F99-1 -> 0.0041677215
B101: 46086 | C101: 197.91 | D101: =C101/C100-1 -> -0.013655619 | F101: 24176.15 | G101: =F101/F100-1 -> 0.0074424264
B102: 46300 | C102: 190 | D102: =C102/C101-1 -> -0.039967662 | F102: 23643.5 | G102: =F102/F101-1 -> -0.022032044
B103: 05/17/2026 | C103: 203.11 | D103: =C103/C102-1 -> 0.069 | F103: 23719.3 | G103: =F103/F102-1 -> 0.0032059551
B104: 05/24/2026 | C104: 204.25 | D104: =C104/C103-1 -> 0.0056127222 | F104: 23547.75 | G104: =F104/F103-1 -> -0.0072325069
...

Sheet Tech Mahindra - Beta
B2: Source: Investing.com
B4: Regression Beta - 2 Years Weekly
B6: Tech Mahindra | F6: NIFTY Returns | I6: Beta Drifting
B8: Date | C8: Closing Price | D8: Return | F8: Closing Price | G8: Return | I8: Levered Raw Beta | J8: =SLOPE(D10:D112,G10:G112) -> 0.6902984
B9: 07/28/2024 | C9: 1507.7 | F9: 24717.7 | I9: Raw Beta Weight | J9: 0.75
B10: 45390 | C10: 1506.7 | D10: =C10/C9-1 -> -0.00066326192 | F10: 24367.5 | G10: =F10/F9-1 -> -0.014167985
B11: 45604 | C11: 1585.3 | D11: =C11/C10-1 -> 0.052166987 | F11: 24541.15 | G11: =F11/F10-1 -> 0.0071262953 | I11: Market Beta | J11: 1
B12: 08/18/2024 | C12: 1598.4 | D12: =C12/C11-1 -> 0.0082634202 | F12: 24823.15 | G12: =F12/F11-1 -> 0.011490904 | I12: Market Beta Weight | J12: =100%-J9 -> 0.25
B13: 08/25/2024 | C13: 1636.5 | D13: =C13/C12-1 -> 0.023836336 | F13: 25235.9 | G13: =F13/F12-1 -> 0.016627624
B14: 45300 | C14: 1623.25 | D14: =C14/C13-1 -> -0.0080965475 | F14: 24852.15 | G14: =F14/F13-1 -> -0.015206511 | I14: Adjusted Beta | J14: =(J8*J9)+(J11*J12) -> 0.7677238
B15: 45513 | C15: 1656.05 | D15: =C15/C14-1 -> 0.020206376 | F15: 25356.5 | G15: =F15/F14-1 -> 0.020294019
B16: 09/15/2024 | C16: 1622.05 | D16: =C16/C15-1 -> -0.020530781 | F16: 25790.95 | G16: =F16/F15-1 -> 0.017133674
B17: 09/22/2024 | C17: 1609.25 | D17: =C17/C16-1 -> -0.0078912487 | F17: 26178.95 | G17: =F17/F16-1 -> 0.015044037
B18: 09/29/2024 | C18: 1616.45 | D18: =C18/C17-1 -> 0.0044741339 | F18: 25014.6 | G18: =F18/F17-1 -> -0.044476574
B19: 45453 | C19: 1647.05 | D19: =C19/C18-1 -> 0.018930372 | F19: 24964.25 | G19: =F19/F18-1 -> -0.0020128245
B20: 10/13/2024 | C20: 1687.9 | D20: =C20/C19-1 -> 0.024801919 | F20: 24854.05 | G20: =F20/F19-1 -> -0.0044143125
B21: 10/20/2024 | C21: 1716.45 | D21: =C21/C20-1 -> 0.016914509 | F21: 24180.8 | G21: =F21/F20-1 -> -0.027088141
B22: 10/27/2024 | C22: 1603.65 | D22: =C22/C21-1 -> -0.065717032 | F22: 24304.35 | G22: =F22/F21-1 -> 0.0051094257
B23: 45362 | C23: 1681.35 | D23: =C23/C22-1 -> 0.048451969 | F23: 24148.2 | G23: =F23/F22-1 -> -0.0064247758
B24: 45576 | C24: 1687.5 | D24: =C24/C23-1 -> 0.003657775 | F24: 23532.7 | G24: =F24/F23-1 -> -0.025488442
B25: 11/17/2024 | C25: 1747.45 | D25: =C25/C24-1 -> 0.035525926 | F25: 23907.25 | G25: =F25/F24-1 -> 0.015916151
B26: 11/24/2024 | C26: 1712.3 | D26: =C26/C25-1 -> -0.020115025 | F26: 24131.1 | G26: =F26/F25-1 -> 0.0093632685
B27: 45303 | C27: 1782.8 | D27: =C27/C26-1 -> 0.041172692 | F27: 24677.8 | G27: =F27/F26-1 -> 0.022655411
B28: 45516 | C28: 1796.4 | D28: =C28/C27-1 -> 0.0076284496 | F28: 24768.3 | G28: =F28/F27-1 -> 0.0036672637
B29: 12/15/2024 | C29: 1686.05 | D29: =C29/C28-1 -> -0.061428412 | F29: 23587.5 | G29: =F29/F28-1 -> -0.047673841
B30: 12/22/2024 | C30: 1711.65 | D30: =C30/C29-1 -> 0.015183417 | F30: 23813.4 | G30: =F30/F29-1 -> 0.0095771065
B31: 12/29/2024 | C31: 1689.45 | D31: =C31/C30-1 -> -0.012969941 | F31: 24004.75 | G31: =F31/F30-1 -> 0.0080353918
B32: 45778 | C32: 1705.6 | D32: =C32/C31-1 -> 0.009559324 | F32: 23431.5 | G32: =F32/F31-1 -> -0.02388069
B33: 45992 | C33: 1660.3 | D33: =C33/C32-1 -> -0.026559568 | F33: 23203.2 | G33: =F33/F32-1 -> -0.0097432943
B34: 01/19/2025 | C34: 1723.05 | D34: =C34/C33-1 -> 0.037794375 | F34: 23092.2 | G34: =F34/F33-1 -> -0.0047838229
B35: 01/26/2025 | C35: 1674.45 | D35: =C35/C34-1 -> -0.028205798 | F35: 23508.4 | G35: =F35/F34-1 -> 0.018023402
B36: 45690 | C36: 1692.1 | D36: =C36/C35-1 -> 0.010540775 | F36: 23559.95 | G36: =F36/F35-1 -> 0.0021928332
B37: 45902 | C37: 1659.1 | D37: =C37/C36-1 -> -0.019502393 | F37: 22929.25 | G37: =F37/F36-1 -> -0.026770006
B38: 02/16/2025 | C38: 1649.5 | D38: =C38/C37-1 -> -0.0057862697 | F38: 22795.9 | G38: =F38/F37-1 -> -0.0058157157
B39: 02/23/2025 | C39: 1487.85 | D39: =C39/C38-1 -> -0.097999394 | F39: 22124.7 | G39: =F39/F38-1 -> -0.029443891
B40: 45691 | C40: 1492.35 | D40: =C40/C39-1 -> 0.0030244984 | F40: 22552.5 | G40: =F40/F39-1 -> 0.019335855
B41: 45903 | C41: 1440.65 | D41: =C41/C40-1 -> -0.034643348 | F41: 22397.2 | G41: =F41/F40-1 -> -0.0068861545
B42: 03/16/2025 | C42: 1409.25 | D42: =C42/C41-1 -> -0.021795717 | F42: 23350.4 | G42: =F42/F41-1 -> 0.042558891
B43: 03/23/2025 | C43: 1418.25 | D43: =C43/C42-1 -> 0.0063863757 | F43: 23519.35 | G43: =F43/F42-1 -> 0.0072354221
B44: 03/30/2025 | C44: 1320.95 | D44: =C44/C43-1 -> -0.068605676 | F44: 22904.45 | G44: =F44/F43-1 -> -0.02614443
B45: 45812 | C45: 1282.25 | D45: =C45/C44-1 -> -0.029297097 | F45: 22828.55 | G45: =F45/F44-1 -> -0.0033137665
B46: 04/13/2025 | C46: 1306.8 | D46: =C46/C45-1 -> 0.019146032 | F46: 23851.65 | G46: =F46/F45-1 -> 0.044816688
B47: 04/20/2025 | C47: 1462 | D47: =C47/C46-1 -> 0.11876339 | F47: 24039.35 | G47: =F47/F46-1 -> 0.0078694765
B48: 04/27/2025 | C48: 1496.3 | D48: =C48/C47-1 -> 0.023461012 | F48: 24346.7 | G48: =F48/F47-1 -> 0.012785287
B49: 45752 | C49: 1493.7 | D49: =C49/C48-1 -> -0.0017376195 | F49: 24008 | G49: =F49/F48-1 -> -0.013911536
B50: 45966 | C50: 1617 | D50: =C50/C49-1 -> 0.082546696 | F50: 25019.8 | G50: =F50/F49-1 -> 0.042144285
B51: 05/18/2025 | C51: 1580.3 | D51: =C51/C50-1 -> -0.022696351 | F51: 24853.15 | G51: =F51/F50-1 -> -0.0066607247
B52: 05/25/2025 | C52: 1573.9 | D52: =C52/C51-1 -> -0.0040498639 | F52: 24750.7 | G52: =F52/F51-1 -> -0.0041222139
B53: 45663 | C53: 1571.1 | D53: =C53/C52-1 -> -0.0017790203 | F53: 25003.05 | G53: =F53/F52-1 -> 0.010195671
B54: 45875 | C54: 1659 | D54: =C54/C53-1 -> 0.055948062 | F54: 24718.6 | G54: =F54/F53-1 -> -0.011376612
B55: 06/15/2025 | C55: 1696.1 | D55: =C55/C54-1 -> 0.022362869 | F55: 25112.4 | G55: =F55/F54-1 -> 0.015931323
B56: 06/22/2025 | C56: 1674.4 | D56: =C56/C55-1 -> -0.012794057 | F56: 25637.8 | G56: =F56/F55-1 -> 0.020921935
B57: 06/29/2025 | C57: 1655.2 | D57: =C57/C56-1 -> -0.011466794 | F57: 25461 | G57: =F57/F56-1 -> -0.0068960675
B58: 45815 | C58: 1602.5 | D58: =C58/C57-1 -> -0.031839053 | F58: 25149.85 | G58: =F58/F57-1 -> -0.012220651
B59: 07/13/2025 | C59: 1548.9 | D59: =C59/C58-1 -> -0.033447738 | F59: 24968.4 | G59: =F59/F58-1 -> -0.0072147548
B60: 07/20/2025 | C60: 1461.9 | D60: =C60/C59-1 -> -0.056168894 | F60: 24837 | G60: =F60/F59-1 -> -0.005262652
B61: 07/27/2025 | C61: 1438.8 | D61: =C61/C60-1 -> -0.015801354 | F61: 24565.35 | G61: =F61/F60-1 -> -0.010937311
B62: 45724 | C62: 1480.4 | D62: =C62/C61-1 -> 0.028912983 | F62: 24363.3 | G62: =F62/F61-1 -> -0.0082249998
B63: 45938 | C63: 1486.7 | D63: =C63/C62-1 -> 0.0042556066 | F63: 24631.3 | G63: =F63/F62-1 -> 0.011000152
B64: 08/17/2025 | C64: 1505 | D64: =C64/C63-1 -> 0.012309141 | F64: 24870.1 | G64: =F64/F63-1 -> 0.0096949816
B65: 08/24/2025 | C65: 1481.4 | D65: =C65/C64-1 -> -0.015681063 | F65: 24426.85 | G65: =F65/F64-1 -> -0.017822606
B66: 08/31/2025 | C66: 1477.9 | D66: =C66/C65-1 -> -0.0023626299 | F66: 24741 | G66: =F66/F65-1 -> 0.012860848
B67: 45847 | C67: 1525.5 | D67: =C67/C66-1 -> 0.032207863 | F67: 25114 | G67: =F67/F66-1 -> 0.015076189
B68: 09/14/2025 | C68: 1553.8 | D68: =C68/C67-1 -> 0.018551295 | F68: 25327.05 | G68: =F68/F67-1 -> 0.0084833161
B69: 09/21/2025 | C69: 1407.7 | D69: =C69/C68-1 -> -0.094027545 | F69: 24654.7 | G69: =F69/F68-1 -> -0.026546716
B70: 09/28/2025 | C70: 1400.6 | D70: =C70/C69-1 -> -0.0050436883 | F70: 24894.25 | G70: =F70/F69-1 -> 0.0097162002
B71: 45787 | C71: 1457.2 | D71: =C71/C70-1 -> 0.040411252 | F71: 25285.35 | G71: =F71/F70-1 -> 0.015710455
B72: 46001 | C72: 1447.6 | D72: =C72/C71-1 -> -0.0065879769 | F72: 25709.85 | G72: =F72/F71-1 -> 0.016788377
B73: 10/19/2025 | C73: 1453.7 | D73: =C73/C72-1 -> 0.0042138712 | F73: 25795.15 | G73: =F73/F72-1 -> 0.0033177945
B74: 10/26/2025 | C74: 1424.4 | D74: =C74/C73-1 -> -0.020155465 | F74: 25722.1 | G74: =F74/F73-1 -> -0.0028319277
B75: 45699 | C75: 1386.7 | D75: =C75/C74-1 -> -0.026467284 | F75: 25492.3 | G75: =F75/F74-1 -> -0.0089339517
B76: 45911 | C76: 1439.2 | D76: =C76/C75-1 -> 0.037859667 | F76: 25910.05 | G76: =F76/F75-1 -> 0.016387301
B77: 11/16/2025 | C77: 1461.5 | D77: =C77/C76-1 -> 0.015494719 | F77: 26068.15 | G77: =F77/F76-1 -> 0.0061018794
B78: 11/23/2025 | C78: 1517.3 | D78: =C78/C77-1 -> 0.038179952 | F78: 26202.95 | G78: =F78/F77-1 -> 0.0051710612
B79: 11/30/2025 | C79: 1570.8 | D79: =C79/C78-1 -> 0.035260001 | F79: 26186.45 | G79: =F79/F78-1 -> -0.00062970009
B80: 45850 | C80: 1578.4 | D80: =C80/C79-1 -> 0.004838299 | F80: 26046.95 | G80: =F80/F79-1 -> -0.0053271826
B81: 12/14/2025 | C81: 1612.5 | D81: =C81/C80-1 -> 0.021604156 | F81: 25966.4 | G81: =F81/F80-1 -> -0.0030924926
B82: 12/21/2025 | C82: 1612.3 | D82: =C82/C81-1 -> -0.00012403101 | F82: 26042.3 | G82: =F82/F81-1 -> 0.0029230082
B83: 12/28/2025 | C83: 1612 | D83: =C83/C82-1 -> -0.00018606959 | F83: 26328.55 | G83: =F83/F82-1 -> 0.010991733
B84: 46113 | C84: 1582.2 | D84: =C84/C83-1 -> -0.018486352 | F84: 25683.3 | G84: =F84/F83-1 -> -0.024507616
B85: 46327 | C85: 1670.5 | D85: =C85/C84-1 -> 0.055808368 | F85: 25694.35 | G85: =F85/F84-1 -> 0.00043024066
B86: 01/18/2026 | C86: 1701.1 | D86: =C86/C85-1 -> 0.018317869 | F86: 25048.65 | G86: =F86/F85-1 -> -0.025130038
B87: 01/25/2026 | C87: 1743.1 | D87: =C87/C86-1 -> 0.024689907 | F87: 25320.65 | G87: =F87/F86-1 -> 0.010858869
B88: 46024 | C88: 1619.9 | D88: =C88/C87-1 -> -0.070678676 | F88: 25693.7 | G88: =F88/F87-1 -> 0.014733034
B89: 46236 | C89: 1534.4 | D89: =C89/C88-1 -> -0.052781036 | F89: 25471.1 | G89: =F89/F88-1 -> -0.0086636024
B90: 02/15/2026 | C90: 1456.9 | D90: =C90/C89-1 -> -0.050508342 | F90: 25571.25 | G90: =F90/F89-1 -> 0.0039319071
B91: 02/22/2026 | C91: 1357.8 | D91: =C91/C90-1 -> -0.068021141 | F91: 25178.65 | G91: =F91/F90-1 -> -0.01535318
B92: 46025 | C92: 1331.7 | D92: =C92/C91-1 -> -0.019222271 | F92: 24450.45 | G92: =F92/F91-1 -> -0.028921328
B93: 46237 | C93: 1332.8 | D93: =C93/C92-1 -> 0.00082601186 | F93: 23151.1 | G93: =F93/F92-1 -> -0.053142171
B94: 03/15/2026 | C94: 1384.8 | D94: =C94/C93-1 -> 0.039015606 | F94: 23114.5 | G94: =F94/F93-1 -> -0.0015809184
B95: 03/22/2026 | C95: 1391.6 | D95: =C95/C94-1 -> 0.0049104564 | F95: 22819.6 | G95: =F95/F94-1 -> -0.012758225
B96: 03/29/2026 | C96: 1441.5 | D96: =C96/C95-1 -> 0.035858005 | F96: 22713.1 | G96: =F96/F95-1 -> -0.0046670406
B97: 46146 | C97: 1440.2 | D97: =C97/C96-1 -> -0.00090183836 | F97: 24050.6 | G97: =F97/F96-1 -> 0.058886722
B98: 46360 | C98: 1511.4 | D98: =C98/C97-1 -> 0.049437578 | F98: 24353.55 | G98: =F98/F97-1 -> 0.012596359
B99: 04/19/2026 | C99: 1358.5 | D99: =C99/C98-1 -> -0.10116448 | F99: 23897.95 | G99: =F99/F98-1 -> -0.018707745
B100: 04/26/2026 | C100: 1473.5 | D100: =C100/C99-1 -> 0.08465219 | F100: 23997.55 | G100: =F100/F99-1 -> 0.0041677215
B101: 46086 | C101: 1463 | D101: =C101/C100-1 -> -0.0071258907 | F101: 24176.15 | G101: =F101/F100-1 -> 0.0074424264
B102: 46300 | C102: 1370.5 | D102: =C102/C101-1 -> -0.063226247 | F102: 23643.5 | G102: =F102/F101-1 -> -0.022032044
B103: 05/17/2026 | C103: 1422.2 | D103: =C103/C102-1 -> 0.037723459 | F103: 23719.3 | G103: =F103/F102-1 -> 0.0032059551
B104: 05/24/2026 | C104: 1483.9 | D104: =C104/C103-1 -> 0.04338349 | F104: 23547.75 | G104: =F104/F103-1 -> -0.0072325069
...

Sheet Rm
B2: Source: Screener.in
B4: Return on Markets
B6: Year | C6: Annual Return
B7: 2000 | C7: -0.1465 | E7: Average Return | G7: =AVERAGE(C7:C32) -> 0.15149231
B8: 2001 | C8: -0.1618 | E8: Dividend Yield | G8: 0.013 | H8: 1
B9: 2002 | C9: 0.0325 | E9: Total Market Return | G9: =SUM(G7:G8) -> 0.16449231
B10: 2003 | C10: 0.719
B11: 2004 | C11: 0.1068
B12: 2005 | C12: 0.3634
B13: 2006 | C13: 0.3983
B14: 2007 | C14: 0.5477
B15: 2008 | C15: -0.5179
B16: 2009 | C16: 0.7576
B17: 2010 | C17: 0.1795
B18: 2011 | C18: -0.2462
B19: 2012 | C19: 0.277
B20: 2013 | C20: 0.0676
B21: 2014 | C21: 0.3139
... B32: 2025 | C32: 0.1051

Sheet DCF>
B2: ALL VALUES ARE IN CRORES
B4: Calculation of PV of FCFF | F4: 46082 | G4: =F4+365 -> 46447 | H4: =G4+366 -> 46813 | I4: =H4+365 -> 47178 | J4: =I4+365 -> 47543 | K4: =J4+365 -> 47908
B6: EBIT | F6: ='Intrinsic Growth'!K35 -> 21880 | G6: =F6*(1+$D$17) -> 23083.4 | H6: =G6*(1+$D$17) -> 24352.987 | I6: =H6*(1+$D$17) -> 25692.401 | J6: =I6*(1+$D$17) -> 27105.483 | K6: =J6*(1+$D$17) -> 28596.285
B7: Tax Rate | F7: 0.25 | G7: 0.25 | H7: 0.25 | I7: 0.25 | J7: 0.25 | K7: 0.25
B8: EBIT(1-Tax) | F8: =F6*(1-F7) -> 16410 | G8: =G6*(1-G7) -> 17312.55 | H8: =H6*(1-H7) -> 18264.74 | I8: =I6*(1-I7) -> 19269.301 | J8: =J6*(1-J7) -> 20329.113 | K8: =K6*(1-K7) -> 21447.214
B9: less: Reinvestment Rate | F9: 0.5806 | G9: =F9+(($K$9-$F$9)/4) -> 0.48388231 | H9: =G9+(($K$9-$F$9)/4) -> 0.38716463 | I9: =H9+(($K$9-$F$9)/4) -> 0.29044694 | J9: =I9+(($K$9-$F$9)/4) -> 0.19372926 | K9: ='Intrinsic Growth'!K54 -> 0.19372926
B10: Free Cash Flow to Firm(FCFF) | F10: =F8*(1-F9) -> 6882.354 | G10: =G8*(1-G9) -> 8935.3132 | H10: =H8*(1-H9) -> 11193.279 | I10: =I8*(1-I9) -> 13672.591 | J10: =J8*(1-J9) -> 16390.769 | K10: =K8*(1-K9) -> 17292.261
B11: Mid Year Convention | G11: 0.5 | H11: =G11+1 -> 1.5 | I11: =H11+1 -> 2.5 | J11: =I11+1 -> 3.5 | K11: =J11+1 -> 4.5
B12: Discounting Factor | G12: =1/(1+$D$18)^G11 -> 0.93953292 | H12: =1/(1+$D$18)^H11 -> 0.82934649 | I12: =1/(1+$D$18)^I11 -> 0.73208249 | J12: =1/(1+$D$18)^J11 -> 0.64622541 | K12: =1/(1+$D$18)^K11 -> 0.57043746
B14: PV of FCFF | G14: =G10*G12 -> 8395.021 | H14: =H10*H12 -> 9283.1066 | I14: =I10*I12 -> 10009.465 | J14: =J10*J12 -> 10592.131 | K14: =K10*K12 -> 9864.1534
B16: Expected growth | D16: 0.1659
B17: Terminal Growth | D17: 0.055
B18: WACC | D18: ='WACC>'!K43 -> 0.13285935
B20: Calculation of Terminal Value | F20: Sensitivity Aanalysis Operatig Assets | L20: Sensitivity Aanalysis per share
B22: FCFF(n+1) | D22: =K10*(1+D16) -> 20161.047 | F22: =D33 -> 195854.04 | G22: 0.11 | H22: 0.1329 | I22: 0.15 | J22: 0.1855 | L22: =D40 -> 516.94993 | M22: 0.11 | N22: 0.1329 | O22: 0.15 | P22: 0.1855
B23: WACC | D23: =D18 -> 0.13285935 | F23: 0.03 | G23: 191901.58 | H23: 159908.86 | I23: 143982.35 | J23: 122102.82 | L23: 0.03 | M23: 507.16809 | N23: 427.99003 | O23: 388.57388 | P23: 334.42475
B24: Terminal Growth Rate | D24: =D17 -> 0.055 | F24: 0.04 | G24: 212438.4 | H24: 171939.53 | I24: 152694.94 | J24: 127185.91 | L24: 0.04 | M24: 557.99419 | N24: 457.76448 | O24: 410.13646 | P24: 347.00477
F25: 0.055 | G25: 257245.99 | H25: 195776.95 | I25: 169203 | J25: 136271.21 | L25: 0.055 | M25: 668.88748 | N25: 516.75915 | O25: 450.99189 | P25: 369.48975
B26: Terminal Value | D26: =D22/(D23-D24) -> 258941.9 | F26: 0.0675 | G26: 318746.62 | H26: 223994.28 | I26: 187545.29 | J26: 145606.73 | L26: 0.0675 | M26: 821.09396 | N26: 586.59358 | O26: 496.3868 | P26: 392.59402
F27: 0.0825 | G27: 466348.11 | H27: 276330.71 | I27: 218523.38 | J27: 159800.35 | L27: 0.0825 | M27: 1186.3895 | N27: 716.11981 | O27: 573.05377 | P27: 427.72148
F28: 0.07 | G28: 335659.29 | H28: 230983.57 | I28: 191901.58 | J28: 147716.31
B29: Calculation of Share Equity Value per share
B31: =B14 -> PV of FCFF | D31: =SUM(G14:K14) -> 48143.877
B32: PV of Terminal Value | D32: =D26*K12 -> 147710.16
B33: Value of Operating Assets | D33: =SUM(D31:D32) -> 195854.04
B35: Add: Cash | D35: ='Infosys Raw FS'!N37 -> 22201
B36: Less: Debt | D36: ='Infosys Raw FS'!N10 -> 9176
B37: Value of Equity | D37: =D33+D35-D36 -> 208879.04
B38: No. of Shares | D38: ='Raw Data Sheet'!B6 -> 404.06048
B40: Equity Value per share | D40: =D37/D38 -> 516.94993
B42: Share Price | D42: 1041
B43: Discount/Premium | D43: =D42/D40 -> 2.0137347

Sheet Intrinsic Growth
G2: 44621 | H2: 44986 | I2: 45352 | J2: 45717 | K2: 46082
B3: Calculation of ROIC
A5: # | B5: Current Assets
B6: Trade Receivables | G6: ='Infosys Raw FS'!J36 -> 22698 | H6: ='Infosys Raw FS'!K36 -> 25424 | I6: ='Infosys Raw FS'!L36 -> 30193 | J6: ='Infosys Raw FS'!M36 -> 31158 | K6: ='Infosys Raw FS'!N36 -> 35234
B7: Loans and Advances | G7: ='Infosys Raw FS'!C38 -> 399 | H7: ='Infosys Raw FS'!D38 -> 614 | I7: ='Infosys Raw FS'!E38 -> 844 | J7: ='Infosys Raw FS'!F38 -> 830 | K7: ='Infosys Raw FS'!G38 -> 1524
B8: Other Assets | G8: ='Infosys Raw FS'!C39 -> 11418 | H8: ='Infosys Raw FS'!D39 -> 14219 | I8: ='Infosys Raw FS'!E39 -> 15390 | J8: ='Infosys Raw FS'!F39 -> 19216 | K8: ='Infosys Raw FS'!G39 -> 19788
B9: Total Current Assets | G9: =SUM(G6:G8) -> 34515 | H9: =SUM(H6:H8) -> 40257 | I9: =SUM(I6:I8) -> 46427 | J9: =SUM(J6:J8) -> 51204 | K9: =SUM(K6:K8) -> 56546
A11: # | B11: Current Liabilities
B12: Non controlling Interest | G12: ='Infosys Raw FS'!J12 -> 386 | H12: ='Infosys Raw FS'!K12 -> 388 | I12: ='Infosys Raw FS'!L12 -> 345 | J12: ='Infosys Raw FS'!M12 -> 385 | K12: ='Infosys Raw FS'!N12 -> 445
B13: Trade Payables | G13: ='Infosys Raw FS'!J13 -> 4134 | H13: ='Infosys Raw FS'!K13 -> 3865 | I13: ='Infosys Raw FS'!L13 -> 3956 | J13: ='Infosys Raw FS'!M13 -> 4164 | K13: ='Infosys Raw FS'!N13 -> 4744
B14: Advance from Customers | G14: ='Infosys Raw FS'!J14 -> 0 | H14: ='Infosys Raw FS'!K14 -> 0 | I14: ='Infosys Raw FS'!L14 -> 0 | J14: ='Infosys Raw FS'!M14 -> 0 | K14: ='Infosys Raw FS'!N14 -> 0
B15: Other Liability Items | G15: ='Infosys Raw FS'!J15 -> 31385 | H15: ='Infosys Raw FS'!K15 -> 36637 | I15: ='Infosys Raw FS'!L15 -> 35244 | J15: ='Infosys Raw FS'!M15 -> 39201 | K15: ='Infosys Raw FS'!N15 -> 47071
B16: Total Current Liabilities | G16: =SUM(G12:G15) -> 35905 | H16: =SUM(H12:H15) -> 40890 | I16: =SUM(I12:I15) -> 39545 | J16: =SUM(J12:J15) -> 43750 | K16: =SUM(K12:K15) -> 52260
A18: # | B18: Net Working Capital | G18: =G9-G16 -> -1390 | H18: =H9-H16 -> -633 | I18: =I9-I16 -> 6882 | J18: =J9-J16 -> 7454 | K18: =K9-K16 -> 4286
B20: Non Current Assets
B21: ='Infosys Raw FS'!B19 -> Land | G21: ='Infosys Raw FS'!J19 -> 2066 | H21: ='Infosys Raw FS'!K19 -> 2054 | I21: ='Infosys Raw FS'!L19 -> 2037 | J21: ='Infosys Raw FS'!M19 -> 2079 | K21: ='Infosys Raw FS'!N19 -> 1990
B22: ='Infosys Raw FS'!B20 -> Building | G22: ='Infosys Raw FS'!J20 -> 16760 | H22: ='Infosys Raw FS'!K20 -> 16903 | I22: ='Infosys Raw FS'!L20 -> 16515 | J22: ='Infosys Raw FS'!M20 -> 16376 | K22: ='Infosys Raw FS'!N20 -> 17193
B23: ='Infosys Raw FS'!B21 -> Plant Machinery | G23: ='Infosys Raw FS'!J21 -> 3210 | H23: ='Infosys Raw FS'!K21 -> 3302 | I23: ='Infosys Raw FS'!L21 -> 3428 | J23: ='Infosys Raw FS'!M21 -> 3461 | K23: ='Infosys Raw FS'!N21 -> 3714
B24: ='Infosys Raw FS'!B22 -> Equipments | G24: ='Infosys Raw FS'!J22 -> 1427 | H24: ='Infosys Raw FS'!K22 -> 1482 | I24: ='Infosys Raw FS'!L22 -> 1528 | J24: ='Infosys Raw FS'!M22 -> 1628 | K24: ='Infosys Raw FS'!N22 -> 1732
B25: ='Infosys Raw FS'!B23 -> Computers | G25: ='Infosys Raw FS'!J23 -> 9936 | H25: ='Infosys Raw FS'!K23 -> 11898 | I25: ='Infosys Raw FS'!L23 -> 12353 | J25: ='Infosys Raw FS'!M23 -> 12925 | K25: ='Infosys Raw FS'!N23 -> 13600
B26: ='Infosys Raw FS'!B24 -> Furniture n fittings | G26: ='Infosys Raw FS'!J24 -> 2278 | H26: ='Infosys Raw FS'!K24 -> 2303 | I26: ='Infosys Raw FS'!L24 -> 2326 | J26: ='Infosys Raw FS'!M24 -> 2340 | K26: ='Infosys Raw FS'!N24 -> 2438
B27: ='Infosys Raw FS'!B25 -> Vehicles | G27: ='Infosys Raw FS'!J25 -> 71 | H27: ='Infosys Raw FS'!K25 -> 60 | I27: ='Infosys Raw FS'!L25 -> 62 | J27: ='Infosys Raw FS'!M25 -> 72 | K27: ='Infosys Raw FS'!N25 -> 70
B28: ='Infosys Raw FS'!B26 -> Intangible Assets | G28: ='Infosys Raw FS'!J26 -> 6495 | H28: ='Infosys Raw FS'!K26 -> 7594 | I28: ='Infosys Raw FS'!L26 -> 7652 | J28: ='Infosys Raw FS'!M26 -> 10626 | K28: ='Infosys Raw FS'!N26 -> 12729
B29: ='Infosys Raw FS'!B27 -> Other fixed assets | G29: ='Infosys Raw FS'!J27 -> 2766 | H29: ='Infosys Raw FS'!K27 -> 3281 | I29: ='Infosys Raw FS'!L27 -> 3294 | J29: ='Infosys Raw FS'!M27 -> 5184 | K29: ='Infosys Raw FS'!N27 -> 6296
B30: Gross Block | G30: =SUM(G21:G29) -> 45009 | H30: =SUM(H21:H29) -> 48877 | I30: =SUM(I21:I29) -> 49195 | J30: =SUM(J21:J29) -> 54691 | K30: =SUM(K21:K29) -> 59762
B31: Accumulated Depreciation | G31: ='Infosys Raw FS'!J29 -> -19209 | H31: ='Infosys Raw FS'!K29 -> -19652 | I31: ='Infosys Raw FS'!L29 -> -21573 | J31: ='Infosys Raw FS'!M29 -> -23730 | K31: ='Infosys Raw FS'!N29 -> -25992
B32: Net Non-Current Assets | G32: =SUM(G30:G31) -> 25800 | H32: =SUM(H30:H31) -> 29225 | I32: =SUM(I30:I31) -> 27622 | J32: =SUM(J30:J31) -> 30961 | K32: =SUM(K30:K31) -> 33770
A34: # | B34: Invested Capital | G34: ='Infosys Raw FS'!J32 -> 416 | H34: ='Infosys Raw FS'!K32 -> 288 | I34: ='Infosys Raw FS'!L32 -> 293 | J34: ='Infosys Raw FS'!M32 -> 814 | K34: ='Infosys Raw FS'!N32 -> 526
B35: EBIT | G35: ='Infosys Raw FS'!J33 -> 20324 | H35: ='Infosys Raw FS'!K33 -> 19478 | I35: ='Infosys Raw FS'!L33 -> 24623 | J35: ='Infosys Raw FS'!M33 -> 23541 | K35: ='Infosys Raw FS'!N33 -> 21880
B37: ROIC | G37: =G35/G34/100 -> 0.48855769 | H37: =H35/H34/100 -> 0.67631944 | I37: =I35/I34/100 -> 0.84037543 | J37: =J35/J34/100 -> 0.28920147 | K37: =K35/K34/100 -> 0.41596958
A40: # | B40: Calculation of Reinvestment Rate | G40: 44621 | H40: 44986 | I40: 45352 | J40: 45717 | K40: 46082
B42: Net Capex | G42: =-'Infosys Raw FS'!J63 -> 2161 | H42: =-'Infosys Raw FS'!K63 -> 2579 | I42: =-'Infosys Raw FS'!L63 -> 2201 | J42: =-'Infosys Raw FS'!M63 -> 2237 | K42: =-'Infosys Raw FS'!N63 -> 2727
B43: Change in Working Capital | H43: =H18-G18 -> 757 | I43: =I18-H18 -> 7515 | J43: =J18-I18 -> 572 | K43: =K18-J18 -> -3168
B45: EBIT | G45: =G35 -> 20324 | H45: =H35 -> 19478 | I45: =I35 -> 24623 | J45: =J35 -> 23541 | K45: =K35 -> 21880
B46: Marginal Tax Rate | G46: 0.25 | H46: 0.25 | I46: 0.25 | J46: 0.25 | K46: 0.25
B47: EBIT(1-T) | G47: =G45*(1-G46) -> 15243 | H47: =H45*(1-H46) -> 14608.5 | I47: =I45*(1-I46) -> 18467.25 | J47: =J45*(1-J46) -> 17655.75 | K47: =K45*(1-K46) -> 16410
B49: Reinvestment | H49: =SUM(H42:H43) -> 3336 | I49: =SUM(I42:I43) -> 9716 | J49: =SUM(J42:J43) -> 2809 | K49: =SUM(K42:K43) -> -441
A51: # | B51: Reinvestment Rate | H51: =H49/H47 -> 0.2283602 | I51: =I49/I47 -> 0.52612056 | J51: =J49/J47 -> 0.15909831 | K51: =K49/K47 -> -0.026873857
J53: 4 Year Average | K53: =AVERAGE(H51:K51) -> 0.2216763
J54: 4 Year Median | K54: =MEDIAN(H51:K51) -> 0.19372926
A57: # | B57: Calculation of Growth Rate | G57: 44621 | H57: 44986 | I57: 45352 | J57: 45717 | K57: 46082
B59: Reinvestment Rate | H59: =H51 -> 0.2283602 | I59: =I51 -> 0.52612056 | J59: =J51 -> 0.15909831 | K59: =K51 -> -0.026873857
B60: ROIC | H60: =H37 -> 0.67631944 | I60: =I37 -> 0.84037543 | J60: =J37 -> 0.28920147 | K60: =K37 -> 0.41596958
B62: Intrinsic Growth | H62: =H59*H60 -> 0.15444444 | I62: =I59*I60 -> 0.44213879 | J62: =J59*J60 -> 0.046011466 | K62: =K59*K60 -> -0.011178707
J64: 4 Year Average | K64: =AVERAGE(H62:K62) -> 0.157854
J65: 4 Year Median | K65: =MEDIAN(H62:K62) -> 0.10022796

Sheet Infosys Raw FS
B2: INFOSYS LTD
B4: Particlualars | C4: 42064 | D4: 42430 | E4: 42795 | F4: 43160 | G4: 43525 | H4: 43891 | I4: 44256 | J4: 44621 | K4: 44986 | L4: 45352 | M4: 45717 | N4: 46082
B6: Equity and Liabilities -
B7: Equity Capital | C7: 572 | D7: 1144 | E7: 1144 | F7: 1088 | G7: 2170 | H7: 2122 | I7: 2124 | J7: 2098 | K7: 2069 | L7: 2071 | M7: 2073 | N7: 2024
B8: Reserves | C8: 50164 | D8: 60600 | E8: 67838 | F8: 63835 | G8: 62778 | H8: 63328 | I8: 74227 | J8: 73252 | K8: 73338 | L8: 86045 | M8: 93745 | N8: 90828
B9: Borrowings - | C9: 0 | D9: 0 | E9: 0 | F9: 0 | G9: 0 | H9: 4633 | I9: 5325 | J9: 5474 | K9: 8299 | L9: 8359 | M9: 8227 | N9: 9176
B10: Lease Liabilities | C10: 0 | D10: 0 | E10: 0 | F10: 0 | G10: 0 | H10: 4633 | I10: 5325 | J10: 5474 | K10: 8299 | L10: 8359 | M10: 8227 | N10: 9176
B11: Other Liabilities - | C11: 15553 | D11: 13354 | E11: 14166 | F11: 14426 | G11: 19118 | H11: 21717 | I11: 25835 | J11: 35905 | K11: 40890 | L11: 39545 | M11: 43750 | N11: 52260
B12: Non controlling int | C12: 0 | D12: 0 | E12: 0 | F12: 1 | G12: 58 | H12: 394 | I12: 431 | J12: 386 | K12: 388 | L12: 345 | M12: 385 | N12: 445
B13: Trade Payables | C13: 140 | D13: 386 | E13: 367 | F13: 694 | G13: 1655 | H13: 2852 | I13: 2645 | J13: 4134 | K13: 3865 | L13: 3956 | M13: 4164 | N13: 4744
B14: Advance from Customers | C14: 27 | D14: 28 | E14: 0 | F14: 0 | G14: 0 | H14: 0 | I14: 0 | J14: 0 | K14: 0 | L14: 0 | M14: 0 | N14: 0
B15: Other liability items | C15: 15386 | D15: 12940 | E15: 13799 | F15: 13731 | G15: 17405 | H15: 18471 | I15: 22759 | J15: 31385 | K15: 36637 | L15: 35244 | M15: 39201 | N15: 47071
B16: Total Liabilities | C16: 66289 | D16: 75098 | E16: 83148 | F16: 79349 | G16: 84066 | H16: 91800 | I16: 107511 | J16: 116729 | K16: 124596 | L16: 136020 | M16: 147795 | N16: 154288
B18: Fixed Assets -
B19: Land | C19: 1564 | D19: 1622 | E19: 1095 | F19: 1229 | G19: 1307 | H19: 1950 | I19: 2035 | J19: 2066 | K19: 2054 | L19: 2037 | M19: 2079 | N19: 1990
B20: Building | C20: 6102 | D20: 6325 | E20: 8419 | F20: 9334 | G20: 10270 | H20: 15104 | I20: 16394 | J20: 16760 | K20: 16903 | L20: 16515 | M20: 16376 | N20: 17193
B21: Plant Machinery | C21: 1427 | D21: 1759 | E21: 2048 | F21: 2306 | G21: 2709 | H21: 3185 | I21: 3296 | J21: 3210 | K21: 3302 | L21: 3428 | M21: 3461 | N21: 3714
B22: Equipments | C22: 676 | D22: 839 | E22: 922 | F22: 1002 | G22: 1101 | H22: 1265 | I22: 1371 | J22: 1427 | K22: 1482 | L22: 1528 | M22: 1628 | N22: 1732
B23: Computers | C23: 3347 | D23: 4486 | E23: 4945 | F23: 4903 | G23: 6287 | H23: 7423 | I23: 8732 | J23: 9936 | K23: 11898 | L23: 12353 | M23: 12925 | N23: 13600
B24: Furniture n fittings | C24: 958 | D24: 1444 | E24: 1277 | F24: 1393 | G24: 1620 | H24: 2073 | I24: 2149 | J24: 2278 | K24: 2303 | L24: 2326 | M24: 2340 | N24: 2438
B25: Vehicles | C25: 34 | D25: 29 | E25: 31 | F25: 31 | G25: 38 | H25: 69 | I25: 73 | J25: 71 | K25: 60 | L25: 62 | M25: 72 | N25: 70
B26: Intangible Assets | C26: 3637 | D26: 3858 | E26: 3743 | F26: 2237 | G26: 3640 | H26: 5528 | I26: 6373 | J26: 6495 | K26: 7594 | L26: 7652 | M26: 10626 | N26: 12729
B27: Other fixed assets | C27: 71 | D27: 931 | E27: 899 | F27: 545 | G27: 1093 | H27: 2289 | I27: 2730 | J27: 2766 | K27: 3281 | L27: 3294 | M27: 5184 | N27: 6296
B28: Gross Block | C28: 17816 | D28: 21293 | E28: 23379 | F28: 22980 | G28: 28065 | H28: 38886 | I28: 43153 | J28: 45009 | K28: 48877 | L28: 49195 | M28: 54691 | N28: 59762
B29: Accumulated Depreciation | C29: -6470 | D29: -7907 | E29: -9200 | F29: -10406 | G29: -12355 | H29: -15097 | I29: -17648 | J29: -19209 | K29: -19652 | L29: -21573 | M29: -23730 | N29: -25992
B30: Net Block | C30: =C28-C29 -> 24286 | D30: =D28-D29 -> 29200 | E30: =E28-E29 -> 32579 | F30: =F28-F29 -> 33386 | G30: =G28-G29 -> 40420 | H30: =H28-H29 -> 53983 | I30: =I28-I29 -> 60801 | J30: =J28-J29 -> 64218 | ... N30: =N28-N29 -> 85754
B32: CWIP | C32: 776 | D32: 960 | E32: 1365 | F32: 1606 | G32: 1388 | H32: 954 | I32: 922 | J32: 416 | K32: 288 | L32: 293 | M32: 814 | N32: 526
B33: Investments | C33: 2270 | D33: 1892 | E33: 16423 | F33: 12163 | G33: 11261 | H33: 8792 | I33: 14205 | J33: 20324 | K33: 19478 | L33: 24623 | M33: 23541 | N33: 21880
B35: Other Assets -
B36: Trade receivables | C36: 9713 | D36: 11330 | E36: 12322 | F36: 13142 | G36: 14827 | H36: 18487 | I36: 19294 | J36: 22698 | K36: 25424 | L36: 30193 | M36: 31158 | N36: 35234
B37: Cash Equivalents | C37: 30367 | D37: 32697 | E37: 22625 | F37: 19818 | G37: 19568 | H37: 18649 | I37: 24714 | J37: 17472 | K37: 12173 | L37: 14786 | M37: 24455 | N37: 22201
B38: Loans n Advances | C38: 399 | D38: 614 | E38: 844 | F38: 830 | G38: 1524 | H38: 1359 | I38: 1460 | J38: 2491 | K38: 3242 | L38: 10330 | M38: 6717 | N38: 6808
B39: Other asset items | C39: 11418 | D39: 14219 | E39: 15390 | F39: 19216 | G39: 19788 | H39: 19770 | I39: 21411 | J39: 27528 | K39: 34766 | L39: 28173 | M39: 30149 | N39: 33869
B40: Total Assets | C40: 66289 | D40: 75098 | E40: 83148 | F40: 79349 | G40: 84066 | H40: 91800 | I40: 107511 | J40: 116729 | K40: 124596 | L40: 136020 | M40: 147795 | N40: 154288
B42: Calculation Of EBIT
B44: Operating Profit | C44: 14883 | D44: 17079 | E44: 18604 | F44: 18822 | G44: 20170 | H44: 22267 | I44: 27889 | J44: 31491 | K44: 35130 | L44: 36425 | M44: 39236 | N44: 42280
B45: OPM % | C45: 0.28 | D45: 0.27 | E45: 0.27 | F45: 0.27 | G45: 0.24 | H45: 0.25 | I45: 0.28 | J45: 0.26 | K45: 0.24 | L45: 0.24 | M45: 0.24 | N45: 0.24
B46: Other Income + | C46: 3430 | D46: 3120 | E46: 3050 | F46: 3311 | G46: 2882 | H46: 2803 | I46: 2201 | J46: 2295 | K46: 2701 | L46: 4711 | M46: 3600 | N46: 3033
B47: Interest | C47: 12 | D47: 0 | E47: 0 | F47: 0 | G47: 0 | H47: 170 | I47: 195 | J47: 200 | K47: 284 | L47: 470 | M47: 416 | N47: 416
B48: Depreciation | C48: 1017 | D48: 1459 | E48: 1703 | F48: 1863 | G48: 2011 | H48: 2893 | I48: 3267 | J48: 3476 | K48: 4225 | L48: 4678 | M48: 4812 | N48: 4902
B49: Profit before tax | C49: 17284 | D49: 18740 | E49: 19951 | F49: 20270 | G49: 21041 | H49: 22007 | I49: 26628 | J49: 30110 | K49: 33322 | L49: 35988 | M49: 37608 | N49: 39995
B50: EBIT | C50: =C44-C48 -> 13866 | D50: =D44-D48 -> 15620 | E50: =E44-E48 -> 16901 | F50: =F44-F48 -> 16959 | G50: =G44-G48 -> 18159 | H50: =H44-H48 -> 19374 | I50: =I44-I48 -> 24622 | J50: =J44-J48 -> 28015 | ... N50: =N44-N48 -> 37378
B53: CASH FLOW STATEMENT
B54: Cash from Operating Activity - | C54: 8353 | D54: 10028 | E54: 11531 | F54: 13218 | G54: 14841 | H54: 17003 | I54: 23224 | J54: 23885 | K54: 22467 | L54: 25210 | M54: 35694 | N54: 33986
B55: Profit from operations | C55: 15946 | D55: 17839 | E55: 19340 | F55: 19963 | G55: 22126 | H55: 23920 | I55: 28845 | J55: 32921 | K55: 37605 | L55: 39523 | M55: 41591 | N55: 45273
B56: Receivables | C56: -1475 | D56: -1654 | E56: -1743 | F56: -1523 | G56: -2881 | H56: -3861 | I56: -1835 | J56: -7937 | K56: -7076 | L56: -2667 | M56: -1769 | N56: -5177
B57: Payables | C57: 0 | D57: 242 | E57: -19 | F57: 328 | G57: 916 | H57: -373 | I57: -245 | J57: 1489 | K57: -279 | L57: 91 | M57: 176 | N57: -26
B58: Loans Advances | C58: -221 | D58: -1134 | E58: 0 | F58: 0 | G58: 0 | H58: 0 | I58: -534 | J58: -1914 | K58: -3108 | L58: -1172 | M58: -1024 | N58: -2645
B59: Other WC items | C59: 854 | D59: 600 | E59: -394 | F59: 1279 | G59: 1512 | H59: 1867 | I59: 3382 | J59: 6938 | K59: 4119 | L59: -1334 | M59: 2322 | N59: 5209
B60: Working capital changes | C60: -842 | D60: -1946 | E60: -2156 | F60: 84 | G60: -453 | H60: -2367 | I60: 768 | J60: -1424 | K60: -6344 | L60: -5082 | M60: -295 | N60: -2639
B61: Direct taxes | C61: -6751 | D61: -5865 | E61: -5653 | F61: -6829 | G61: -6832 | H61: -4550 | I61: -6389 | J61: -7612 | K61: -8794 | L61: -9231 | M61: -5602 | N61: -8648
B62: Cash from Investing Activity - | C62: 999 | D62: -885 | E62: -14664 | F62: 4533 | G62: -632 | H62: -331 | I62: -7373 | J62: -6485 | K62: -1071 | L62: -5093 | M62: -1864 | N62: 3546
B63: Fixed assets purchased | C63: -2247 | D63: -2723 | E63: -2760 | F63: -1998 | G63: -2445 | H63: -3307 | I63: -2107 | J63: -2161 | K63: -2579 | L63: -2201 | M63: -2237 | N63: -2727
B64: Investments purchased | C64: -23923 | D64: -24577 | E64: -66410 | F64: -69159 | G64: -79410 | H64: -37482 | I64: -46738 | J64: -59951 | K64: -75800 | L64: -78092 | M64: -82742 | N64: -82617
B65: Investments sold | C65: 25253 | D65: 24980 | E65: 52048 | F65: 74003 | G65: 78098 | H65: 38861 | I65: 40381 | J65: 57356 | K65: 76722 | L65: 72930 | M65: 84877 | N65: 89699
... B78: Free Cash Flow | C78: 6106 | D78: 7305 | E78: 8771 | F78: 11220 | G78: 12396 | H78: 13696 | I78: 21117 | J78: 21724 | K78: 19888 | L78: 23009 | M78: 33457 | N78: 31259
B80: Source: Screener.in

Sheet Football Field Analysis>
K2: Football Field Analysis - Data
L3: Open Low | M3: Low | N3: Open High | O3: High
K4: Comps | L4: =M4 -> 2083.3277 | M4: ='Comps Value'!O33 -> 2083.3277 | N4: =O4 -> 1538.3758 | O4: ='Comps Value'!Q33 -> 1538.3758
K5: DCF Bear | L5: =M5 -> 334.42475 | M5: ='DCF>'!P23 -> 334.42475 | N5: =O5 -> 427.72148 | O5: ='DCF>'!P27 -> 427.72148
K6: DCF Base | L6: =M6 -> 427.99003 | M6: ='DCF>'!N23 -> 427.99003 | N6: =O6 -> 716.11981 | O6: ='DCF>'!N27 -> 716.11981
K7: DCF Bull | L7: =M7 -> 507.16809 | M7: ='DCF>'!M23 -> 507.16809 | N7: =O7 -> 1186.3895 | O7: ='DCF>'!M27 -> 1186.3895
K8: 52 Week H/L | L8: 982 | M8: 982 | N8: 1728 | O8: 1728
O16: `

Sheet Comps Value
B2: Amount in crores
B3: Comparable Company Valuation
D5: Market Data | K5: Financials | O5: Valuation
B6: Company | C6: Ticker | D6: Share Price | E6: Share Outsdanding | F6: Equity Value | G6: Net Debt | H6: Enterprise Value | K6: Revenue | L6: EBITDA | M6: Net income | O6: EV/Revenue | P6: EV/EBITDA | Q6: PE
A8: # | B8: ='Comps Data'!C5 -> TCS | C8: ` | D8: ='Comps Data'!D5 -> 2446.6 | E8: ='Comps Data'!E5 -> 361.81 | F8: =D8*E8 -> 885204.35 | G8: ='Comps Data'!I5 -> -1625 | H8: =F8+G8 -> 883579.35 | K8: ='Comps Data'!K5 -> 275859 | L8: ='Comps Data'!L5 -> 50055 | M8: ='Comps Data'!M5 -> 5560 | O8: =$H8/K8 -> 3.2030108 | P8: =$H8/L8 -> 17.65217 | Q8: =F8/M8 -> 159.20941
B9: ='Comps Data'!C6 -> Infosys | D9: ='Comps Data'!D6 -> 1155.6 | E9: ='Comps Data'!E6 -> 405.76 | F9: =D9*E9 -> 468896.26 | G9: ='Comps Data'!I6 -> -13464 | H9: =F9+G9 -> 455432.26 | K9: ='Comps Data'!K6 -> 184582 | L9: ='Comps Data'!L6 -> 30325 | M9: ='Comps Data'!M6 -> 4902 | O9: =$H9/K9 -> 2.4673709 | P9: =$H9/L9 -> 15.018376 | Q9: =F9/M9 -> 95.654071
B10: ='Comps Data'!C7 -> HCL Technologies | D10: ='Comps Data'!D7 -> 1344.3 | E10: ='Comps Data'!E7 -> 271.37 | F10: =D10*E10 -> 364802.69 | G10: ='Comps Data'!I7 -> -18210 | H10: =F10+G10 -> 346592.69 | K10: ='Comps Data'!K7 -> 134374 | L10: ='Comps Data'!L7 -> 17434 | M10: ='Comps Data'!M7 -> 4355 | O10: =$H10/K10 -> 2.5793136 | P10: =$H10/L10 -> 19.880274 | Q10: =F10/M10 -> 83.766404
B11: ='Comps Data'!C8 -> Wipro | D11: ='Comps Data'!D8 -> 183.61 | E11: ='Comps Data'!E8 -> 990.41 | F11: =D11*E11 -> 181849.18 | G11: ='Comps Data'!I8 -> 9735.5 | H11: =F11+G11 -> 191584.68 | K11: ='Comps Data'!K8 -> 94968 | L11: ='Comps Data'!L8 -> 13285.3 | M11: ='Comps Data'!M8 -> 2910.7 | O11: =$H11/K11 -> 2.0173604 | P11: =$H11/L11 -> 14.420802 | Q11: =F11/M11 -> 62.476099
B12: ='Comps Data'!C9 -> Tech Mahindra | D12: ='Comps Data'!D9 -> 1644.2 | E12: ='Comps Data'!E9 -> 98.01 | F12: =D12*E12 -> 161148.04 | G12: ='Comps Data'!I9 -> -2919.2 | H12: =F12+G12 -> 158228.84 | K12: ='Comps Data'!K9 -> 59176.1 | L12: ='Comps Data'!L9 -> 5163 | M12: ='Comps Data'!M9 -> 1881.6 | O12: =$H12/K12 -> 2.673864 | P12: =$H12/L12 -> 30.646686 | Q12: =F12/M12 -> 85.644155
B13: ='Comps Data'!C10 -> LTM | D13: ='Comps Data'!D10 -> 4422.7 | E13: ='Comps Data'!E10 -> 29.66 | F13: =D13*E13 -> 131177.28 | G13: ='Comps Data'!I10 -> -502.4 | H13: =F13+G13 -> 130674.88 | K13: ='Comps Data'!K10 -> 44075 | L13: ='Comps Data'!L10 -> 5196.7 | M13: ='Comps Data'!M10 -> 1054.1 | O13: =$H13/K13 -> 2.96483 | P13: =$H13/L13 -> 25.145743 | Q13: =F13/M13 -> 124.44482
B14: ='Comps Data'!C11 -> Persistent Systems | D14: ='Comps Data'!D11 -> 5483.3 | E14: ='Comps Data'!E11 -> 15.78 | F14: =D14*E14 -> 86526.474 | G14: ='Comps Data'!I11 -> -740.8 | H14: =F14+G14 -> 85785.674 | K14: ='Comps Data'!K11 -> 14748.45 | L14: ='Comps Data'!L11 -> 1865.12 | M14: ='Comps Data'!M11 -> 402.95 | O14: =$H14/K14 -> 5.8165891 | P14: =$H14/L14 -> 45.994721 | Q14: =F14/M14 -> 214.73253
B15: ='Comps Data'!C12 -> Coforge | D15: ='Comps Data'!D12 -> 1714.9 | E15: ='Comps Data'!E12 -> 44.27 | F15: =D15*E15 -> 75918.623 | G15: ='Comps Data'!I12 -> -371.4 | H15: =F15+G15 -> 75547.223 | K15: ='Comps Data'!K12 -> 18195.4 | L15: ='Comps Data'!L12 -> 1920 | M15: ='Comps Data'!M12 -> 681.9 | O15: =$H15/K15 -> 4.1519957 | P15: =$H15/L15 -> 39.347512 | Q15: =F15/M15 -> 111.33395
B16: ='Comps Data'!C13 -> Mphasis | D16: ='Comps Data'!D13 -> 2361.3 | E16: ='Comps Data'!E13 -> 19.09 | F16: =D16*E16 -> 45077.217 | G16: ='Comps Data'!I13 -> 866.97 | H16: =F16+G16 -> 45944.187 | K16: ='Comps Data'!K13 -> 16531.21 | L16: ='Comps Data'!L13 -> 1910.41 | M16: ='Comps Data'!M13 -> 555.27 | O16: =$H16/K16 -> 2.7792392 | P16: =$H16/L16 -> 24.049386 | Q16: =F16/M16 -> 81.180717
B17: ='Comps Data'!C14 -> Hexaware Tech. | D17: ='Comps Data'!D14 -> 618.3 | E17: ='Comps Data'!E14 -> 61.1 | F17: =D17*E17 -> 37778.13 | G17: ='Comps Data'!I14 -> -1299.5 | H17: =F17+G17 -> 36478.63 | K17: ='Comps Data'!K14 -> 14420 | L17: ='Comps Data'!L14 -> 1343.3 | M17: ='Comps Data'!M14 -> 361.3 | O17: =$H17/K17 -> 2.5297247 | P17: =$H17/L17 -> 27.155982 | Q17: =F17/M17 -> 104.56167
B19: High | O19: =MAX(O8:O17) -> 5.8165891 | P19: =MAX(P8:P17) -> 45.994721 | Q19: =MAX(Q8:Q17) -> 214.73253
B20: 75th Percentile | O20: =QUARTILE(O8:O17,3) -> 3.1434656 | P20: =QUARTILE(P8:P17,3) -> 29.77401 | Q20: =QUARTILE(Q8:Q17,3) -> 121.1671
B21: Average | O21: =AVERAGE(O8:O17) -> 3.1183298 | P21: =AVERAGE(P8:P17) -> 25.931165 | Q21: =AVERAGE(Q8:Q17) -> 112.30038
B22: Median | O22: =MEDIAN(O8:O17) -> 2.7265516 | P22: =MEDIAN(P8:P17) -> 24.597564 | Q22: =MEDIAN(Q8:Q17) -> 100.10787
B23: 25th Percentile | O23: =QUARTILE(O8:O17,1) -> 2.5421219 | P23: =QUARTILE(P8:P17,1) -> 18.209196 | Q23: =QUARTILE(Q8:Q17,1) -> 84.235842
B24: Low | O24: =MIN(O8:O17) -> 2.0173604 | P24: =MIN(P8:P17) -> 14.420802 | Q24: =MIN(Q8:Q17) -> 62.476099
A26: # | B26: Infosys Comparable Company Valuation | O26: EV/Revenue | P26: EV/EBITDA | Q26: PE
B28: Implied Enterprise Value | O28: =O22*K8 -> 752143.8 | P28: =P22*L8 -> 1231231.1 | Q28: =Q30+Q29 -> 554974.75
B29: Net Debt | O29: =$G$8 -> -1625 | P29: =$G$8 -> -1625 | Q29: =$G$8 -> -1625
B30: Implied Market Value | O30: =O28-O29 -> 753768.8 | P30: =P28-P29 -> 1232856.1 | Q30: =Q22*M8 -> 556599.75
B31: Shares Outstanding | O31: =$E$8 -> 361.81 | P31: =$E$8 -> 361.81 | Q31: =$E$8 -> 361.81
B33: Implied Value per share | O33: =O30/O31 -> 2083.3277 | P33: =P30/P31 -> 3407.4682 | Q33: =Q30/Q31 -> 1538.3758
B35: Source: The Valuation School and Screener.in
O36: =IF(O33>$D$9,"Undervalued","Overvalued") -> Undervalued | P36: =IF(P33>$D$9,"Undervalued","Overvalued") -> Undervalued | Q36: =IF(Q33>$D$9,"Undervalued","Overvalued") -> Undervalued

Sheet Comps Data
B2: DATA TABLE
B4: S.No. | C4: Name | D4: CMP Rs. | E4: No. Eq. Shares (Cr.) | F4: Market Cap | G4: Debt Rs.Cr. | H4: Cash End Rs.Cr. | I4: Net Debt | J4: EV | K4: Sales Rs.Cr. | L4: NP 12M Rs.Cr. | M4: Dep 12M Rs.Cr. | N4: EBITDA | O4: EBIT
B5: 1 | C5: TCS | D5: 2446.6 | E5: 361.81 | F5: =D5*E5 -> 885204.35 | G5: 11283 | H5: 12908 | I5: =G5-H5 -> -1625 | J5: 883749.85 | K5: 275859 | L5: 50055 | M5: 5560 | N5: =O5+M5 -> 78511 | O5: 72951
B6: 2 | C6: Infosys | D6: 1155.6 | E6: 405.76 | F6: =D6*E6 -> 468896.26 | G6: 8737 | H6: 22201 | I6: =G6-H6 -> -13464 | J6: 456050.99 | K6: 184582 | L6: 30325 | M6: 4902 | N6: =O6+M6 -> 47904 | O6: 43002
B7: 3 | C7: HCL Technologies | D7: 1344.3 | E7: 271.37 | F7: =D7*E7 -> 364802.69 | G7: 5215 | H7: 23425 | I7: =G7-H7 -> -18210 | J7: 346602.07 | K7: 134374 | L7: 17434 | M7: 4355 | N7: =O7+M7 -> 29076 | O7: 24721
B8: 4 | C8: Wipro | D8: 183.61 | E8: 990.41 | F8: =D8*E8 -> 181849.18 | G8: 20291 | H8: 10555.5 | I8: =G8-H8 -> 9735.5 | J8: 191615.96 | K8: 94968 | L8: 13285.3 | M8: 2910.7 | N8: =O8+M8 -> 21898.8 | O8: 18988.1
B9: 5 | C9: Tech Mahindra | D9: 1644.2 | E9: 98.01 | F9: =D9*E9 -> 161148.04 | G9: 2186.2 | H9: 5105.4 | I9: =G9-H9 -> -2919.2 | J9: 158282.64 | K9: 59176.1 | L9: 5163 | M9: 1881.6 | N9: =O9+M9 -> 9521.8 | O9: 7640.2
B10: 6 | C10: LTM | D10: 4422.7 | E10: 29.66 | F10: =D10*E10 -> 131177.28 | G10: 2310 | H10: 2812.4 | I10: =G10-H10 -> -502.4 | J10: 130704.66 | K10: 44075 | L10: 5196.7 | M10: 1054.1 | N10: =O10+M10 -> 8905.7 | O10: 7851.6
B11: 7 | C11: Persistent Systems | D11: 5483.3 | E11: 15.78 | F11: =D11*E11 -> 86526.474 | G11: 477.45 | H11: 1218.25 | I11: =G11-H11 -> -740.8 | J11: 85798.51 | K11: 14748.45 | L11: 1865.12 | M11: 402.95 | N11: =O11+M11 -> 2970.2 | O11: 2567.25
B12: 8 | C12: Coforge | D12: 1714.9 | E12: 44.27 | F12: =D12*E12 -> 75918.623 | G12: 727.8 | H12: 1099.2 | I12: =G12-H12 -> -371.4 | J12: 75543.16 | K12: 18195.4 | L12: 1920 | M12: 681.9 | N12: =O12+M12 -> 3416.6 | O12: 2734.7
B13: 9 | C13: Mphasis | D13: 2361.3 | E13: 19.09 | F13: =D13*E13 -> 45077.217 | G13: 2619.68 | H13: 1752.71 | I13: =G13-H13 -> 866.97 | J13: 45973.45 | K13: 16531.21 | L13: 1910.41 | M13: 555.27 | N13: =O13+M13 -> 3383.49 | O13: 2828.22
B14: 10 | C14: Hexaware Tech. | D14: 618.3 | E14: 61.1 | F14: =D14*E14 -> 37778.13 | G14: 683 | H14: 1982.5 | I14: =G14-H14 -> -1299.5 | J14: 36808.22 | K14: 14420 | L14: 1343.3 | M14: 361.3 | N14: =O14+M14 -> 2327.1 | O14: 1965.8
B16: Source: Screener.in

Sheet LBO 
B2: LBO
A4: x | B4: Assumptions
B6: Entry ($MM) | G6: Financials | L6: Capital Structure | N6: Amount | O6: Cost | Q6: Infosys is not an ideal LBO candidate, for several reasons:
B7: LTM EBITDA | E7: =J9 -> 42280 | G7: LTM Financials | L7: Bank Debt | N7: 4 | O7: 0.06
B8: EBITDA Multiple | E8: =E9/E7 -> 10.771813 | G8: Revenue | J8: =' Forecasted FS>'!I9 -> 178650 | L8: Senior Notes | N8: 2 | O8: 0.12 | Q8: Too large | R8: At 422,800 Cr ($50bn+), very few PE firms could finance this
B9: Enterprise Value | E9: ='Comps Value'!H9 -> 455432.26 | G9: EBITDA | J9: =' Forecasted FS>'!I21 -> 42280 | Q9: Net cash position : | R9: LBOs work best on companies with stable, debt-serviceable
B10: Existing Net Debt | E10: =' Forecasted FS>'!I54-' Forecasted FS>'!I66 -> -13025 | G10: D&A | J10: =' Forecasted FS>'!I27 -> 4902 | L10: For Reference | R10: cash flows and some existing leverage capacity. Infosys has
B11: Equity Value | E11: =E9-E10 -> 468457.26 | G11: Capex | J11: =' Forecasted FS>'!I85 -> -2727 | L11: IRR | O11: =O107 -> 0.11126657 | R11: negative net debt, meaning you are paying a premium for cash you don't need
G12: NWC | J12: =' Forecasted FS>'!I64 -> 35234 | Q12: Asset-light, low capex | R12: Good for cash generation but LBOs typically target companies with hard assets
B13: Fees & Expenses | E13: 50 | R13: that can be used as loan collateral. Banks are less comfortable lending against an
R14: IT services business
B15: Exit ($MM) | Q15: High payout ratio | R15: Infosys pays out ~73% of earnings as dividends, meaning less retained cash to
B16: EBITDA Multiple | E16: =E8 -> 10.771813 | R16: service new LBO debt
Q17: Debt burden post-close | R17: The model shows debt barely gets paid down over 5 years (total debt stays
R18: 253,968 Cr, because interest consumes a large portion of free cash flow at 6x leverage
A19: x | B19: Sources and Uses
B21: Sources | J21: Uses | Q21: What makes the returns look attractive (22.4% IRR)?
E22: Amount | F22: xEBITDA | G22: % Capital | M22: Amount | N22: xEBITDA | O22: % Capital
B23: =L7 -> Bank Debt | E23: =N7*$J$9 -> 169120 | F23: =IFERROR(E23/J9,0) -> 4 | G23: =IFERROR(E23/($E$25+$E$27),0) -> 0.37129877 | L23: Enterprise Value | M23: =E9 -> 455432.26 | N23: =J9/M23*100 -> 9.2834883 | O23: =M23/$M$25 -> 0.99989023 | P23: 1 | Q23: Purely driven by EBITDA growth (7% revenue growth + margin expansion) and multiple arbitrage staying flat at 10x
B24: =L8 -> Senior Notes | E24: =N8*$J$9 -> 84560 | F24: =IFERROR(E24/J9,0) -> 2 | G24: =IFERROR(E24/($E$25+$E$27),0) -> 0.18564938 | L24: Fees & Expenses | M24: =E13 -> 50 | N24: 0 | O24: =M24/$M$25 -> 0.00010977376 | P24: 2 | Q24: If exit multiple compresses to 8x (common in IT sector re-ratings), IRR drops significantly
B25: Total Debt | E25: =SUM(E23:E24) -> 253680 | F25: =IFERROR(E25/J9,0) -> 6 | G25: =IFERROR(E25/($E$25+$E$27),0) -> 0.55694815 | L25: Total Uses | M25: =SUM(M23:M24) -> 455482.26 | N25: =SUM(N23:N24) -> 9.2834883 | O25: =M25/$M$25 -> 1 | P25: 3 | Q25: The return is not really coming from debt paydown (the traditional LBO value driver) which is a weakness
P26: 4 | Q26: Interest on Senior Notes (12%) is being capitalised (PIK'd) rather than paid in cash, the balance grows from ₹84,560 Cr
B27: Sponsor Equity | E27: =E9+E13-E25 -> 201802.26 | F27: =IFERROR(E27/J9,0) -> 4.7729956 | G27: =IFERROR(E27/($E$25+$E$27),0) -> 0.44305185 | Q27: at entry to ₹149,023 Cr at exit. In a real transaction, senior notes would either be cash-pay or explicitly structured as
Q28: PIK with lender consent. This is a modelling simplification; in practice, the additional interest burden would further reduce
B29: Total Sources | E29: =SUM(E25:E28) -> 455482.26 | F29: =IFERROR(E29/J9,0) -> 10.772996 | G29: =SUM(G25:G28) -> 1 | Q29: bank debt paydown capacity and compress IRR.
A32: x | B32: Financials
B35: Operating Model | J35: Year 0 | K35: Year 1 | L35: Year 2 | M35: Year 3 | N35: Year 4 | O35: Year 5
B36: Revenue | J36: =J8 -> 178650 | K36: =' Forecasted FS>'!I9 -> 178650 | L36: =' Forecasted FS>'!J9 -> 196517.57 | M36: =' Forecasted FS>'!K9 -> 211540.5 | N36: =' Forecasted FS>'!L9 -> 226563.43 | O36: =' Forecasted FS>'!M9 -> 241586.36
B37: % growth | J37: - | K37: =IFERROR(K36/J36-1,0) -> 0 | L37: =IFERROR(L36/K36-1,0) -> 0.10001439 | M37: =IFERROR(M36/L36-1,0) -> 0.076445727 | N37: =IFERROR(N36/M36-1,0) -> 0.071016796 | O37: =IFERROR(O36/N36-1,0) -> 0.066307827
B39: EBITDA | J39: =J9 -> 42280 | K39: =' Forecasted FS>'!I21 -> 42280 | L39: =' Forecasted FS>'!J21 -> 46055 | M39: =' Forecasted FS>'!K21 -> 49185.964 | N39: =' Forecasted FS>'!L21 -> 52316.929 | O39: =' Forecasted FS>'!M21 -> 55447.893
B40: % sales | J40: =IFERROR(J9/J8,0) -> 0.23666387 | K40: =J40+$J$16 -> 0.23666387 | L40: =K40+$J$16 -> 0.23666387 | M40: =L40+$J$16 -> 0.23666387 | N40: =M40+$J$16 -> 0.23666387 | O40: =N40+$J$16 -> 0.23666387
B42: EBIT | J42: =J39-J57 -> 37378 | K42: =' Forecasted FS>'!I48 -> 37378 | L42: =' Forecasted FS>'!J48 -> 40544.714 | M42: =' Forecasted FS>'!K48 -> 43307.143 | N42: =' Forecasted FS>'!L48 -> 46069.571 | O42: =' Forecasted FS>'!M48 -> 48832
B43: % sales | J43: =IFERROR(J42/J36,0) -> 0.20922474 | K43: =IFERROR(K42/K36,0) -> 0.20922474 | L43: =IFERROR(L42/L36,0) -> 0.20631597 | M43: =IFERROR(M42/M36,0) -> 0.2047227 | N43: =IFERROR(N42/N36,0) -> 0.20334072 | O43: =IFERROR(O42/O36,0) -> 0.20213062
B45: Interest | J45: =0 -> 0 | K45: =K92 -> 20294.4 | L45: =L92 -> 20929.904 | M45: =M92 -> 21757.341 | N45: =N92 -> 22564.906 | O45: =O92 -> 23394.137
B47: EBT | J47: =J42-J45 -> 37378 | K47: =K42-K45 -> 17083.6 | L47: =L42-L45 -> 19614.81 | M47: =M42-M45 -> 21549.802 | N47: =N42-N45 -> 23504.665 | O47: =O42-O45 -> 25437.863
B48: % sales | J48: =IFERROR(J47/J36,0) -> 0.20922474 | K48: =IFERROR(K47/K36,0) -> 0.095626085 | L48: =IFERROR(L47/L36,0) -> 0.09981199 | M48: =IFERROR(M47/M36,0) -> 0.10187081 | N48: =IFERROR(N47/N36,0) -> 0.1037443 | O48: =IFERROR(O47/O36,0) -> 0.10529512
B50: Taxes | J50: =J47*J17 -> 0 | K50: =K47*K51 -> 4862.7389 | L50: =L47*L51 -> 5978.7608 | M50: =M47*M51 -> 6593.8922 | N50: =N47*N51 -> 7216.3809 | O50: =O47*O51 -> 7833.2786
B51: % tax rate | J51: =J17 -> 0 | K51: =' Forecasted FS>'!I34 -> 0.28464369 | L51: =' Forecasted FS>'!J34 -> 0.3048085 | M51: =' Forecasted FS>'!K34 -> 0.30598389 | N51: =' Forecasted FS>'!L34 -> 0.30701909 | O51: =' Forecasted FS>'!M34 -> 0.30793776
B53: Net Income | J53: =J47-J50 -> 37378 | K53: =K47-K50 -> 12220.861 | L53: =L47-L50 -> 13636.049 | M53: =M47-M50 -> 14955.909 | N53: =N47-N50 -> 16288.284 | O53: =O47-O50 -> 17604.585
B54: % sales | J54: =IFERROR(J53/J36,0) -> 0.20922474 | K54: =IFERROR(K53/K36,0) -> 0.068406723 | L54: =IFERROR(L53/L36,0) -> 0.069388447 | M54: =IFERROR(M53/M36,0) -> 0.070699981 | N54: =IFERROR(N53/N36,0) -> 0.071892823 | O54: =IFERROR(O53/O36,0) -> 0.072870774
A56: x | B56: Cash flow Items | J56: Year 0 | K56: Year 1 | L56: Year 2 | M56: Year 3 | N56: Year 4 | O56: Year 5
B57: D&A | J57: =J10 -> 4902 | K57: =K36*K58 -> 4902 | L57: =L36*L58 -> 5392.2706 | M57: =M36*M58 -> 5804.4866 | N57: =N36*N58 -> 6216.7026 | O57: =O36*O58 -> 6628.9187
B58: % sales | J58: =IFERROR(J10/J8,0) -> 0.027439127 | K58: =J58 -> 0.027439127 | L58: =J58 -> 0.027439127 | M58: =J58 -> 0.027439127 | N58: =J58 -> 0.027439127 | O58: =J58 -> 0.027439127
B60: Net Working Capital | J60: =J12 -> 35234 | K60: =K36*K61 -> 35234 | L60: =L36*L61 -> 38757.907 | M60: =M36*M61 -> 41720.784 | N60: =N36*N61 -> 44683.66 | O60: =O36*O61 -> 47646.536
B61: % sales | J61: =IFERROR(J12/J8,0) -> 0.19722362 | K61: =J61 -> 0.19722362 | L61: =J61 -> 0.19722362 | M61: =J61 -> 0.19722362 | N61: =J61 -> 0.19722362 | O61: =J61 -> 0.19722362
B62: Change in Net Working Capital | J62: =0 -> 0 | K62: =-(K60-J60) -> 0 | L62: =-(L60-K60) -> -3523.9071 | M62: =-(M60-L60) -> -2962.8764 | N62: =-(N60-M60) -> -2962.8764 | O62: =-(O60-N60) -> -2962.8764
B64: CapEx | J64: =-J11 -> 2727 | K64: =-K36*K65 -> 2727 | L64: =-L36*L65 -> 2999.7393 | M64: =-M36*M65 -> 3229.0565 | N64: =-N36*N65 -> 3458.3737 | O64: =-O36*O65 -> 3687.691
B65: % sales | J65: =IFERROR(J11/J8,0) -> -0.015264484 | K65: =J65 -> -0.015264484 | L65: =K65 -> -0.015264484 | M65: =L65 -> -0.015264484 | N65: =M65 -> -0.015264484 | O65: =N65 -> -0.015264484
A67: x | B67: Levered Cash Flow | J67: Year 0 | K67: Year 1 | L67: Year 2 | M67: Year 3 | N67: Year 4 | O67: Year 5
B68: Net Income | J68: =J53 -> 37378 | K68: =K53 -> 12220.861 | L68: =L53 -> 13636.049 | M68: =M53 -> 14955.909 | N68: =N53 -> 16288.284 | O68: =O53 -> 17604.585
B69: D&A | J69: =J57 -> 4902 | K69: =K57 -> 4902 | L69: =L57 -> 5392.2706 | M69: =M57 -> 5804.4866 | N69: =N57 -> 6216.7026 | O69: =O57 -> 6628.9187
B70: CapEx | J70: =J64 -> 2727 | K70: =K64 -> 2727 | L70: =L64 -> 2999.7393 | M70: =M64 -> 3229.0565 | N70: =N64 -> 3458.3737 | O70: =O64 -> 3687.691
B71: Change in NWC | J71: =J62 -> 0 | K71: =K62 -> 0 | L71: =L62 -> -3523.9071 | M71: =M62 -> -2962.8764 | N71: =N62 -> -2962.8764 | O71: =O62 -> -2962.8764
B72: Levered Cash Flow | J72: =SUM(J68:J71) -> 45007 | K72: =SUM(K68:K71) -> 19849.861 | L72: =SUM(L68:L71) -> 18504.152 | M72: =SUM(M68:M71) -> 21026.576 | N72: =SUM(N68:N71) -> 23000.484 | O72: =SUM(O68:O71) -> 24958.318
A75: x | B75: Debt Schedule
J77: Year 0 | K77: Year 1 | L77: Year 2 | M77: Year 3 | N77: Year 4 | O77: Year 5
B78: Bank Debt
B79: Beginning Balance | J79: =E23 -> 169120 | K79: =J82 -> 169120 | L79: =K82 -> 159417.34 | M79: =L82 -> 150478.23 | N79: =M82 -> 138480.35 | O79: =N82 -> 123788.68
B80: Interest | J80: =0 -> 0 | K80: =K79*$O$7 -> 10147.2 | L80: =L79*$O$7 -> 9565.0403 | M80: =M79*$O$7 -> 9028.6936 | N80: =N79*$O$7 -> 8308.8207 | O80: =O79*$O$7 -> 7427.3209
B81: Paydown | J81: =0 -> 0 | K81: =-MIN(K72,K79) -> -19849.861 | L81: =-MIN(L72,L79) -> -18504.152 | M81: =-MIN(M72,M79) -> -21026.576 | N81: =-MIN(N72,N79) -> -23000.484 | O81: =-MIN(O72,O79) -> -24958.318
B82: Ending Balance | J82: =J79 -> 169120 | K82: =MAX(K79+K80+K81,0) -> 159417.34 | L82: =MAX(L79+L80+L81,0) -> 150478.23 | M82: =MAX(M79+M80+M81,0) -> 138480.35 | N82: =MAX(N79+N80+N81,0) -> 123788.68 | O82: =MAX(O79+O80+O81,0) -> 106257.68
B84: Sr. Notes
B85: Beginning Balance | J85: =E24 -> 84560 | K85: =J88 -> 84560 | L85: =K88 -> 94707.2 | M85: =L88 -> 106072.06 | N85: =M88 -> 118800.71 | O85: =N88 -> 133056.8
B86: Interest | J86: =0 -> 0 | K86: =K85*$O$8 -> 10147.2 | L86: =L85*$O$8 -> 11364.864 | M86: =M85*$O$8 -> 12728.648 | N86: =N85*$O$8 -> 14256.085 | O86: =O85*$O$8 -> 15966.816
B87: Paydown | J87: =0 -> 0 | K87: =-MIN(MAX(K72+K81,0),K85) -> 0 | L87: =-MIN(MAX(L72+L81,0),L85) -> 0 | M87: =-MIN(MAX(M72+M81,0),M85) -> 0 | N87: =-MIN(MAX(N72+N81,0),N85) -> 0 | O87: =-MIN(MAX(O72+O81,0),O85) -> 0
B88: Ending Balance | J88: =J85 -> 84560 | K88: =MAX(K85+K86+K87,0) -> 94707.2 | L88: =MAX(L85+L86+L87,0) -> 106072.06 | M88: =MAX(M85+M86+M87,0) -> 118800.71 | N88: =MAX(N85+N86+N87,0) -> 133056.8 | O88: =MAX(O85+O86+O87,0) -> 149023.61
B90: Total Debt
B91: Beginning Balance | J91: =J79+J85 -> 253680 | K91: =K79+K85 -> 253680 | L91: =L79+L85 -> 254124.54 | M91: =M79+M85 -> 256550.29 | N91: =N79+N85 -> 257281.06 | O91: =O79+O85 -> 256845.48
B92: Interest | J92: =J80+J86 -> 0 | K92: =K80+K86 -> 20294.4 | L92: =L80+L86 -> 20929.904 | M92: =M80+M86 -> 21757.341 | N92: =N80+N86 -> 22564.906 | O92: =O80+O86 -> 23394.137
B93: Paydown | J93: =J81+J87 -> 0 | K93: =K81+K87 -> -19849.861 | L93: =L81+L87 -> -18504.152 | M93: =M81+M87 -> -21026.576 | N93: =N81+N87 -> -23000.484 | O93: =O81+O87 -> -24958.318
B94: Ending Balance | J94: =J82+J88 -> 253680 | K94: =K82+K88 -> 254124.54 | L94: =L82+L88 -> 256550.29 | M94: =M82+M88 -> 257281.06 | N94: =N82+N88 -> 256845.48 | O94: =O82+O88 -> 255281.3
A96: x | B96: IRR
B98: EBITDA at Exit | O98: =O39 -> 55447.893
B99: Exit Multiple | O99: =E16 -> 10.771813
B100: Enterprise Value | O100: =O98*O99 -> 597274.34
B101: Net Debt | O101: =O94 -> 255281.3
B102: Sponsor Equity Value | O102: =O100-O101 -> 341993.04
B104: Sponsor Equity at Entry | O104: =E27 -> 201802.26
B106: MOIC | O106: =IFERROR(O102/O104,0) -> 1.6946938
A107: x | B107: IRR | O107: =IFERROR(O106^(1/5)-1,0) -> 0.11126657
